Workbook
Name _00_ANOS_FIN: '[1]Lista desplegableGeneral'!$B$3:$B$16
Name _00_ANOS_INICIO_: '[1]Lista desplegableGeneral'!$A$3:$A$13
Name _00_CAT_GASTO: '[1]Lista desplegableGeneral'!$H$3:$H$5
Name _00_ESPECIFICA_DETALLE_GASTO: '[1]Lista desplegableGeneral'!$M$3:$M$475
Name _00_ESPECIFICA_GASTO: '[1]Lista desplegableGeneral'!$L$3:$L$170
Name _00_FUENTE_FINAC: '[1]Lista desplegableGeneral'!$G$3:$G$7
Name _00_GENERICA_GASTO: '[1]Lista desplegableGeneral'!$I$3:$I$11
Name _00_SI_NO: '[1]Lista desplegableGeneral'!$F$3:$F$4
Name _00_SUBGENERICA_DETALLE_GASTO: '[1]Lista desplegableGeneral'!$K$3:$K$79
Name _00_SUBGENERICA_GASTO: '[1]Lista desplegableGeneral'!$J$3:$J$30
Name _01_SECTORES_GNGRGL: [1]listaDesplegableUE!$A$3:$C$34
Name _1._ORDEN_DE_COMPRA: '[1]Lista desplegableGeneral'!#REF!
Name _2._ORDEN_DE_SERVICIO: '[1]Lista desplegableGeneral'!#REF!
Name AA: [2]Hoja1!$A$1:$A$86
Name ACTIVIDAD_PRESUPUESTAL: [3]columnas!$A$2:$A$5
Name BASE: [4]INFORME!$A$3:$M$1002
Name BASE1: [4]INFORME!$A$4:$M$1048576
Name BATER: #REF!
Name BATER: #REF!
Name BATER: #REF!
Name BEJI: [5]DATA!$B$4:$C$26
Name BET: [6]Hoja9!$A$40:$B$70
Name buscar: #REF!
Name buscar: #REF!
Name buscar: #REF!
Name cabe: #REF!
Name cabe: #REF!
Name cabe: #REF!
Name CAMALEON: #REF!
Name CAMALEON: #REF!
Name CAMALEON: #REF!
Name cambiar: #REF!
Name cambiar: #REF!
Name cambiar: #REF!
Name cargo: [7]Enero!$A$5:$D$196
Name case: [8]poi!$A$1:$S$102
Name cave: #REF!
Name cave: #REF!
Name cave: #REF!
Name certif: #REF!
Name certif: #REF!
Name certif: #REF!
Name CLASIFI: #REF!
Name CLASIFI: #REF!
Name CLASIFI: #REF!
Name COLUMNA1_F1: [9]LISTA_NIVEL1!$A$21:$C$33
Name como: #REF!
Name como: #REF!
Name como: #REF!
Name costo: [10]Hoja4!$A$53:$B$103
Name dbidud: #REF!
Name dbidud: #REF!
Name dbidud: #REF!
Name dedos: #REF!
Name dedos: #REF!
Name dedos: #REF!
Name DESCRIPCION: [11]!PRESUPUESTO[[#All],[CLASIFICADOR]:[S1]]
Name EJECUTORAS_F3: #REF!
Name encuentra: #REF!
Name encuentra: #REF!

Sheet INICIO
E2: Programa de Empleo Temporal "LLAMKASUN PERÚ"
AL9: % de Avance (devengado)
O10: Ejecución PIM 2026 | Y10: CERTIFICACIONES Ejecución de CCPs
AQ16: =+PIM!Z24 -> 0.46310112
O23: ® UNIDAD FUNCIONAL DE PLANEAMIENTO Y PRESUPUESTO

Sheet PIM
M1: EJECUCIÓN PRESUPUESTAL 2025
AH2: Programa de Empleo Temporal "LLAMKASUN PERÚ"
GC3: PIM | GD3: =+M6 -> 452587256 | GG3: PIM | GH3: =+M6 -> 452587256
M4: PIM (S/) | AS4: EJEC. + PROY. MENSUAL
GC5: Poco avance | GD5: 80 | GE5: 0.98 | GG5: Muy bueno | GH5: 50 | GI5: 0.98
M6: =+SUBTOTAL(9,Tabla1[PIM]) -> 452587256 | GC6: avance regular | GD6: 17 | GE6: 0.96 | GG6: Buen avance | GH6: 40 | GI6: 0.95
AS7: ENE | AU7: =+DETALLE_PIM!AI1 -> 1423292.2 | GC7: Bueno | GD7: 2 | GE7: 0.95 | GG7: Avance regular | GH7: 7 | GI7: 0.85
AS8: FEB | AU8: =+DETALLE_PIM!AJ1 -> 1908012.2 | GC8: My bueno | GD8: 1 | GE8: 0.5 | GG8: Bajo avance | GH8: 3 | GI8: 0.5
AS9: MAR | AU9: =+DETALLE_PIM!AK1 -> 2592566.7 | GC9: TOTAL | GD9: =+SUM(GD5:GD8) -> 100 | GE9: 0 | GG9: TOTAL | GH9: =+SUM(GH5:GH8) -> 100 | GI9: 0
M10: CERTIFICADO (S/) | V10: % Avance (Certificación) | AJ10: PIM No Certificado (S/) | AS10: MAR' | AU10: =+DETALLE_PIM!AL1 -> 1.9663774e+08
AS11: ABR | AU11: =+DETALLE_PIM!AM1 -> 2150196.8 | GC11: CERT | GD11: =+M12 -> 4.4491515e+08 | GG11: dev | GH11: =+M21 -> 2.0959367e+08
M12: =+SUBTOTAL(9,Tabla1[CERTIFICADO]) -> 4.4491515e+08 | AJ12: =+DETALLE_PIM!U1-DETALLE_PIM!X1 -> 7672110.8 | AS12: MAY | AU12: =+DETALLE_PIM!AN1 -> 2409957.3 | GC12: % AVANCE | GD12: =+IFERROR(GD11/GD3,0) -> 0.98304833 | GG12: % AVANCE | GH12: =+IFERROR(GH11/GH3,0) -> 0.46310112
AS13: JUN | AU13: =+DETALLE_PIM!AO1 -> 2472710.9
M14: COMP. ANUAL (S/) | AS14: JUL | AU14: =+DETALLE_PIM!AP1 -> 171124.46 | GC14: Grados | GD14: =+GD12*PI() -> 3.0883374 | GG14: Grados | GH14: =+GH12*PI() -> 1.4548751
M15: =+SUBTOTAL(9,Tabla1[COMP. ANUAL]) -> 2.2238882e+08 | Z15: =+GD12 -> 0.98304833 | AS15: AGO | AU15: =+DETALLE_PIM!AQ1 -> 53719157
M16: CERT - COMP. ANUAL | AS16: SET | AU16: =+DETALLE_PIM!AR1 -> 1.7352122e+08
M17: =+M12-M15 -> 2.2252632e+08 | AS17: OCT | AU17: =+DETALLE_PIM!AS1 -> 7329009.3 | GD17: X | GE17: Y | GH17: X | GI17: Y
AS18: NOV | AU18: =+DETALLE_PIM!AT1 -> 2216583.5 | GC18: Inicial | GD18: 0 | GE18: 0 | GG18: Inicial | GH18: 0 | GI18: 0
M19: DEVENGADO (S/) | V19: % de Avance (devengado) | AJ19: PIM por DEVENGAR (S/) | AS19: DIC | AU19: =+DETALLE_PIM!AU1 -> 6035690.4 | GC19: Final | GD19: =COS(GD14)*-1 -> 0.99858227 | GE19: =+SIN(GD14) -> 0.053230079 | GG19: Final | GH19: =COS(GH14)*-1 -> -0.1156618 | GI19: =+SIN(GH14) -> 0.99328865
M21: =+SUBTOTAL(9,Tabla1[DEVENGADO2]) -> 2.0959367e+08 | AJ21: =+M6-M21 -> 2.4299359e+08 | AS21: EJEC. PROYECTADA
AS22: =+DETALLE_PIM!AV1 -> 452587256
Z24: =+GH12 -> 0.46310112 | AS24: SALDO PROYECTADO
AS25: =+DETALLE_PIM!AW1 -> 0
AS26: PIM no DEVENGADO
A27: ® UFPP-2025 | M27: ® Unidad Funcional de Planeamiento y Presupuesto-2025 | AS27: =+M6-M15 -> 2.3019843e+08
GD28: =+#REF!+1 -> #REF! | GF28: =+#REF!+1 -> #REF! | GH28: =+GF28/#REF! -> #REF! | GJ28: LABORABLE | GL28: JUEVES
GD29: =+GD28+1 -> #REF! | GF29: =+GF28+1 -> #REF! | GH29: =+GF29/#REF! -> #REF! | GJ29: LABORABLE | GL29: VIERNES
GD30: =+GD29+1 -> #REF! | GF30: =+GF29+1 -> #REF! | GH30: =+GF30/#REF! -> #REF! | GJ30: LABORABLE | GL30: SÁBADO
GD31: =+GD30+1 -> #REF! | GF31: =+GF30+1 -> #REF! | GH31: =+GF31/#REF! -> #REF! | GJ31: LABORABLE | GL31: DOMINGO
GD32: =+GD31+1 -> #REF! | GF32: =+GF31+1 -> #REF! | GH32: =+GF32/#REF! -> #REF! | GJ32: LABORABLE | GL32: LUNES
GD33: =+GD32+1 -> #REF! | GF33: =+GF32+1 -> #REF! | GH33: =+GF33/#REF! -> #REF! | GJ33: LABORABLE | GL33: MARTES
GD34: =+GD33+1 -> #REF! | GF34: =+GF33+1 -> #REF! | GH34: =+GF34/#REF! -> #REF! | GJ34: LABORABLE | GL34: MIÉRCOLES
GD35: =+GD34+1 -> #REF! | GF35: =+GF34+1 -> #REF! | GH35: =+GF35/#REF! -> #REF! | GJ35: LABORABLE | GL35: JUEVES
GD36: =+GD35+1 -> #REF! | GF36: =+GF35+1 -> #REF! | GH36: =+GF36/#REF! -> #REF! | GJ36: LABORABLE | GL36: VIERNES
GD37: =+GD36+1 -> #REF! | GF37: =+GF36+1 -> #REF! | GH37: =+GF37/#REF! -> #REF! | GJ37: LABORABLE | GL37: SÁBADO
GD38: =+GD37+1 -> #REF! | GF38: =+GF37+1 -> #REF! | GH38: =+GF38/#REF! -> #REF! | GJ38: LABORABLE | GL38: DOMINGO
GD39: =+GD38+1 -> #REF! | GF39: =+GF38+1 -> #REF! | GH39: =+GF39/#REF! -> #REF! | GJ39: LABORABLE | GL39: LUNES
GD40: =+GD39+1 -> #REF! | GF40: =+GF39+1 -> #REF! | GH40: =+GF40/#REF! -> #REF! | GJ40: LABORABLE | GL40: MARTES
... GD131: =+GD130+1 -> #REF! | GF131: =+GF130+1 -> #REF! | GH131: =+GF131/#REF! -> #REF! | GJ131: LABORABLE | GL131: MARTES
AA132: 47616.35 | GD132: =+GD131+1 -> #REF! | GF132: =+GF131+1 -> #REF! | GH132: =+GF132/#REF! -> #REF! | GJ132: LABORABLE | GL132: MIÉRCOLES
GD133: =+GD132+1 -> #REF! | GF133: =+GF132+1 -> #REF! | GH133: =+GF133/#REF! -> #REF! | GJ133: LABORABLE | GL133: JUEVES
GD134: =+GD133+1 -> #REF! | GF134: =+GF133+1 -> #REF! | GH134: =+GF134/#REF! -> #REF! | GJ134: LABORABLE | GL134: VIERNES
GD135: =+GD134+1 -> #REF! | GF135: =+GF134+1 -> #REF! | GH135: =+GF135/#REF! -> #REF! | GJ135: LABORABLE | GL135: SÁBADO
GD136: =+GD135+1 -> #REF! | GF136: =+GF135+1 -> #REF! | GH136: =+GF136/#REF! -> #REF! | GJ136: LABORABLE | GL136: DOMINGO
GD137: =+GD136+1 -> #REF! | GF137: =+GF136+1 -> #REF! | GH137: =+GF137/#REF! -> #REF! | GJ137: LABORABLE | GL137: LUNES
GD138: =+GD137+1 -> #REF! | GF138: =+GF137+1 -> #REF! | GH138: =+GF138/#REF! -> #REF! | GJ138: LABORABLE | GL138: MARTES
GD139: =+GD138+1 -> #REF! | GF139: =+GF138+1 -> #REF! | GH139: =+GF139/#REF! -> #REF! | GJ139: LABORABLE | GL139: MIÉRCOLES
GD140: =+GD139+1 -> #REF! | GF140: =+GF139+1 -> #REF! | GH140: =+GF140/#REF! -> #REF! | GJ140: LABORABLE | GL140: JUEVES
GD141: =+GD140+1 -> #REF! | GF141: =+GF140+1 -> #REF! | GH141: =+GF141/#REF! -> #REF! | GJ141: LABORABLE | GL141: VIERNES
GD142: =+GD141+1 -> #REF! | GF142: =+GF141+1 -> #REF! | GH142: =+GF142/#REF! -> #REF! | GJ142: LABORABLE | GL142: SÁBADO
GD143: =+GD142+1 -> #REF! | GF143: =+GF142+1 -> #REF! | GH143: =+GF143/#REF! -> #REF! | GJ143: LABORABLE | GL143: DOMINGO
GD144: =+GD143+1 -> #REF! | GF144: =+GF143+1 -> #REF! | GH144: =+GF144/#REF! -> #REF! | GJ144: LABORABLE | GL144: LUNES
... GD381: =+GD380+1 -> #REF! | GF381: =+GF380+1 -> #REF! | GH381: =+GF381/#REF! -> #REF! | GJ381: NO LABORABLE | GL381: DOMINGO

Sheet DETALLE_PIM
A1: PRESUPUESTO 2026 - UE: 005 - PROGRAMA DE EMPLEO TEMPORAL "LLAMKASUN PERÚ" | L1: EJECUCIÓN Y PROYECCIÓN | T1: =+SUBTOTAL(9,T5:T822) -> 452488556 | U1: =+SUBTOTAL(9,U5:U822) -> 452587256 | X1: =+SUBTOTAL(9,X5:X822) -> 4.4491515e+08 | Y1: =+IFERROR(X1/U1,0) -> 0.98304833 | Z1: =+SUBTOTAL(9,Z5:Z822) -> 7672110.8 | AB1: =+SUBTOTAL(9,AB5:AB822) -> 2.2238882e+08 | AC1: =+SUBTOTAL(9,AC5:AC822) -> 2.3019843e+08 | AD1: =+SUBTOTAL(9,AD5:AD822) -> 2.1411364e+08 | AF1: =+SUBTOTAL(9,AF5:AF822) -> 2.0959367e+08 | AG1: =+IFERROR(AF1/U1,0) -> 0.46310112 | AH1: =+SUBTOTAL(9,AH5:AH822) -> 2.4299359e+08 | AI1: =+SUBTOTAL(9,AI5:AI822) -> 1423292.2 | AJ1: =+SUBTOTAL(9,AJ5:AJ822) -> 1908012.2 | AK1: =+SUBTOTAL(9,AK5:AK822) -> 2592566.7 | AL1: =+SUBTOTAL(9,AL5:AL822) -> 1.9663774e+08 | AM1: =+SUBTOTAL(9,AM5:AM822) -> 2150196.8 | AN1: =+SUBTOTAL(9,AN5:AN822) -> 2409957.3 | AO1: =+SUBTOTAL(9,AO5:AO822) -> 2472710.9 | ... AW1: =+SUBTOTAL(9,AW5:AW822) -> 0
Z2: =+AF2-Z1 -> -7672110.8
AI3: EJECUCIÓN | AP3: PROYECCIÓN DEL GASTO
A4: Prog. Pptal. | B4: fte. Fto. | C4: DISP. LEGAL | D4: PRODUCTO | E4: COD ACT_PPTAL | F4: FINALIDAD | G4: ACTIVIDAD OPERATIVA | H4: CONCEPTO DE GASTO 1 | I4: RESTRINGIDA | J4: OF NAC / UT /TRANSF | K4: CENTRO DE COSTO | L4: UF / UT/ | M4: SEC.FUN. | N4: Sec. Fun. (Meta Pptal.) | O4: NEMONICO | P4: GEN. DE GASTO | Q4: CLASIFICADOR3 | R4: CLASIFICADOR2 | S4: DESCRIPCION | T4: PIA | U4: PIM | V4: . | W4: Columna2 | X4: CERTIFICADO | Y4: % CERT | Z4: NO CERT | AA4: .3 | AB4: COMP. ANUAL | AC4: PIM sin COMP | AD4: COMPROMISO | AE4: .4 | AF4: DEVENGADO2 | AG4: % EJEC | AH4: CERT NO DEV | AI4: ENE | AJ4: FEB | AK4: MAR | AL4: ABR | AM4: MAY | AN4: JUN | AO4: JUL | AP4: JUL2 | AQ4: AGO | AR4: SET | AS4: OCT | AT4: NOV | AU4: DIC | AV4: TOTAL | AW4: SALDO / DEFICIT
A5: 0073.PROGRAMA PARA LA GENERACION DEL EMPLEO SOCIAL INCLUSIVO - TRABAJA PERU | B5: 00 | C5: 01. PIA 2026 | D5: 3000001.ACCIONES COMUNES | E5: 5000276.GESTION DEL PROGRAMA | F5: 0047173.GESTION DEL PROGRAMA | G5: AOI00106600144. GESTIÓN OPERATIVA - UT AMAZONAS | H5: CAS | I5: RESTRINGIDA | J5: UFAF | K5: UFAF | L5: UT AMAZONAS | M5: 0001. UT AMAZONAS | N5: 0001 | O5: UT AMAZONAS | P5: 5-21.PERSONAL Y OBLIGACIONES SOCIALES | Q5: 21 1 9 1 4. AGUINALDOS DE CONTRATO ADMINISTRATIVO DE SERVICIOS | R5: 21 1 9 1 4 | S5: AGUINALDOS DE CONTRATO ADMINISTRATIVO DE SERVICIOS | T5: 600 | U5: 600 | X5: 600 | Y5: =+IFERROR(X5/U5,0) -> 1 | Z5: =+U5-X5 -> 0 | AB5: 600 | AC5: 0 | AD5: 0 | AF5: 0 | AG5: =+IFERROR(AF5/U5,0) -> 0 | AH5: =+Tabla1[[#This Row],[PIM]]-Tabla1[[#This Row],[DEVENGADO2]] -> 600 | AI5: 0 | AJ5: 0 | AK5: 0 | AL5: 0 | AM5: 0 | AN5: 0 | AO5: 0 | AP5: 300 | AQ5: 0 | AR5: 0 | AS5: 0 | AT5: 0 | AU5: 300 | AV5: =+SUM(AI5:AU5) -> 600 | AW5: =+U5-AV5 -> 0
A6: 0073.PROGRAMA PARA LA GENERACION DEL EMPLEO SOCIAL INCLUSIVO - TRABAJA PERU | B6: 00 | C6: 01. PIA 2026 | D6: 3000001.ACCIONES COMUNES | E6: 5000276.GESTION DEL PROGRAMA | F6: 0047173.GESTION DEL PROGRAMA | G6: AOI00106600144. GESTIÓN OPERATIVA - UT AMAZONAS | H6: CAS | I6: RESTRINGIDA | J6: UFAF | K6: UFAF | L6: UT AMAZONAS | M6: 0001. UT AMAZONAS | N6: 0001 | O6: UT AMAZONAS | P6: 5-21.PERSONAL Y OBLIGACIONES SOCIALES | Q6: 21 113 1 1. CONTRATO ADMINISTRATIVO DE SERVICIOS - INDETERMINADO | R6: 21 113 1 1 | S6: CONTRATO ADMINISTRATIVO DE SERVICIOS - INDETERMINADO | T6: 33170 | U6: 34371 | X6: 34371 | Y6: =+IFERROR(X6/U6,0) -> 1 | Z6: =+U6-X6 -> 0 | AB6: 34371 | AC6: 0 | AD6: 20049.33 | AF6: 20049.33 | AG6: =+IFERROR(AF6/U6,0) -> 0.58332111 | AH6: =+Tabla1[[#This Row],[PIM]]-Tabla1[[#This Row],[DEVENGADO2]] -> 14321.67 | AI6: 2864.19 | AJ6: 2864.19 | AK6: 2864.19 | AL6: 2864.19 | AM6: 2864.19 | AN6: 2864.19 | AO6: 2864.19 | AP6: 0 | AQ6: 2764.19 | AR6: 2764.19 | AS6: 2764.19 | AT6: 2764.19 | AU6: 3264.91 | AV6: =+SUM(AI6:AU6) -> 34371 | AW6: =+U6-AV6 -> 0
A7: 0073.PROGRAMA PARA LA GENERACION DEL EMPLEO SOCIAL INCLUSIVO - TRABAJA PERU | B7: 00 | C7: 01. PIA 2026 | D7: 3000001.ACCIONES COMUNES | E7: 5000276.GESTION DEL PROGRAMA | F7: 0047173.GESTION DEL PROGRAMA | G7: AOI00106600144. GESTIÓN OPERATIVA - UT AMAZONAS | H7: CAS | I7: RESTRINGIDA | J7: UFAF | K7: UFAF | L7: UT AMAZONAS | M7: 0001. UT AMAZONAS | N7: 0001 | O7: UT AMAZONAS | P7: 5-21.PERSONAL Y OBLIGACIONES SOCIALES | Q7: 21 3 1 115. CONTRIBUCIONES A ESSALUD DE CONTRATO ADMINISTRATIVO DE SERVICIOS | R7: 21 3 1 115 | S7: CONTRIBUCIONES A ESSALUD DE CONTRATO ADMINISTRATIVO DE SERVICIOS | T7: 2760 | U7: 2673 | X7: 2673 | Y7: =+IFERROR(X7/U7,0) -> 1 | Z7: =+U7-X7 -> 0 | AB7: 2673 | AC7: 0 | AD7: 1559.25 | AF7: 1559.25 | AG7: =+IFERROR(AF7/U7,0) -> 0.58333333 | AH7: =+Tabla1[[#This Row],[PIM]]-Tabla1[[#This Row],[DEVENGADO2]] -> 1113.75 | AI7: 222.75 | AJ7: 222.75 | AK7: 222.75 | AL7: 222.75 | AM7: 222.75 | AN7: 222.75 | AO7: 222.75 | AP7: 0 | AQ7: 230 | AR7: 230 | AS7: 230 | AT7: 230 | AU7: 193.75 | AV7: =+SUM(AI7:AU7) -> 2673 | AW7: =+U7-AV7 -> 0
A8: 0073.PROGRAMA PARA LA GENERACION DEL EMPLEO SOCIAL INCLUSIVO - TRABAJA PERU | B8: 00 | C8: 01. PIA 2026 | D8: 3000001.ACCIONES COMUNES | E8: 5000276.GESTION DEL PROGRAMA | F8: 0047173.GESTION DEL PROGRAMA | G8: AOI00106600144. GESTIÓN OPERATIVA - UT AMAZONAS | H8: COMBUSTIBLE | I8: NO RESTRINGIDA | J8: UFAF | K8: UFAF | L8: UT AMAZONAS | M8: 0001. UT AMAZONAS | N8: 0001 | O8: UT AMAZONAS | P8: 5-23.BIENES Y SERVICIOS | Q8: 23 1 3 1 1. COMBUSTIBLES Y CARBURANTES | R8: 23 1 3 1 1 | S8: COMBUSTIBLES Y CARBURANTES | T8: 3750 | U8: 0 | X8: 0 | Y8: =+IFERROR(X8/U8,0) -> 0 | Z8: =+U8-X8 -> 0 | AB8: 0 | AC8: 0 | AD8: 0 | AF8: 0 | AG8: =+IFERROR(AF8/U8,0) -> 0 | AH8: =+Tabla1[[#This Row],[PIM]]-Tabla1[[#This Row],[DEVENGADO2]] -> 0 | AI8: 0 | AJ8: 0 | AK8: 0 | AL8: 0 | AM8: 0 | AN8: 0 | AO8: 0 | AP8: 0 | AQ8: 0 | AR8: 0 | AS8: 0 | AT8: 0 | AU8: 0 | AV8: =+SUM(AI8:AU8) -> 0 | AW8: =+U8-AV8 -> 0
A9: 0073.PROGRAMA PARA LA GENERACION DEL EMPLEO SOCIAL INCLUSIVO - TRABAJA PERU | B9: 00 | C9: 01. PIA 2026 | D9: 3000001.ACCIONES COMUNES | E9: 5000276.GESTION DEL PROGRAMA | F9: 0047173.GESTION DEL PROGRAMA | G9: AOI00106600144. GESTIÓN OPERATIVA - UT AMAZONAS | H9: OTROS BIENES | I9: NO RESTRINGIDA | J9: UFAF | K9: UFAF | L9: UT AMAZONAS | M9: 0001. UT AMAZONAS | N9: 0001 | O9: UT AMAZONAS | P9: 5-23.BIENES Y SERVICIOS | Q9: 23 1 59999. OTROS | R9: 23 1 59999 | S9: OTROS | T9: 0 | U9: 7900 | X9: 7900 | Y9: =+IFERROR(X9/U9,0) -> 1 | Z9: =+U9-X9 -> 0 | AB9: 7900 | AC9: 0 | AD9: 5106.4 | AF9: 5106.4 | AG9: =+IFERROR(AF9/U9,0) -> 0.64637975 | AH9: =+Tabla1[[#This Row],[PIM]]-Tabla1[[#This Row],[DEVENGADO2]] -> 2793.6 | AI9: 500 | AJ9: 0 | AK9: 95.8 | AL9: 1386.6 | AM9: 745 | AN9: 1386 | AO9: 993 | AP9: 0 | AQ9: 718.18182 | AR9: 718.18182 | AS9: 718.18182 | AT9: 639.05455 | AU9: 0 | AV9: =+SUM(AI9:AU9) -> 7900 | AW9: =+U9-AV9 -> 0
A10: 0073.PROGRAMA PARA LA GENERACION DEL EMPLEO SOCIAL INCLUSIVO - TRABAJA PERU | B10: 00 | C10: 01. PIA 2026 | D10: 3000001.ACCIONES COMUNES | E10: 5000276.GESTION DEL PROGRAMA | F10: 0047173.GESTION DEL PROGRAMA | G10: AOI00106600144. GESTIÓN OPERATIVA - UT AMAZONAS | H10: OTROS BIENES | I10: NO RESTRINGIDA | J10: UFAF | K10: UFAF | L10: UT AMAZONAS | M10: 0001. UT AMAZONAS | N10: 0001 | O10: UT AMAZONAS | P10: 5-23.BIENES Y SERVICIOS | Q10: 23 1 6 1 1. DE VEHICULOS | R10: 23 1 6 1 1 | S10: DE VEHICULOS | T10: 545 | U10: 0 | X10: 0 | Y10: =+IFERROR(X10/U10,0) -> 0 | Z10: =+U10-X10 -> 0 | AB10: 0 | AC10: 0 | AD10: 0 | AF10: 0 | AG10: =+IFERROR(AF10/U10,0) -> 0 | AH10: =+Tabla1[[#This Row],[PIM]]-Tabla1[[#This Row],[DEVENGADO2]] -> 0 | AI10: 0 | AJ10: 0 | AK10: 0 | AL10: 0 | AM10: 0 | AN10: 0 | AO10: 0 | AP10: 0 | AQ10: 0 | AR10: 0 | AS10: 0 | AT10: 0 | AU10: 0 | AV10: =+SUM(AI10:AU10) -> 0 | AW10: =+U10-AV10 -> 0
A11: 0073.PROGRAMA PARA LA GENERACION DEL EMPLEO SOCIAL INCLUSIVO - TRABAJA PERU | B11: 00 | C11: 01. PIA 2026 | D11: 3000001.ACCIONES COMUNES | E11: 5000276.GESTION DEL PROGRAMA | F11: 0047173.GESTION DEL PROGRAMA | G11: AOI00106600144. GESTIÓN OPERATIVA - UT AMAZONAS | H11: PASAJES Y VIATICOS | I11: NO RESTRINGIDA | J11: UFAF | K11: UFAF | L11: UT AMAZONAS | M11: 0001. UT AMAZONAS | N11: 0001 | O11: UT AMAZONAS | P11: 5-23.BIENES Y SERVICIOS | Q11: 23 2 1 2 1. PASAJES Y GASTOS DE TRANSPORTE | R11: 23 2 1 2 1 | S11: PASAJES Y GASTOS DE TRANSPORTE | T11: 2000 | U11: 4600 | X11: 4600 | Y11: =+IFERROR(X11/U11,0) -> 1 | Z11: =+U11-X11 -> 0 | AB11: 4600 | AC11: 0 | AD11: 4570 | AF11: 4570 | AG11: =+IFERROR(AF11/U11,0) -> 0.99347826 | AH11: =+Tabla1[[#This Row],[PIM]]-Tabla1[[#This Row],[DEVENGADO2]] -> 30 | AI11: 0 | AJ11: 2300 | AK11: 400 | AL11: 0 | AM11: 1550 | AN11: 0 | AO11: 320 | AP11: 0 | AQ11: 0 | AR11: 0 | AS11: 0 | AT11: 0 | AU11: 30 | AV11: =+SUM(AI11:AU11) -> 4600 | AW11: =+U11-AV11 -> 0
A12: 0073.PROGRAMA PARA LA GENERACION DEL EMPLEO SOCIAL INCLUSIVO - TRABAJA PERU | B12: 00 | C12: 01. PIA 2026 | D12: 3000001.ACCIONES COMUNES | E12: 5000276.GESTION DEL PROGRAMA | F12: 0047173.GESTION DEL PROGRAMA | G12: AOI00106600144. GESTIÓN OPERATIVA - UT AMAZONAS | H12: PASAJES Y VIATICOS | I12: NO RESTRINGIDA | J12: UFAF | K12: UFAF | L12: UT AMAZONAS | M12: 0001. UT AMAZONAS | N12: 0001 | O12: UT AMAZONAS | P12: 5-23.BIENES Y SERVICIOS | Q12: 23 2 1 2 2. VIATICOS Y ASIGNACIONES POR COMISION DE SERVICIO | R12: 23 2 1 2 2 | S12: VIATICOS Y ASIGNACIONES POR COMISION DE SERVICIO | T12: 0 | U12: 3700 | X12: 3700 | Y12: =+IFERROR(X12/U12,0) -> 1 | Z12: =+U12-X12 -> 0 | AB12: 3700 | AC12: 0 | AD12: 983 | AF12: 983 | AG12: =+IFERROR(AF12/U12,0) -> 0.26567568 | AH12: =+Tabla1[[#This Row],[PIM]]-Tabla1[[#This Row],[DEVENGADO2]] -> 2717 | AI12: 0 | AJ12: 290 | AK12: 70 | AL12: 65 | AM12: 493 | AN12: 65 | AO12: 0 | AP12: 336.36364 | AQ12: 336.36364 | AR12: 336.36364 | AS12: 336.36364 | AT12: 336.36364 | AU12: 1035.1818 | AV12: =+SUM(AI12:AU12) -> 3700 | AW12: =+U12-AV12 -> 0
A13: 0073.PROGRAMA PARA LA GENERACION DEL EMPLEO SOCIAL INCLUSIVO - TRABAJA PERU | B13: 00 | C13: 01. PIA 2026 | D13: 3000001.ACCIONES COMUNES | E13: 5000276.GESTION DEL PROGRAMA | F13: 0047173.GESTION DEL PROGRAMA | G13: AOI00106600144. GESTIÓN OPERATIVA - UT AMAZONAS | H13: OTROS SERVICIOS | I13: NO RESTRINGIDA | J13: UFAF | K13: UFAF | L13: UT AMAZONAS | M13: 0001. UT AMAZONAS | N13: 0001 | O13: UT AMAZONAS | P13: 5-23.BIENES Y SERVICIOS | Q13: 23 2 1 299. OTROS GASTOS | R13: 23 2 1 299 | S13: OTROS GASTOS | T13: 0 | U13: 100 | X13: 100 | Y13: =+IFERROR(X13/U13,0) -> 1 | Z13: =+U13-X13 -> 0 | AB13: 100 | AC13: 0 | AD13: 26.1 | AF13: 26.1 | AG13: =+IFERROR(AF13/U13,0) -> 0.261 | AH13: =+Tabla1[[#This Row],[PIM]]-Tabla1[[#This Row],[DEVENGADO2]] -> 73.9 | AI13: 0 | AJ13: 0 | AK13: 0 | AL13: 0 | AM13: 8.7 | AN13: 8.7 | AO13: 8.7 | AP13: 0 | AQ13: 9.0909091 | AR13: 9.0909091 | AS13: 9.0909091 | AT13: 9.0909091 | AU13: 37.536364 | AV13: =+SUM(AI13:AU13) -> 100 | AW13: =+U13-AV13 -> 0
A14: 0073.PROGRAMA PARA LA GENERACION DEL EMPLEO SOCIAL INCLUSIVO - TRABAJA PERU | B14: 00 | C14: 01. PIA 2026 | D14: 3000001.ACCIONES COMUNES | E14: 5000276.GESTION DEL PROGRAMA | F14: 0047173.GESTION DEL PROGRAMA | G14: AOI00106600144. GESTIÓN OPERATIVA - UT AMAZONAS | H14: SERVICIOS DE LUZ, AGUA, INTERNET, TELF. FJA | I14: RESTRINGIDA | J14: UFAF | K14: UFAF | L14: UT AMAZONAS | M14: 0001. UT AMAZONAS | N14: 0001 | O14: UT AMAZONAS | P14: 5-23.BIENES Y SERVICIOS | Q14: 23 2 2 2 3. SERVICIO DE INTERNET | R14: 23 2 2 2 3 | S14: SERVICIO DE INTERNET | T14: 6000 | U14: 6000 | X14: 3150 | Y14: =+IFERROR(X14/U14,0) -> 0.525 | Z14: =+U14-X14 -> 2850 | AB14: 3150 | AC14: 2850 | AD14: 3150 | AF14: 3150 | AG14: =+IFERROR(AF14/U14,0) -> 0.525 | AH14: =+Tabla1[[#This Row],[PIM]]-Tabla1[[#This Row],[DEVENGADO2]] -> 2850 | AI14: 450 | AJ14: 450 | AK14: 450 | AL14: 450 | AM14: 450 | AN14: 450 | AO14: 450 | AP14: 0 | AQ14: 516.66667 | AR14: 516.66667 | AS14: 516.66667 | AT14: 516.66667 | AU14: 783.33333 | AV14: =+SUM(AI14:AU14) -> 6000 | AW14: =+U14-AV14 -> 0
A15: 0073.PROGRAMA PARA LA GENERACION DEL EMPLEO SOCIAL INCLUSIVO - TRABAJA PERU | B15: 00 | C15: 01. PIA 2026 | D15: 3000001.ACCIONES COMUNES | E15: 5000276.GESTION DEL PROGRAMA | F15: 0047173.GESTION DEL PROGRAMA | G15: AOI00106600144. GESTIÓN OPERATIVA - UT AMAZONAS | H15: SERVICIO DE MENSAJERIA | I15: NO RESTRINGIDA | J15: UFAF | K15: UFAF | L15: UT AMAZONAS | M15: 0001. UT AMAZONAS | N15: 0001 | O15: UT AMAZONAS | P15: 5-23.BIENES Y SERVICIOS | Q15: 23 2 2 3 1. CORREOS Y SERVICIOS DE MENSAJERIA | R15: 23 2 2 3 1 | S15: CORREOS Y SERVICIOS DE MENSAJERIA | T15: 0 | U15: 1600 | X15: 1600 | Y15: =+IFERROR(X15/U15,0) -> 1 | Z15: =+U15-X15 -> 0 | AB15: 1600 | AC15: 0 | AD15: 0 | AF15: 0 | AG15: =+IFERROR(AF15/U15,0) -> 0 | AH15: =+Tabla1[[#This Row],[PIM]]-Tabla1[[#This Row],[DEVENGADO2]] -> 1600 | AI15: 0 | AJ15: 0 | AK15: 0 | AL15: 0 | AM15: 0 | AN15: 0 | AO15: 0 | AP15: 145.45455 | AQ15: 145.45455 | AR15: 145.45455 | AS15: 145.45455 | AT15: 145.45455 | AU15: 872.72727 | AV15: =+SUM(AI15:AU15) -> 1600 | AW15: =+U15-AV15 -> 0
A16: 0073.PROGRAMA PARA LA GENERACION DEL EMPLEO SOCIAL INCLUSIVO - TRABAJA PERU | B16: 00 | C16: 01. PIA 2026 | D16: 3000001.ACCIONES COMUNES | E16: 5000276.GESTION DEL PROGRAMA | F16: 0047173.GESTION DEL PROGRAMA | G16: AOI00106600144. GESTIÓN OPERATIVA - UT AMAZONAS | H16: MANTENIMIENOT DE VEHICULOS | I16: NO RESTRINGIDA | J16: UFAF | K16: UFAF | L16: UT AMAZONAS | M16: 0001. UT AMAZONAS | N16: 0001 | O16: UT AMAZONAS | P16: 5-23.BIENES Y SERVICIOS | Q16: 23 2 4 5 1. DE VEHICULOS | R16: 23 2 4 5 1 | S16: DE VEHICULOS | T16: 8000 | U16: 520 | X16: 520 | Y16: =+IFERROR(X16/U16,0) -> 1 | Z16: =+U16-X16 -> 0 | AB16: 520 | AC16: 0 | AD16: 520 | AF16: 520 | AG16: =+IFERROR(AF16/U16,0) -> 1 | AH16: =+Tabla1[[#This Row],[PIM]]-Tabla1[[#This Row],[DEVENGADO2]] -> 0 | AI16: 0 | AJ16: 0 | AK16: 0 | AL16: 520 | AM16: 0 | AN16: 0 | AO16: 0 | AP16: 0 | AQ16: 0 | AR16: 0 | AS16: 0 | AT16: 0 | AU16: 0 | AV16: =+SUM(AI16:AU16) -> 520 | AW16: =+U16-AV16 -> 0
... A346: 0073.PROGRAMA PARA LA GENERACION DEL EMPLEO SOCIAL INCLUSIVO - TRABAJA PERU | B346: 00 | C346: 01. PIA 2026 | D346: 3000001.ACCIONES COMUNES | E346: 5000276.GESTION DEL PROGRAMA | F346: 0047173.GESTION DEL PROGRAMA | G346: AOI00106600086. PROGRAMACIÓN, FORMULACIÓN, APROBACIÓN, EJECUCIÓN Y EVALUACIÓN DEL PROCESO PRESUPUESTARIO DEL PROGRAMA | H346: SERVICIOS DIVERSOS | I346: RESTRINGIDA | J346: UFPP | K346: UFPP | L346: UFPP | M346: 0017. UFPP | N346: 0017 | O346: UFPP | P346: 5-23.BIENES Y SERVICIOS | Q346: 23 2 71199. SERVICIOS DIVERSOS | R346: 23 2 71199 | S346: SERVICIOS DIVERSOS | T346: 619300 | U346: 418922 | X346: 418922 | Y346: =+IFERROR(X346/U346,0) -> 1 | Z346: =+U346-X346 -> 0 | AB346: 418922 | AC346: 0 | AD346: 0 | AF346: 0 | AG346: =+IFERROR(AF346/U346,0) -> 0 | AH346: =+Tabla1[[#This Row],[PIM]]-Tabla1[[#This Row],[DEVENGADO2]] -> 418922 | AI346: 0 | AJ346: 0 | AK346: 0 | AL346: 0 | AM346: 0 | AN346: 0 | AO346: 0 | AP346: 0 | AQ346: 10000 | AR346: 0 | AS346: 0 | AT346: 0 | AU346: 408922 | AV346: =+SUM(AI346:AU346) -> 418922 | AW346: =+U346-AV346 -> 0
A347: 0073.PROGRAMA PARA LA GENERACION DEL EMPLEO SOCIAL INCLUSIVO - TRABAJA PERU | C347: 01. PIA 2026 | D347: 3000001.ACCIONES COMUNES | E347: 5000276.GESTION DEL PROGRAMA | F347: 0047173.GESTION DEL PROGRAMA | G347: AOI00106600086. PROGRAMACIÓN, FORMULACIÓN, APROBACIÓN, EJECUCIÓN Y EVALUACIÓN DEL PROCESO PRESUPUESTARIO DEL PROGRAMA | H347: LOCADORES | I347: NO RESTRINGIDA | J347: UFPP | K347: UFPP | L347: UFPP | M347: 0017. UFPP | N347: 0017 | O347: UFPP | P347: 5-23.BIENES Y SERVICIOS | Q347: 23 2 9 1 1. LOCACIÓN DE SERVICIOS REALIZADOS POR PERSONA NATURAL | R347: 23 2 9 1 1 | S347: LOCACIÓN DE SERVICIOS REALIZADOS POR PERSONA NATURAL | T347: 1106019 | U347: 24500 | X347: 24500 | Y347: =+IFERROR(X347/U347,0) -> 1 | Z347: =+U347-X347 -> 0 | AB347: 24500 | AC347: 0 | AD347: 24500 | AF347: 24500 | AG347: =+IFERROR(AF347/U347,0) -> 1 | AH347: =+Tabla1[[#This Row],[PIM]]-Tabla1[[#This Row],[DEVENGADO2]] -> 0 | AI347: 0 | AJ347: 0 | AK347: 12000 | AL347: 6000 | AM347: 0 | AN347: 6500 | AO347: 0 | AP347: 0 | AQ347: 0 | AR347: 0 | AS347: 0 | AT347: 0 | AU347: 0 | AV347: =+SUM(AI347:AU347) -> 24500 | AW347: =+U347-AV347 -> 0
A348: 0073.PROGRAMA PARA LA GENERACION DEL EMPLEO SOCIAL INCLUSIVO - TRABAJA PERU | B348: 00 | C348: 01. PIA 2026 | D348: 3000001.ACCIONES COMUNES | E348: 5000276.GESTION DEL PROGRAMA | F348: 0047173.GESTION DEL PROGRAMA | G348: AOI00106600086. PROGRAMACIÓN, FORMULACIÓN, APROBACIÓN, EJECUCIÓN Y EVALUACIÓN DEL PROCESO PRESUPUESTARIO DEL PROGRAMA | H348: FINANCIAMIENTO DE AII | I348: NO RESTRINGIDA | J348: UFPP | K348: UFPP | L348: UFPP | M348: 0017. UFPP | N348: 0017 | O348: UFPP | P348: 5-24.DONACIONES Y TRANSFERENCIAS | Q348: 24 1 3 1 3. A OTRAS UNIDADES DEL GOBIERNO LOCAL | R348: 24 1 3 1 3 | S348: A OTRAS UNIDADES DEL GOBIERNO LOCAL | T348: 0 | U348: 2401572 | X348: 0 | Y348: =+IFERROR(X348/U348,0) -> 0 | Z348: =+U348-X348 -> 2401572 | AB348: 0 | AC348: 2401572 | AD348: 0 | AF348: 0 | AG348: =+IFERROR(AF348/U348,0) -> 0 | AH348: =+Tabla1[[#This Row],[PIM]]-Tabla1[[#This Row],[DEVENGADO2]] -> 2401572 | AI348: 0 | AJ348: 0 | AK348: 0 | AL348: 0 | AM348: 0 | AN348: 0 | AO348: 0 | AP348: 0 | AQ348: 0 | AR348: 2401572 | AS348: 0 | AT348: 0 | AU348: 0 | AV348: =+SUM(AI348:AU348) -> 2401572 | AW348: =+U348-AV348 -> 0
A349: 0073.PROGRAMA PARA LA GENERACION DEL EMPLEO SOCIAL INCLUSIVO - TRABAJA PERU | B349: 00 | C349: 01. PIA 2026 | D349: 3000001.ACCIONES COMUNES | E349: 5000276.GESTION DEL PROGRAMA | F349: 0047173.GESTION DEL PROGRAMA | G349: AOI00106600093. PLANIFICACIÓN Y GESTIÓN ESTRATEGICA DE RECURSOS HUMANOS | H349: PERSONAL DL 728 | I349: RESTRINGIDA | J349: UFRH | K349: UFRH | L349: UFRH | M349: 0018. UFRH | N349: 0018 | O349: UFRH | P349: 5-21.PERSONAL Y OBLIGACIONES SOCIALES | Q349: 21 1 9 1 1. GRATIFICACIONES | R349: 21 1 9 1 1 | S349: GRATIFICACIONES | T349: 0 | U349: 80000 | X349: 80000 | Y349: =+IFERROR(X349/U349,0) -> 1 | Z349: =+U349-X349 -> 0 | AB349: 80000 | AC349: 0 | AD349: 66288.71 | AF349: 66288.71 | AG349: =+IFERROR(AF349/U349,0) -> 0.82860888 | AH349: =+Tabla1[[#This Row],[PIM]]-Tabla1[[#This Row],[DEVENGADO2]] -> 13711.29 | AI349: 0 | AJ349: 0 | AK349: 0 | AL349: 0 | AM349: 0 | AN349: 0 | AO349: 66288.71 | AP349: 0 | AQ349: 0 | AR349: 0 | AS349: 0 | AT349: 0 | AU349: 13711.29 | AV349: =+SUM(AI349:AU349) -> 80000 | AW349: =+U349-AV349 -> 0
A350: 0073.PROGRAMA PARA LA GENERACION DEL EMPLEO SOCIAL INCLUSIVO - TRABAJA PERU | B350: 00 | C350: 01. PIA 2026 | D350: 3000001.ACCIONES COMUNES | E350: 5000276.GESTION DEL PROGRAMA | F350: 0047173.GESTION DEL PROGRAMA | G350: AOI00106600093. PLANIFICACIÓN Y GESTIÓN ESTRATEGICA DE RECURSOS HUMANOS | H350: CAS | I350: RESTRINGIDA | J350: UFRH | K350: UFRH | L350: UFRH | M350: 0018. UFRH | N350: 0018 | O350: UFRH | P350: 5-21.PERSONAL Y OBLIGACIONES SOCIALES | Q350: 21 1 9 1 4. AGUINALDOS DE CONTRATO ADMINISTRATIVO DE SERVICIOS | R350: 21 1 9 1 4 | S350: AGUINALDOS DE CONTRATO ADMINISTRATIVO DE SERVICIOS | T350: 6600 | U350: 6300 | X350: 6300 | Y350: =+IFERROR(X350/U350,0) -> 1 | Z350: =+U350-X350 -> 0 | AB350: 6300 | AC350: 0 | AD350: 0 | AF350: 0 | AG350: =+IFERROR(AF350/U350,0) -> 0 | AH350: =+Tabla1[[#This Row],[PIM]]-Tabla1[[#This Row],[DEVENGADO2]] -> 6300 | AI350: 0 | AJ350: 0 | AK350: 0 | AL350: 0 | AM350: 0 | AN350: 0 | AO350: 0 | AP350: 3300 | AQ350: 0 | AR350: 0 | AS350: 0 | AT350: 0 | AU350: 3000 | AV350: =+SUM(AI350:AU350) -> 6300 | AW350: =+U350-AV350 -> 0
A351: 0073.PROGRAMA PARA LA GENERACION DEL EMPLEO SOCIAL INCLUSIVO - TRABAJA PERU | B351: 00 | C351: 01. PIA 2026 | D351: 3000001.ACCIONES COMUNES | E351: 5000276.GESTION DEL PROGRAMA | F351: 0047173.GESTION DEL PROGRAMA | G351: AOI00106600093. PLANIFICACIÓN Y GESTIÓN ESTRATEGICA DE RECURSOS HUMANOS | H351: CAS | I351: RESTRINGIDA | J351: UFRH | K351: UFRH | L351: UFRH | M351: 0018. UFRH | N351: 0018 | O351: UFRH | P351: 5-21.PERSONAL Y OBLIGACIONES SOCIALES | Q351: 21 1 9 314. OTROS BONOS EXTRAORDINARIOS PERSONAL CAS | R351: 21 1 9 314 | S351: OTROS BONOS EXTRAORDINARIOS PERSONAL CAS | T351: 0 | U351: 18700 | X351: 16900 | Y351: =+IFERROR(X351/U351,0) -> 0.90374332 | Z351: =+U351-X351 -> 1800 | AB351: 16900 | AC351: 1800 | AD351: 16900 | AF351: 16900 | AG351: =+IFERROR(AF351/U351,0) -> 0.90374332 | AH351: =+Tabla1[[#This Row],[PIM]]-Tabla1[[#This Row],[DEVENGADO2]] -> 1800 | AI351: 16500 | AJ351: 400 | AK351: 0 | AL351: 0 | AM351: 0 | AN351: 0 | AO351: 0 | AP351: 0 | AQ351: 0 | AR351: 0 | AS351: 0 | AT351: 0 | AU351: 1800 | AV351: =+SUM(AI351:AU351) -> 18700 | AW351: =+U351-AV351 -> 0
A352: 0073.PROGRAMA PARA LA GENERACION DEL EMPLEO SOCIAL INCLUSIVO - TRABAJA PERU | B352: 00 | C352: 01. PIA 2026 | D352: 3000001.ACCIONES COMUNES | E352: 5000276.GESTION DEL PROGRAMA | F352: 0047173.GESTION DEL PROGRAMA | G352: AOI00106600093. PLANIFICACIÓN Y GESTIÓN ESTRATEGICA DE RECURSOS HUMANOS | H352: CAS | I352: RESTRINGIDA | J352: UFRH | K352: UFRH | L352: UFRH | M352: 0018. UFRH | N352: 0018 | O352: UFRH | P352: 5-21.PERSONAL Y OBLIGACIONES SOCIALES | Q352: 21 113 1 1. CONTRATO ADMINISTRATIVO DE SERVICIOS - INDETERMINADO | R352: 21 113 1 1 | S352: CONTRATO ADMINISTRATIVO DE SERVICIOS - INDETERMINADO | T352: 387851 | U352: 374552 | X352: 374552 | Y352: =+IFERROR(X352/U352,0) -> 1 | Z352: =+U352-X352 -> 0 | AB352: 374552 | AC352: 0 | AD352: 210162.03 | AF352: 210162.03 | AG352: =+IFERROR(AF352/U352,0) -> 0.56110241 | AH352: =+Tabla1[[#This Row],[PIM]]-Tabla1[[#This Row],[DEVENGADO2]] -> 164389.97 | AI352: 13653.94 | AJ352: 32747.31 | AK352: 32762.17 | AL352: 32728.12 | AM352: 32772.57 | AN352: 32748.92 | AO352: 32749 | AP352: 0 | AQ352: 32320.95 | AR352: 32320.95 | AS352: 32320.95 | AT352: 32320.95 | AU352: 35106.17 | AV352: =+SUM(AI352:AU352) -> 374552 | AW352: =+U352-AV352 -> 0
A353: 0073.PROGRAMA PARA LA GENERACION DEL EMPLEO SOCIAL INCLUSIVO - TRABAJA PERU | B353: 00 | C353: 01. PIA 2026 | D353: 3000001.ACCIONES COMUNES | E353: 5000276.GESTION DEL PROGRAMA | F353: 0047173.GESTION DEL PROGRAMA | G353: AOI00106600093. PLANIFICACIÓN Y GESTIÓN ESTRATEGICA DE RECURSOS HUMANOS | H353: CAS | I353: RESTRINGIDA | J353: UFRH | K353: UFRH | L353: UFRH | M353: 0018. UFRH | N353: 0018 | O353: UFRH | P353: 5-21.PERSONAL Y OBLIGACIONES SOCIALES | Q353: 21 113 1 2. CONTRATO ADMINISTRATIVO DE SERVICIOS - TRANSITORIO | R353: 21 113 1 2 | S353: CONTRATO ADMINISTRATIVO DE SERVICIOS - TRANSITORIO | T353: 589077 | U353: 826737 | X353: 826737 | Y353: =+IFERROR(X353/U353,0) -> 1 | Z353: =+U353-X353 -> 0 | AB353: 826737 | AC353: 0 | AD353: 290890.44 | AF353: 290890.44 | AG353: =+IFERROR(AF353/U353,0) -> 0.35185366 | AH353: =+Tabla1[[#This Row],[PIM]]-Tabla1[[#This Row],[DEVENGADO2]] -> 535846.56 | AI353: 56612.3 | AJ353: 34312.95 | AK353: 34373.67 | AL353: 41482.11 | AM353: 41458.16 | AN353: 41382.43 | AO353: 41268.82 | AP353: 0 | AQ353: 49085.14 | AR353: 49085.14 | AS353: 49085.14 | AT353: 49085.14 | AU353: 339506 | AV353: =+SUM(AI353:AU353) -> 826737 | AW353: =+U353-AV353 -> 0
A354: 0073.PROGRAMA PARA LA GENERACION DEL EMPLEO SOCIAL INCLUSIVO - TRABAJA PERU | B354: 00 | C354: 01. PIA 2026 | D354: 3000001.ACCIONES COMUNES | E354: 5000276.GESTION DEL PROGRAMA | F354: 0047173.GESTION DEL PROGRAMA | G354: AOI00106600093. PLANIFICACIÓN Y GESTIÓN ESTRATEGICA DE RECURSOS HUMANOS | H354: CAS | I354: RESTRINGIDA | J354: UFRH | K354: UFRH | L354: UFRH | M354: 0018. UFRH | N354: 0018 | O354: UFRH | P354: 5-21.PERSONAL Y OBLIGACIONES SOCIALES | Q354: 21 3 1 115. CONTRIBUCIONES A ESSALUD DE CONTRATO ADMINISTRATIVO DE SERVICIOS | R354: 21 3 1 115 | S354: CONTRIBUCIONES A ESSALUD DE CONTRATO ADMINISTRATIVO DE SERVICIOS | T354: 30360 | U354: 34749 | X354: 34749 | Y354: =+IFERROR(X354/U354,0) -> 1 | Z354: =+U354-X354 -> 0 | AB354: 34749 | AC354: 0 | AD354: 15363.39 | AF354: 15363.39 | AG354: =+IFERROR(AF354/U354,0) -> 0.44212467 | AH354: =+Tabla1[[#This Row],[PIM]]-Tabla1[[#This Row],[DEVENGADO2]] -> 19385.61 | AI354: 2227.5 | AJ354: 2004.75 | AK354: 2004.75 | AL354: 2227.5 | AM354: 2227.5 | AN354: 2227.5 | AO354: 2443.89 | AP354: 0 | AQ354: 2530 | AR354: 2530 | AS354: 2530 | AT354: 2530 | AU354: 9265.61 | AV354: =+SUM(AI354:AU354) -> 34749 | AW354: =+U354-AV354 -> 0
A355: 0073.PROGRAMA PARA LA GENERACION DEL EMPLEO SOCIAL INCLUSIVO - TRABAJA PERU | B355: 00 | C355: 01. PIA 2026 | D355: 3000001.ACCIONES COMUNES | E355: 5000276.GESTION DEL PROGRAMA | F355: 0047173.GESTION DEL PROGRAMA | G355: AOI00106600093. PLANIFICACIÓN Y GESTIÓN ESTRATEGICA DE RECURSOS HUMANOS | H355: CAS | I355: NO RESTRINGIDA | J355: UFRH | K355: UFRH | L355: UFRH | M355: 0018. UFRH | N355: 0018 | O355: UFRH | P355: 5-21.PERSONAL Y OBLIGACIONES SOCIALES | Q355: 21 4 1 1 7. VACACIONES TRUNCAS PERSONAL CAS | R355: 21 4 1 1 7 | S355: VACACIONES TRUNCAS PERSONAL CAS | T355: 0 | U355: 14710 | X355: 14710 | Y355: =+IFERROR(X355/U355,0) -> 1 | Z355: =+U355-X355 -> 0 | AB355: 14710 | AC355: 0 | AD355: 14707.94 | AF355: 14707.94 | AG355: =+IFERROR(AF355/U355,0) -> 0.99985996 | AH355: =+Tabla1[[#This Row],[PIM]]-Tabla1[[#This Row],[DEVENGADO2]] -> 2.06 | AI355: 6550.99 | AJ355: 8156.95 | AK355: 0 | AL355: 0 | AM355: 0 | AN355: 0 | AO355: 0 | AP355: 0 | AQ355: 0 | AR355: 0 | AS355: 0 | AT355: 0 | AU355: 2.06 | AV355: =+SUM(AI355:AU355) -> 14710 | AW355: =+U355-AV355 -> 0
A356: 0073.PROGRAMA PARA LA GENERACION DEL EMPLEO SOCIAL INCLUSIVO - TRABAJA PERU | B356: 00 | C356: 01. PIA 2026 | D356: 3000001.ACCIONES COMUNES | E356: 5000276.GESTION DEL PROGRAMA | F356: 0047173.GESTION DEL PROGRAMA | G356: AOI00106600093. PLANIFICACIÓN Y GESTIÓN ESTRATEGICA DE RECURSOS HUMANOS | H356: AGUA DE MESA | I356: NO RESTRINGIDA | J356: UFRH | K356: UFRH | L356: UFRH | M356: 0018. UFRH | N356: 0018 | O356: UFRH | P356: 5-23.BIENES Y SERVICIOS | Q356: 23 1 1 1 1. ALIMENTOS Y BEBIDAS PARA CONSUMO HUMANO | R356: 23 1 1 1 1 | S356: ALIMENTOS Y BEBIDAS PARA CONSUMO HUMANO | T356: 1400 | U356: 1400 | X356: 0 | Y356: =+IFERROR(X356/U356,0) -> 0 | Z356: =+U356-X356 -> 1400 | AB356: 0 | AC356: 1400 | AD356: 0 | AF356: 0 | AG356: =+IFERROR(AF356/U356,0) -> 0 | AH356: =+Tabla1[[#This Row],[PIM]]-Tabla1[[#This Row],[DEVENGADO2]] -> 1400 | AI356: 0 | AJ356: 0 | AK356: 0 | AL356: 0 | AM356: 0 | AN356: 0 | AO356: 0 | AP356: 0 | AQ356: 0 | AR356: 0 | AS356: 0 | AT356: 0 | AU356: 1400 | AV356: =+SUM(AI356:AU356) -> 1400 | AW356: =+U356-AV356 -> 0
A357: 0073.PROGRAMA PARA LA GENERACION DEL EMPLEO SOCIAL INCLUSIVO - TRABAJA PERU | B357: 00 | C357: 01. PIA 2026 | D357: 3000001.ACCIONES COMUNES | E357: 5000276.GESTION DEL PROGRAMA | F357: 0047173.GESTION DEL PROGRAMA | G357: AOI00106600093. PLANIFICACIÓN Y GESTIÓN ESTRATEGICA DE RECURSOS HUMANOS | H357: VESTUARIO | I357: NO RESTRINGIDA | J357: UFRH | K357: UFRH | L357: UFRH | M357: 0018. UFRH | N357: 0018 | O357: UFRH | P357: 5-23.BIENES Y SERVICIOS | Q357: 23 1 2 1 1. VESTUARIO, ACCESORIOS Y PRENDAS DIVERSAS | R357: 23 1 2 1 1 | S357: VESTUARIO, ACCESORIOS Y PRENDAS DIVERSAS | T357: 8380 | U357: 0 | X357: 0 | Y357: =+IFERROR(X357/U357,0) -> 0 | Z357: =+U357-X357 -> 0 | AB357: 0 | AC357: 0 | AD357: 0 | AF357: 0 | AG357: =+IFERROR(AF357/U357,0) -> 0 | AH357: =+Tabla1[[#This Row],[PIM]]-Tabla1[[#This Row],[DEVENGADO2]] -> 0 | AI357: 0 | AJ357: 0 | AK357: 0 | AL357: 0 | AM357: 0 | AN357: 0 | AO357: 0 | AP357: 0 | AQ357: 0 | AR357: 0 | AS357: 0 | AT357: 0 | AU357: 0 | AV357: =+SUM(AI357:AU357) -> 0 | AW357: =+U357-AV357 -> 0
A358: 0073.PROGRAMA PARA LA GENERACION DEL EMPLEO SOCIAL INCLUSIVO - TRABAJA PERU | B358: 00 | C358: 01. PIA 2026 | D358: 3000001.ACCIONES COMUNES | E358: 5000276.GESTION DEL PROGRAMA | F358: 0047173.GESTION DEL PROGRAMA | G358: AOI00106600093. PLANIFICACIÓN Y GESTIÓN ESTRATEGICA DE RECURSOS HUMANOS | H358: OTROS BIENES | I358: NO RESTRINGIDA | J358: UFRH | K358: UFRH | L358: UFRH | M358: 0018. UFRH | N358: 0018 | O358: UFRH | P358: 5-23.BIENES Y SERVICIOS | Q358: 23 1 5 1 1. REPUESTOS Y ACCESORIOS | R358: 23 1 5 1 1 | S358: REPUESTOS Y ACCESORIOS | T358: 0 | U358: 0 | X358: 0 | Y358: =+IFERROR(X358/U358,0) -> 0 | Z358: =+U358-X358 -> 0 | AB358: 0 | AC358: 0 | AD358: 0 | AF358: 0 | AG358: =+IFERROR(AF358/U358,0) -> 0 | AH358: =+Tabla1[[#This Row],[PIM]]-Tabla1[[#This Row],[DEVENGADO2]] -> 0 | AI358: 0 | AJ358: 0 | AK358: 0 | AL358: 0 | AM358: 0 | AN358: 0 | AO358: 0 | AP358: 0 | AQ358: 0 | AR358: 0 | AS358: 0 | AT358: 0 | AU358: 0 | AV358: =+SUM(AI358:AU358) -> 0 | AW358: =+U358-AV358 -> 0
A359: 0073.PROGRAMA PARA LA GENERACION DEL EMPLEO SOCIAL INCLUSIVO - TRABAJA PERU | B359: 00 | C359: 01. PIA 2026 | D359: 3000001.ACCIONES COMUNES | E359: 5000276.GESTION DEL PROGRAMA | F359: 0047173.GESTION DEL PROGRAMA | G359: AOI00106600093. PLANIFICACIÓN Y GESTIÓN ESTRATEGICA DE RECURSOS HUMANOS | H359: OTROS BIENES | I359: NO RESTRINGIDA | J359: UFRH | K359: UFRH | L359: UFRH | M359: 0018. UFRH | N359: 0018 | O359: UFRH | P359: 5-23.BIENES Y SERVICIOS | Q359: 23 1 5 3 1. ASEO, LIMPIEZA Y TOCADOR | R359: 23 1 5 3 1 | S359: ASEO, LIMPIEZA Y TOCADOR | T359: 3240 | U359: 0 | X359: 0 | Y359: =+IFERROR(X359/U359,0) -> 0 | Z359: =+U359-X359 -> 0 | AB359: 0 | AC359: 0 | AD359: 0 | AF359: 0 | AG359: =+IFERROR(AF359/U359,0) -> 0 | AH359: =+Tabla1[[#This Row],[PIM]]-Tabla1[[#This Row],[DEVENGADO2]] -> 0 | AI359: 0 | AJ359: 0 | AK359: 0 | AL359: 0 | AM359: 0 | AN359: 0 | AO359: 0 | AP359: 0 | AQ359: 0 | AR359: 0 | AS359: 0 | AT359: 0 | AU359: 0 | AV359: =+SUM(AI359:AU359) -> 0 | AW359: =+U359-AV359 -> 0
... A510: 0073.PROGRAMA PARA LA GENERACION DEL EMPLEO SOCIAL INCLUSIVO - TRABAJA PERU | B510: 00 | C510: 01. PIA 2026 | D510: 3000001.ACCIONES COMUNES | E510: 5000276.GESTION DEL PROGRAMA | F510: 0047173.GESTION DEL PROGRAMA | G510: AOI00106600163. GESTIÓN OPERATIVA - UT SAN MARTIN | H510: SERVICIOS DE LUZ, AGUA, INTERNET, TELF. FJA | I510: RESTRINGIDA | J510: UFAF | K510: UFAF | L510: UT SAN MARTIN | M510: 0027. UT SAN MARTIN | N510: 0027 | O510: UT SAN MARTIN | P510: 5-23.BIENES Y SERVICIOS | Q510: 23 2 2 2 3. SERVICIO DE INTERNET | R510: 23 2 2 2 3 | S510: SERVICIO DE INTERNET | T510: 1200 | U510: 3893 | X510: 3892.95 | Y510: =+IFERROR(X510/U510,0) -> 0.99998716 | Z510: =+U510-X510 -> 0.05 | AB510: 3892.95 | AC510: 0.05 | AD510: 3892.95 | AF510: 1892.95 | AG510: =+IFERROR(AF510/U510,0) -> 0.48624454 | AH510: =+Tabla1[[#This Row],[PIM]]-Tabla1[[#This Row],[DEVENGADO2]] -> 2000.05 | AI510: 0 | AJ510: 199.98 | AK510: 92.97 | AL510: 400 | AM510: 400 | AN510: 400 | AO510: 400 | AP510: 0 | AQ510: 400.00714 | AR510: 400.00714 | AS510: 400.00714 | AT510: 400.00714 | AU510: 400.02143 | AV510: =+SUM(AI510:AU510) -> 3893 | AW510: =+U510-AV510 -> 0
A511: 0073.PROGRAMA PARA LA GENERACION DEL EMPLEO SOCIAL INCLUSIVO - TRABAJA PERU | C511: 01. PIA 2026 | D511: 3000001.ACCIONES COMUNES | E511: 5000276.GESTION DEL PROGRAMA | F511: 0047173.GESTION DEL PROGRAMA | G511: AOI00106600163. GESTIÓN OPERATIVA - UT SAN MARTIN | H511: SERVICIO DE MENSAJERIA | I511: NO RESTRINGIDA | J511: UFAF | K511: UFAF | L511: UT SAN MARTIN | M511: 0027. UT SAN MARTIN | N511: 0027 | O511: UT SAN MARTIN | P511: 5-23.BIENES Y SERVICIOS | Q511: 23 2 2 3 1. CORREOS Y SERVICIOS DE MENSAJERIA | R511: 23 2 2 3 1 | S511: CORREOS Y SERVICIOS DE MENSAJERIA | T511: 0 | U511: 600 | X511: 600 | Y511: =+IFERROR(X511/U511,0) -> 1 | Z511: =+U511-X511 -> 0 | AB511: 600 | AC511: 0 | AD511: 150 | AF511: 150 | AG511: =+IFERROR(AF511/U511,0) -> 0.25 | AH511: =+Tabla1[[#This Row],[PIM]]-Tabla1[[#This Row],[DEVENGADO2]] -> 450 | AI511: 0 | AJ511: 0 | AK511: 0 | AL511: 122 | AM511: 0 | AN511: 28 | AO511: 0 | AP511: 54.545455 | AQ511: 54.545455 | AR511: 54.545455 | AS511: 54.545455 | AT511: 54.545455 | AU511: 177.27273 | AV511: =+SUM(AI511:AU511) -> 600 | AW511: =+U511-AV511 -> 0
A512: 0073.PROGRAMA PARA LA GENERACION DEL EMPLEO SOCIAL INCLUSIVO - TRABAJA PERU | C512: 01. PIA 2026 | D512: 3000001.ACCIONES COMUNES | E512: 5000276.GESTION DEL PROGRAMA | F512: 0047173.GESTION DEL PROGRAMA | G512: AOI00106600163. GESTIÓN OPERATIVA - UT SAN MARTIN | H512: MANTENIMIENOT DE VEHICULOS | I512: NO RESTRINGIDA | J512: UFAF | K512: UFAF | L512: UT SAN MARTIN | M512: 0027. UT SAN MARTIN | N512: 0027 | O512: UT SAN MARTIN | P512: 5-23.BIENES Y SERVICIOS | Q512: 23 2 4 5 1. DE VEHICULOS | R512: 23 2 4 5 1 | S512: DE VEHICULOS | T512: 7600 | U512: 3764 | X512: 3764 | Y512: =+IFERROR(X512/U512,0) -> 1 | Z512: =+U512-X512 -> 0 | AB512: 3764 | AC512: 0 | AD512: 3764 | AF512: 3764 | AG512: =+IFERROR(AF512/U512,0) -> 1 | AH512: =+Tabla1[[#This Row],[PIM]]-Tabla1[[#This Row],[DEVENGADO2]] -> 0 | AI512: 0 | AJ512: 1485.5 | AK512: 0 | AL512: 0 | AM512: 793 | AN512: 0 | AO512: 1485.5 | AP512: 0 | AQ512: 0 | AR512: 0 | AS512: 0 | AT512: 0 | AU512: 0 | AV512: =+SUM(AI512:AU512) -> 3764 | AW512: =+U512-AV512 -> 0
A513: 0073.PROGRAMA PARA LA GENERACION DEL EMPLEO SOCIAL INCLUSIVO - TRABAJA PERU | C513: 01. PIA 2026 | D513: 3000001.ACCIONES COMUNES | E513: 5000276.GESTION DEL PROGRAMA | F513: 0047173.GESTION DEL PROGRAMA | G513: AOI00106600163. GESTIÓN OPERATIVA - UT SAN MARTIN | H513: ALQUILER DE LOCAL | I513: NO RESTRINGIDA | J513: UFAF | K513: UFAF | L513: UT SAN MARTIN | M513: 0027. UT SAN MARTIN | N513: 0027 | O513: UT SAN MARTIN | P513: 5-23.BIENES Y SERVICIOS | Q513: 23 2 5 1 1. DE EDIFICIOS Y ESTRUCTURAS | R513: 23 2 5 1 1 | S513: DE EDIFICIOS Y ESTRUCTURAS | T513: 48000 | U513: 48000 | X513: 48000 | Y513: =+IFERROR(X513/U513,0) -> 1 | Z513: =+U513-X513 -> 0 | AB513: 48000 | AC513: 0 | AD513: 48000 | AF513: 24000 | AG513: =+IFERROR(AF513/U513,0) -> 0.5 | AH513: =+Tabla1[[#This Row],[PIM]]-Tabla1[[#This Row],[DEVENGADO2]] -> 24000 | AI513: 0 | AJ513: 4000 | AK513: 4000 | AL513: 4000 | AM513: 4000 | AN513: 4000 | AO513: 4000 | AP513: 0 | AQ513: 4800 | AR513: 4800 | AS513: 4800 | AT513: 4800 | AU513: 4800 | AV513: =+SUM(AI513:AU513) -> 48000 | AW513: =+U513-AV513 -> 0
A514: 0073.PROGRAMA PARA LA GENERACION DEL EMPLEO SOCIAL INCLUSIVO - TRABAJA PERU | C514: 01. PIA 2026 | D514: 3000001.ACCIONES COMUNES | E514: 5000276.GESTION DEL PROGRAMA | F514: 0047173.GESTION DEL PROGRAMA | G514: AOI00106600163. GESTIÓN OPERATIVA - UT SAN MARTIN | H514: OTROS SERVICIOS | I514: NO RESTRINGIDA | J514: UFAF | K514: UFAF | L514: UT SAN MARTIN | M514: 0027. UT SAN MARTIN | N514: 0027 | O514: UT SAN MARTIN | P514: 5-23.BIENES Y SERVICIOS | Q514: 23 2 711 2. TRANSPORTE Y TRASLADO DE CARGA, BIENES Y MATERIALES | R514: 23 2 711 2 | S514: TRANSPORTE Y TRASLADO DE CARGA, BIENES Y MATERIALES | T514: 0 | U514: 1000 | X514: 0 | Y514: =+IFERROR(X514/U514,0) -> 0 | Z514: =+U514-X514 -> 1000 | AB514: 0 | AC514: 1000 | AD514: 0 | AF514: 0 | AG514: =+IFERROR(AF514/U514,0) -> 0 | AH514: =+Tabla1[[#This Row],[PIM]]-Tabla1[[#This Row],[DEVENGADO2]] -> 1000 | AI514: 0 | AJ514: 0 | AK514: 0 | AL514: 0 | AM514: 0 | AN514: 0 | AO514: 0 | AP514: 0 | AQ514: 0 | AR514: 1000 | AS514: 0 | AT514: 0 | AU514: 0 | AV514: =+SUM(AI514:AU514) -> 1000 | AW514: =+U514-AV514 -> 0
A515: 0073.PROGRAMA PARA LA GENERACION DEL EMPLEO SOCIAL INCLUSIVO - TRABAJA PERU | C515: 01. PIA 2026 | D515: 3000001.ACCIONES COMUNES | E515: 5000276.GESTION DEL PROGRAMA | F515: 0047173.GESTION DEL PROGRAMA | G515: AOI00106600163. GESTIÓN OPERATIVA - UT SAN MARTIN | H515: SERVICIOS DIVERSOS | I515: RESTRINGIDA | J515: UFAF | K515: UFAF | L515: UT SAN MARTIN | M515: 0027. UT SAN MARTIN | N515: 0027 | O515: UT SAN MARTIN | P515: 5-23.BIENES Y SERVICIOS | Q515: 23 2 71199. SERVICIOS DIVERSOS | R515: 23 2 71199 | S515: SERVICIOS DIVERSOS | T515: 59600 | U515: 60034 | X515: 36534 | Y515: =+IFERROR(X515/U515,0) -> 0.60855515 | Z515: =+U515-X515 -> 23500 | AB515: 36534 | AC515: 23500 | AD515: 34546 | AF515: 25146 | AG515: =+IFERROR(AF515/U515,0) -> 0.41886264 | AH515: =+Tabla1[[#This Row],[PIM]]-Tabla1[[#This Row],[DEVENGADO2]] -> 34888 | AI515: 1000 | AJ515: 3234 | AK515: 4700 | AL515: 4752 | AM515: 3000 | AN515: 3760 | AO515: 4700 | AP515: 0 | AQ515: 5500 | AR515: 5500 | AS515: 5500 | AT515: 5500 | AU515: 12888 | AV515: =+SUM(AI515:AU515) -> 60034 | AW515: =+U515-AV515 -> 0
A516: 0073.PROGRAMA PARA LA GENERACION DEL EMPLEO SOCIAL INCLUSIVO - TRABAJA PERU | C516: 01. PIA 2026 | D516: 3000001.ACCIONES COMUNES | E516: 5000276.GESTION DEL PROGRAMA | F516: 0047173.GESTION DEL PROGRAMA | G516: AOI00106600163. GESTIÓN OPERATIVA - UT SAN MARTIN | H516: LOCADORES | I516: NO RESTRINGIDA | J516: UFAF | K516: UFAF | L516: UT SAN MARTIN | M516: 0027. UT SAN MARTIN | N516: 0027 | O516: UT SAN MARTIN | P516: 5-23.BIENES Y SERVICIOS | Q516: 23 2 9 1 1. LOCACIÓN DE SERVICIOS REALIZADOS POR PERSONA NATURAL | R516: 23 2 9 1 1 | S516: LOCACIÓN DE SERVICIOS REALIZADOS POR PERSONA NATURAL | T516: 22500 | U516: 5000 | X516: 5000 | Y516: =+IFERROR(X516/U516,0) -> 1 | Z516: =+U516-X516 -> 0 | AB516: 5000 | AC516: 0 | AD516: 5000 | AF516: 5000 | AG516: =+IFERROR(AF516/U516,0) -> 1 | AH516: =+Tabla1[[#This Row],[PIM]]-Tabla1[[#This Row],[DEVENGADO2]] -> 0 | AI516: 0 | AJ516: 0 | AK516: 2500 | AL516: 2500 | AM516: 0 | AN516: 0 | AO516: 0 | AP516: 0 | AQ516: 0 | AR516: 0 | AS516: 0 | AT516: 0 | AU516: 0 | AV516: =+SUM(AI516:AU516) -> 5000 | AW516: =+U516-AV516 -> 0
A517: 0073.PROGRAMA PARA LA GENERACION DEL EMPLEO SOCIAL INCLUSIVO - TRABAJA PERU | C517: 01. PIA 2026 | D517: 3000001.ACCIONES COMUNES | E517: 5000276.GESTION DEL PROGRAMA | F517: 0047173.GESTION DEL PROGRAMA | G517: AOI00106600164. GESTIÓN OPERATIVA - UT TACNA | H517: CAS | I517: RESTRINGIDA | J517: UFAF | K517: UFAF | L517: UT TACNA | M517: 0028. UT TACNA | N517: 0028 | O517: UT TACNA | P517: 5-21.PERSONAL Y OBLIGACIONES SOCIALES | Q517: 21 1 9 1 4. AGUINALDOS DE CONTRATO ADMINISTRATIVO DE SERVICIOS | R517: 21 1 9 1 4 | S517: AGUINALDOS DE CONTRATO ADMINISTRATIVO DE SERVICIOS | T517: 1200 | U517: 1200 | X517: 1200 | Y517: =+IFERROR(X517/U517,0) -> 1 | Z517: =+U517-X517 -> 0 | AB517: 1200 | AC517: 0 | AD517: 0 | AF517: 0 | AG517: =+IFERROR(AF517/U517,0) -> 0 | AH517: =+Tabla1[[#This Row],[PIM]]-Tabla1[[#This Row],[DEVENGADO2]] -> 1200 | AI517: 0 | AJ517: 0 | AK517: 0 | AL517: 0 | AM517: 0 | AN517: 0 | AO517: 0 | AP517: 600 | AQ517: 0 | AR517: 0 | AS517: 0 | AT517: 0 | AU517: 600 | AV517: =+SUM(AI517:AU517) -> 1200 | AW517: =+U517-AV517 -> 0
A518: 0073.PROGRAMA PARA LA GENERACION DEL EMPLEO SOCIAL INCLUSIVO - TRABAJA PERU | C518: 01. PIA 2026 | D518: 3000001.ACCIONES COMUNES | E518: 5000276.GESTION DEL PROGRAMA | F518: 0047173.GESTION DEL PROGRAMA | G518: AOI00106600164. GESTIÓN OPERATIVA - UT TACNA | H518: CAS | I518: RESTRINGIDA | J518: UFAF | K518: UFAF | L518: UT TACNA | M518: 0028. UT TACNA | N518: 0028 | O518: UT TACNA | P518: 5-21.PERSONAL Y OBLIGACIONES SOCIALES | Q518: 21 113 1 2. CONTRATO ADMINISTRATIVO DE SERVICIOS - TRANSITORIO | R518: 21 113 1 2 | S518: CONTRATO ADMINISTRATIVO DE SERVICIOS - TRANSITORIO | T518: 66340 | U518: 67152 | X518: 67152 | Y518: =+IFERROR(X518/U518,0) -> 1 | Z518: =+U518-X518 -> 0 | AB518: 67152 | AC518: 0 | AD518: 36396.49 | AF518: 36396.49 | AG518: =+IFERROR(AF518/U518,0) -> 0.54200158 | AH518: =+Tabla1[[#This Row],[PIM]]-Tabla1[[#This Row],[DEVENGADO2]] -> 30755.51 | AI518: 5197.57 | AJ518: 5200 | AK518: 5198.92 | AL518: 5200 | AM518: 5200 | AN518: 5200 | AO518: 5200 | AP518: 0 | AQ518: 5528.38 | AR518: 5528.38 | AS518: 5528.38 | AT518: 5528.38 | AU518: 8641.99 | AV518: =+SUM(AI518:AU518) -> 67152 | AW518: =+U518-AV518 -> 0
A519: 0073.PROGRAMA PARA LA GENERACION DEL EMPLEO SOCIAL INCLUSIVO - TRABAJA PERU | C519: 01. PIA 2026 | D519: 3000001.ACCIONES COMUNES | E519: 5000276.GESTION DEL PROGRAMA | F519: 0047173.GESTION DEL PROGRAMA | G519: AOI00106600164. GESTIÓN OPERATIVA - UT TACNA | H519: CAS | I519: RESTRINGIDA | J519: UFAF | K519: UFAF | L519: UT TACNA | M519: 0028. UT TACNA | N519: 0028 | O519: UT TACNA | P519: 5-21.PERSONAL Y OBLIGACIONES SOCIALES | Q519: 21 3 1 115. CONTRIBUCIONES A ESSALUD DE CONTRATO ADMINISTRATIVO DE SERVICIOS | R519: 21 3 1 115 | S519: CONTRIBUCIONES A ESSALUD DE CONTRATO ADMINISTRATIVO DE SERVICIOS | T519: 5520 | U519: 5346 | X519: 5346 | Y519: =+IFERROR(X519/U519,0) -> 1 | Z519: =+U519-X519 -> 0 | AB519: 5346 | AC519: 0 | AD519: 3118.5 | AF519: 3118.5 | AG519: =+IFERROR(AF519/U519,0) -> 0.58333333 | AH519: =+Tabla1[[#This Row],[PIM]]-Tabla1[[#This Row],[DEVENGADO2]] -> 2227.5 | AI519: 445.5 | AJ519: 445.5 | AK519: 445.5 | AL519: 445.5 | AM519: 445.5 | AN519: 445.5 | AO519: 445.5 | AP519: 0 | AQ519: 460 | AR519: 460 | AS519: 460 | AT519: 460 | AU519: 387.5 | AV519: =+SUM(AI519:AU519) -> 5346 | AW519: =+U519-AV519 -> 0
A520: 0073.PROGRAMA PARA LA GENERACION DEL EMPLEO SOCIAL INCLUSIVO - TRABAJA PERU | C520: 01. PIA 2026 | D520: 3000001.ACCIONES COMUNES | E520: 5000276.GESTION DEL PROGRAMA | F520: 0047173.GESTION DEL PROGRAMA | G520: AOI00106600164. GESTIÓN OPERATIVA - UT TACNA | H520: COMBUSTIBLE | I520: NO RESTRINGIDA | J520: UFAF | K520: UFAF | L520: UT TACNA | M520: 0028. UT TACNA | N520: 0028 | O520: UT TACNA | P520: 5-23.BIENES Y SERVICIOS | Q520: 23 1 3 1 1. COMBUSTIBLES Y CARBURANTES | R520: 23 1 3 1 1 | S520: COMBUSTIBLES Y CARBURANTES | T520: 3850 | U520: 9516 | X520: 9515.8 | Y520: =+IFERROR(X520/U520,0) -> 0.99997898 | Z520: =+U520-X520 -> 0.2 | AB520: 9515.8 | AC520: 0.2 | AD520: 2764.75 | AF520: 2764.75 | AG520: =+IFERROR(AF520/U520,0) -> 0.29053699 | AH520: =+Tabla1[[#This Row],[PIM]]-Tabla1[[#This Row],[DEVENGADO2]] -> 6751.25 | AI520: 0 | AJ520: 0 | AK520: 0 | AL520: 261.54 | AM520: 0 | AN520: 2503.21 | AO520: 0 | AP520: 0 | AQ520: 0 | AR520: 750 | AS520: 5251.25 | AT520: 750 | AU520: 0 | AV520: =+SUM(AI520:AU520) -> 9516 | AW520: =+U520-AV520 -> 0
A521: 0073.PROGRAMA PARA LA GENERACION DEL EMPLEO SOCIAL INCLUSIVO - TRABAJA PERU | C521: 01. PIA 2026 | D521: 3000001.ACCIONES COMUNES | E521: 5000276.GESTION DEL PROGRAMA | F521: 0047173.GESTION DEL PROGRAMA | G521: AOI00106600164. GESTIÓN OPERATIVA - UT TACNA | H521: OTROS BIENES | I521: NO RESTRINGIDA | J521: UFAF | K521: UFAF | L521: UT TACNA | M521: 0028. UT TACNA | N521: 0028 | O521: UT TACNA | P521: 5-23.BIENES Y SERVICIOS | Q521: 23 1 59999. OTROS | R521: 23 1 59999 | S521: OTROS | T521: 0 | U521: 4550 | X521: 4550 | Y521: =+IFERROR(X521/U521,0) -> 1 | Z521: =+U521-X521 -> 0 | AB521: 4550 | AC521: 0 | AD521: 3402.08 | AF521: 3402.08 | AG521: =+IFERROR(AF521/U521,0) -> 0.74770989 | AH521: =+Tabla1[[#This Row],[PIM]]-Tabla1[[#This Row],[DEVENGADO2]] -> 1147.92 | AI521: 500 | AJ521: 639.01 | AK521: 636.8 | AL521: 1041.68 | AM521: 80 | AN521: 504.59 | AO521: 0 | AP521: 127.96455 | AQ521: 69.955455 | AR521: 950 | AS521: 0 | AT521: 0 | AU521: 0 | AV521: =+SUM(AI521:AU521) -> 4550 | AW521: =+U521-AV521 -> 0
A522: 0073.PROGRAMA PARA LA GENERACION DEL EMPLEO SOCIAL INCLUSIVO - TRABAJA PERU | C522: 01. PIA 2026 | D522: 3000001.ACCIONES COMUNES | E522: 5000276.GESTION DEL PROGRAMA | F522: 0047173.GESTION DEL PROGRAMA | G522: AOI00106600164. GESTIÓN OPERATIVA - UT TACNA | H522: OTROS BIENES | I522: NO RESTRINGIDA | J522: UFAF | K522: UFAF | L522: UT TACNA | M522: 0028. UT TACNA | N522: 0028 | O522: UT TACNA | P522: 5-23.BIENES Y SERVICIOS | Q522: 23 1 6 1 1. DE VEHICULOS | R522: 23 1 6 1 1 | S522: DE VEHICULOS | T522: 550 | U522: 0 | X522: 0 | Y522: =+IFERROR(X522/U522,0) -> 0 | Z522: =+U522-X522 -> 0 | AB522: 0 | AC522: 0 | AD522: 0 | AF522: 0 | AG522: =+IFERROR(AF522/U522,0) -> 0 | AH522: =+Tabla1[[#This Row],[PIM]]-Tabla1[[#This Row],[DEVENGADO2]] -> 0 | AI522: 0 | AJ522: 0 | AK522: 0 | AL522: 0 | AM522: 0 | AN522: 0 | AO522: 0 | AP522: 0 | AQ522: 0 | AR522: 0 | AS522: 0 | AT522: 0 | AU522: 0 | AV522: =+SUM(AI522:AU522) -> 0 | AW522: =+U522-AV522 -> 0
... A822: 0073.PROGRAMA PARA LA GENERACION DEL EMPLEO SOCIAL INCLUSIVO - TRABAJA PERU | C822: 01. PIA 2026 | D822: 3000194.EMPLEO TEMPORAL GENERADO | E822: 5006294.TRANSFERENCIA DE RECURSOS PARA LA EJECUCION DE PROYECTOS Y ACTIVIDADES | F822: 0059376.TRANSFERENCIA DE RECURSOS PARA LA EJECUCION DE ACTIVIDADES | G822: - | H822: FINANCIAMIENTO DE AII | I822: NO RESTRINGIDA | J822: UFGI - TRANSFERENCIAS AII | K822: UFGI - TRANSFERENCIAS AII | L822: UCAYALI | M822: 0130. UCAYALI | N822: 0130 | O822: UCAYALI | P822: 5-24.DONACIONES Y TRANSFERENCIAS | Q822: 24 1 3 1 3. A OTRAS UNIDADES DEL GOBIERNO LOCAL | R822: 24 1 3 1 3 | S822: A OTRAS UNIDADES DEL GOBIERNO LOCAL | T822: 0 | U822: 732266 | X822: 732266 | Y822: =+IFERROR(X822/U822,0) -> 1 | Z822: =+U822-X822 -> 0 | AB822: 732266 | AC822: 0 | AD822: 732266 | AF822: 732266 | AG822: =+IFERROR(AF822/U822,0) -> 1 | AH822: =+Tabla1[[#This Row],[PIM]]-Tabla1[[#This Row],[DEVENGADO2]] -> 0 | AI822: 0 | AJ822: 0 | AK822: 0 | AL822: 732266 | AM822: 0 | AN822: 0 | AO822: 0 | AP822: 0 | AQ822: 0 | AR822: 0 | AS822: 0 | AT822: 0 | AU822: 0 | AV822: =+SUM(AI822:AU822) -> 732266 | AW822: =+U822-AV822 -> 0

Sheet CCP
N2: SEGUIMIENTO A LA EJECUCIÓN DE CCP - 2026
FZ3: PIM | GA3: =+#REF! -> #REF! | GD3: PIM | GE3: =+#REF! -> #REF!
N5: CERTIFICADO (S/) | X5: N° de CCPs | FZ5: Poco avance | GA5: 95 | GB5: 0.98 | GD5: Muy bueno | GE5: 70 | GF5: 0.98
FZ6: TOTAL | GA6: =+SUM(GA5:GA5) -> 95 | GB6: 0 | GD6: TOTAL | GE6: =+SUM(GE5:GE5) -> 70 | GF6: 0
N7: =+DETALLE_CCP!AB4 -> 2.3383864e+08 | X7: =+DETALLE_CCP!R4 -> 1875
FZ8: CERT | GA8: =+#REF! -> #REF! | GD8: dev | GE8: =+#REF! -> #REF!
FZ9: % AVANCE | GA9: =+IFERROR(GA8/GA3,0) -> 0 | GD9: % AVANCE | GE9: =+IFERROR(GE8/GE3,0) -> 0
FZ11: Grados | GA11: =+GA9*PI() -> 0 | GD11: Grados | GE11: =+GE9*PI() -> 0
N12: COMP. ANUAL (S/) | X12: CERT SIN COMP. ANUAL | FZ12: Inicial | GA12: 0 | GB12: 0 | GD12: Inicial | GE12: 0 | GF12: 0
AG13: EJEC. de CCP MENSUAL | FZ13: Final | GA13: =COS(GA11)*-1 -> -1 | GB13: =+SIN(GA11) -> 0 | GD13: Final | GE13: =COS(GE11)*-1 -> -1 | GF13: =+SIN(GE11) -> 0
N14: =+DETALLE_CCP!AC4 -> 1.0179106e+08 | X14: =+N7-N14 -> 1.3204758e+08
AG15: ENE | AI15: =+DETALLE_CCP!AJ4 -> 1066379.2
AG16: FEB | AI16: =+DETALLE_CCP!AK4 -> 1962584.9
AG17: MAR | AI17: =+DETALLE_CCP!AL4 -> 2792982.9
AG18: ABR | AI18: =+DETALLE_CCP!AM4 -> 1.9653967e+08
N19: DEVENGADO (S/) | X19: COMP ANUAL x DEVENGAR (S/) | AG19: MAY | AI19: =+DETALLE_CCP!AN4 -> 2187059.9
AG20: JUN | AI20: =+DETALLE_CCP!AO4 -> 2547006
N21: =+DETALLE_CCP!AF4 -> 2.0959367e+08 | X21: =+N7-N21 -> 24244971 | AG21: JUL | AI21: =+DETALLE_CCP!AP4 -> 2497981.6
AG22: AGO | AI22: =+DETALLE_CCP!AQ4 -> 0
AG23: SET | AI23: =+DETALLE_CCP!AR4 -> 0
AG24: OCT | AI24: =+DETALLE_CCP!AS4 -> 0
AG25: NOV | AI25: =+DETALLE_CCP!AT4 -> 0
AG26: DIC | AI26: =+DETALLE_CCP!AT4 -> 0
N28: ® UNIDAD FUNCIONAL DE PLANEAMIENTO Y PRESUPUESTO
GA35: =+#REF!+1 -> #REF! | GC35: =+#REF!+1 -> #REF! | GE35: =+GC35/$GC$23 -> #REF! | GG35: LABORABLE | GI35: SÁBADO
GA36: =+GA35+1 -> #REF! | GC36: =+GC35+1 -> #REF! | GE36: =+GC36/$GC$23 -> #REF! | GG36: LABORABLE | GI36: DOMINGO
GA37: =+GA36+1 -> #REF! | GC37: =+GC36+1 -> #REF! | GE37: =+GC37/$GC$23 -> #REF! | GG37: LABORABLE | GI37: LUNES
GA38: =+GA37+1 -> #REF! | GC38: =+GC37+1 -> #REF! | GE38: =+GC38/$GC$23 -> #REF! | GG38: LABORABLE | GI38: MARTES
GA39: =+GA38+1 -> #REF! | GC39: =+GC38+1 -> #REF! | GE39: =+GC39/$GC$23 -> #REF! | GG39: LABORABLE | GI39: MIÉRCOLES
GA40: =+#REF!+1 -> #REF! | GC40: =+#REF!+1 -> #REF! | GE40: =+GC40/$GC$23 -> #REF! | GG40: LABORABLE | GI40: VIERNES
GA41: =+GA40+1 -> #REF! | GC41: =+GC40+1 -> #REF! | GE41: =+GC41/$GC$23 -> #REF! | GG41: LABORABLE | GI41: SÁBADO
GA42: =+GA41+1 -> #REF! | GC42: =+GC41+1 -> #REF! | GE42: =+GC42/$GC$23 -> #REF! | GG42: LABORABLE | GI42: DOMINGO
GA43: =+GA42+1 -> #REF! | GC43: =+GC42+1 -> #REF! | GE43: =+GC43/$GC$23 -> #REF! | GG43: LABORABLE | GI43: LUNES
GA44: =+GA43+1 -> #REF! | GC44: =+GC43+1 -> #REF! | GE44: =+GC44/$GC$23 -> #REF! | GG44: LABORABLE | GI44: MARTES
GA45: =+GA44+1 -> #REF! | GC45: =+GC44+1 -> #REF! | GE45: =+GC45/$GC$23 -> #REF! | GG45: LABORABLE | GI45: MIÉRCOLES
GA46: =+GA45+1 -> #REF! | GC46: =+GC45+1 -> #REF! | GE46: =+GC46/$GC$23 -> #REF! | GG46: LABORABLE | GI46: JUEVES
GA47: =+GA46+1 -> #REF! | GC47: =+GC46+1 -> #REF! | GE47: =+GC47/$GC$23 -> #REF! | GG47: LABORABLE | GI47: VIERNES
GA48: =+GA47+1 -> #REF! | GC48: =+GC47+1 -> #REF! | GE48: =+GC48/$GC$23 -> #REF! | GG48: LABORABLE | GI48: SÁBADO
GA49: =+GA48+1 -> #REF! | GC49: =+GC48+1 -> #REF! | GE49: =+GC49/$GC$23 -> #REF! | GG49: LABORABLE | GI49: DOMINGO
GA50: =+GA49+1 -> #REF! | GC50: =+GC49+1 -> #REF! | GE50: =+GC50/$GC$23 -> #REF! | GG50: LABORABLE | GI50: LUNES
GA51: =+GA50+1 -> #REF! | GC51: =+GC50+1 -> #REF! | GE51: =+GC51/$GC$23 -> #REF! | GG51: LABORABLE | GI51: MARTES
GA52: =+GA51+1 -> #REF! | GC52: =+GC51+1 -> #REF! | GE52: =+GC52/$GC$23 -> #REF! | GG52: LABORABLE | GI52: MIÉRCOLES
... GA385: =+GA384+1 -> #REF! | GC385: =+GC384+1 -> #REF! | GE385: =+GC385/$GC$23 -> #REF! | GG385: NO LABORABLE | GI385: DOMINGO

Sheet DETALLE_CCP
A1: SEGUIMIENTO DE LOS CCP - 2026 | AJ1: DEVENGADO
A2: Fuente: SIAF-MPP, reporte al 31.07.2026 - 09.00am
A4: TOTAL | R4: =+SUBTOTAL(3,Tabla2[CCP]) -> 1875 | AB4: =+SUBTOTAL(9,Tabla2[CERT]) -> 2.3383864e+08 | AC4: =+SUBTOTAL(9,Tabla2[COMP ANUAL]) -> 1.0179106e+08 | AD4: =+AB4-AC4 -> 1.3204758e+08 | AE4: =+SUBTOTAL(9,Tabla2[COMPROMISO]) -> 2.1411364e+08 | AF4: =+SUBTOTAL(9,Tabla2[DEVENGADO]) -> 2.0959367e+08 | AG4: =+AB4-AF4 -> 24244971 | AH4: =+SUBTOTAL(9,Tabla2[GIRADO]) -> 2.0946935e+08 | AI4: =+SUBTOTAL(9,AI7:AI3405) -> 0 | AJ4: =+SUBTOTAL(9,Tabla2[ENE]) -> 1066379.2 | AK4: =+SUBTOTAL(9,Tabla2[FEB]) -> 1962584.9 | AL4: =+SUBTOTAL(9,Tabla2[MAR]) -> 2792982.9 | AM4: =+SUBTOTAL(9,Tabla2[ABR]) -> 1.9653967e+08 | AN4: =+SUBTOTAL(9,Tabla2[MAY]) -> 2187059.9 | AO4: =+SUBTOTAL(9,Tabla2[JUN]) -> 2547006 | AP4: =+SUBTOTAL(9,Tabla2[JUL]) -> 2497981.6 | AQ4: =+SUBTOTAL(9,Tabla2[AGO]) -> 0 | AR4: =+SUBTOTAL(9,Tabla2[SEP]) -> 0 | AS4: =+SUBTOTAL(9,Tabla2[OCT]) -> 0 | AT4: =+SUBTOTAL(9,Tabla2[NOV]) -> 0 | AU4: =+SUBTOTAL(9,Tabla2[DIC]) -> 0
A6: fecha_doc | B6: MES DE APROBADO CCP | C6: Estado | D6: CENTRO DE COSTO | E6: DISPOSITIVO LEGAL | F6: PROG. PPTAL. | G6: ACT. PPTAL. | H6: CONCEPTO DE GASTO | I6: RESTRINGIDA / NO RESTRINGIDA | J6: OF. NAC. / UT / TRANSF | K6: UNIDAD / UT | L6: EXP. SIAF | M6: N° O/S | N6: FECHA O/S | O6: RUC PROVEEDOR | P6: NOMBRE PROVEEDOR | Q6: Fte. Fto. | R6: CCP | S6: Glosa Certificación | T6: N° de CCP + Glosa | U6: Sec. Fun. | V6: Nemonico Sec.Fun. | W6: Sec. fun. + Nemonico | X6: Gen de Gastos | Y6: Clasificador | Z6: DESCRIPCIÓN | AA6: Clasif + Desc. | AB6: CERT | AC6: COMP ANUAL | AD6: SALDO (CERT - COMP ANUAL) | AE6: COMPROMISO | AF6: DEVENGADO | AG6: SALDO (COMP. ANUAL - DEV) | AH6: GIRADO | AI6: . | AJ6: ENE | AK6: FEB | AL6: MAR | AM6: ABR | AN6: MAY | AO6: JUN | AP6: JUL | AQ6: AGO | AR6: SEP | AS6: OCT | AT6: NOV | AU6: DIC | AV6: CERT POR COMP ANUAL | AW6: COMP. ANUAL POR DEVENGAR | AX6: SERVICIO
A7: 46035 | B7: 01. ENE | C7: APROBADO | D7: UFAF | E7: 01. PIA 2026 | F7: 3000001.ACCIONES COMUNES | G7: 5000276.GESTION DEL PROGRAMA | H7: DIFUSION EN EL PERUANO | I7: NO RESTRINGIDA | J7: OFICINA NACIONAL | K7: UFAF | L7: 0000000003 | M7: 12229 | N7: 08/01/2026 | O7: 0 | P7: 0000000001 | 12229 | SIN NOMBRE | Q7: 00 | R7: 0000000001 | S7: CCMN-000036: CONTRATACION DEL SERVICIO DE PUBLICACION EN EL DIARIO OFICIAL EL PERUANO | T7: 0000000001. CCMN-000036: CONTRATACION DEL SERVICIO DE PUBLICACION EN EL DIARIO OFICIAL EL PERUANO | U7: 0014 | V7: UFAF | W7: 0014. UFAF | X7: 5-23. BIENES Y SERVICIOS | Y7: 23 2 2 5 1 | Z7: DIFUSIÓN EN EL DIARIO OFICIAL | AA7: 23 2 2 5 1. DIFUSIÓN EN EL DIARIO OFICIAL | AB7: 20000 | AC7: 20000 | AD7: 0 | AE7: 20000 | AF7: 1286.86 | AG7: 18713.14 | AH7: 1286.86 | AI7: 2026 | AJ7: 1286.86 | AK7: 0 | AL7: 0 | AM7: 0 | AN7: 0 | AO7: 0 | AP7: 0 | AQ7: 0 | AR7: 0 | AS7: 0 | AT7: 0 | AU7: 0 | AV7: CCP SIN SALDO | AW7: CCP POR DEVENGAR | AX7: -
A8: 46035 | B8: 01. ENE | C8: APROBADO | D8: UFAF | E8: 01. PIA 2026 | F8: 3000001.ACCIONES COMUNES | G8: 5000276.GESTION DEL PROGRAMA | H8: AGUA DE MESA | I8: NO RESTRINGIDA | J8: OFICINA NACIONAL | K8: UFAF | L8: 0000000007 | M8: 0000001 | N8: 15/01/2026 | O8: 20340549750 | P8: 0000000002 | 0000001 | CONQUISTADORES REAL SERVICE S.A. | Q8: 00 | R8: 0000000002 | S8: CCMN-000001: ADQUISICION DE AGUA DE MESA PARA LA OFICINA NACIONAL, ARCHIVO CENTRAL Y UNIDADES TERRITORIALES LIMA | T8: 0000000002. CCMN-000001: ADQUISICION DE AGUA DE MESA PARA LA OFICINA NACIONAL, ARCHIVO CENTRAL Y UNIDADES TERRITORIALES LIMA | U8: 0014 | V8: UFAF | W8: 0014. UFAF | X8: 5-23. BIENES Y SERVICIOS | Y8: 23 1 1 1 1 | Z8: ALIMENTOS Y BEBIDAS PARA CONSUMO HUMANO | AA8: 23 1 1 1 1. ALIMENTOS Y BEBIDAS PARA CONSUMO HUMANO | AB8: 16800 | AC8: 16800 | AD8: 0 | AE8: 16800 | AF8: 14400 | AG8: 2400 | AH8: 14400 | AI8: 2026 | AJ8: 2400 | AK8: 2400 | AL8: 2400 | AM8: 2400 | AN8: 2400 | AO8: 0 | AP8: 2400 | AQ8: 0 | AR8: 0 | AS8: 0 | AT8: 0 | AU8: 0 | AV8: CCP SIN SALDO | AW8: CCP POR DEVENGAR | AX8: -
A9: 46035 | B9: 01. ENE | C9: APROBADO | D9: UFAF | E9: 01. PIA 2026 | F9: 3000001.ACCIONES COMUNES | G9: 5000276.GESTION DEL PROGRAMA | H9: LOCADORES | I9: NO RESTRINGIDA | J9: OFICINA NACIONAL | K9: UFAF | L9: 0000000011 | M9: 0000008 | N9: 15/01/2026 | O9: 10444528121 | P9: 0000000003 | 0000008 | GALLOSO ROSAS YULIANA LIZBETH | Q9: 00 | R9: 0000000003 | S9: CCMN-002013: CONTRATACION DEL SERVICIO DE SEGUIMIENTO Y MONITOREO DE SERVICIOS GENERALES DE LA COORDINACION FUNCI | T9: 0000000003. CCMN-002013: CONTRATACION DEL SERVICIO DE SEGUIMIENTO Y MONITOREO DE SERVICIOS GENERALES DE LA COORDINACION FUNCI | U9: 0014 | V9: UFAF | W9: 0014. UFAF | X9: 5-23. BIENES Y SERVICIOS | Y9: 23 2 9 1 1 | Z9: LOCACIÓN DE SERVICIOS REALIZADOS POR PERSONA NATURAL | AA9: 23 2 9 1 1. LOCACIÓN DE SERVICIOS REALIZADOS POR PERSONA NATURAL | AB9: 6000 | AC9: 6000 | AD9: 0 | AE9: 6000 | AF9: 6000 | AG9: 0 | AH9: 6000 | AI9: 2026 | AJ9: 6000 | AK9: 0 | AL9: 0 | AM9: 0 | AN9: 0 | AO9: 0 | AP9: 0 | AQ9: 0 | AR9: 0 | AS9: 0 | AT9: 0 | AU9: 0 | AV9: CCP SIN SALDO | AW9: CCP DEVENGADO | AX9: LOCADOR
A10: 46035 | B10: 01. ENE | C10: APROBADO | D10: UFAF | E10: 01. PIA 2026 | F10: 3000001.ACCIONES COMUNES | G10: 5000276.GESTION DEL PROGRAMA | H10: LOCADORES | I10: NO RESTRINGIDA | J10: OFICINA NACIONAL | K10: UFAF | L10: 0000000042 | M10: 0000034 | N10: 16/01/2026 | O10: 10740657238 | P10: 0000000004 | 0000034 | SANCA BUSTAMANTE JHONATHAN ALEXANDER | Q10: 00 | R10: 0000000004 | S10: CCMN-002007: SERVICIOS DE ANALISIS DE PROCESOS DE CONTRATACIONES MENORES O IGUALES A 8 UIT | T10: 0000000004. CCMN-002007: SERVICIOS DE ANALISIS DE PROCESOS DE CONTRATACIONES MENORES O IGUALES A 8 UIT | U10: 0014 | V10: UFAF | W10: 0014. UFAF | X10: 5-23. BIENES Y SERVICIOS | Y10: 23 2 9 1 1 | Z10: LOCACIÓN DE SERVICIOS REALIZADOS POR PERSONA NATURAL | AA10: 23 2 9 1 1. LOCACIÓN DE SERVICIOS REALIZADOS POR PERSONA NATURAL | AB10: 7000 | AC10: 7000 | AD10: 0 | AE10: 7000 | AF10: 7000 | AG10: 0 | AH10: 7000 | AI10: 2026 | AJ10: 7000 | AK10: 0 | AL10: 0 | AM10: 0 | AN10: 0 | AO10: 0 | AP10: 0 | AQ10: 0 | AR10: 0 | AS10: 0 | AT10: 0 | AU10: 0 | AV10: CCP SIN SALDO | AW10: CCP DEVENGADO | AX10: LOCADOR
A11: 46035 | B11: 01. ENE | C11: APROBADO | D11: UFSMI | E11: 01. PIA 2026 | F11: 3000194.EMPLEO TEMPORAL GENERADO | G11: 5006296.SEGUIMIENTO DE LOS PROYECTOS Y ACTIVIDADES EN EJECUCION | H11: LOCADORES | I11: NO RESTRINGIDA | J11: OFICINA NACIONAL | K11: UFSMI | L11: 0000000045 | M11: 0000037 | N11: 16/01/2026 | O11: 10182169922 | P11: 0000000005 | 0000037 | MELGAR OCAMPOS FREDY RONALD | Q11: 00 | R11: 0000000005 | S11: CCMN-002008: SERVICIO DE SUPERVISION, SEGUIMIENTO Y MONITOREO A LA EJECUCION DE PROYECTOS DE INVERSION Y ACTIVIDA | T11: 0000000005. CCMN-002008: SERVICIO DE SUPERVISION, SEGUIMIENTO Y MONITOREO A LA EJECUCION DE PROYECTOS DE INVERSION Y ACTIVIDA | U11: 0056 | V11: UFSMI | W11: 0056. UFSMI | X11: 5-23. BIENES Y SERVICIOS | Y11: 23 2 9 1 1 | Z11: LOCACIÓN DE SERVICIOS REALIZADOS POR PERSONA NATURAL | AA11: 23 2 9 1 1. LOCACIÓN DE SERVICIOS REALIZADOS POR PERSONA NATURAL | AB11: 8000 | AC11: 8000 | AD11: 0 | AE11: 8000 | AF11: 8000 | AG11: 0 | AH11: 8000 | AI11: 2026 | AJ11: 8000 | AK11: 0 | AL11: 0 | AM11: 0 | AN11: 0 | AO11: 0 | AP11: 0 | AQ11: 0 | AR11: 0 | AS11: 0 | AT11: 0 | AU11: 0 | AV11: CCP SIN SALDO | AW11: CCP DEVENGADO | AX11: LOCADOR
A12: 46035 | B12: 01. ENE | C12: APROBADO | D12: UFAJ | E12: 01. PIA 2026 | F12: 3000001.ACCIONES COMUNES | G12: 5000276.GESTION DEL PROGRAMA | H12: LOCADORES | I12: NO RESTRINGIDA | J12: OFICINA NACIONAL | K12: UFAJ | L12: 0000000044 | M12: 0000036 | N12: 16/01/2026 | O12: 10481279700 | P12: 0000000006 | 0000036 | MORA ASNARAN FERNANDO | Q12: 00 | R12: 0000000006 | S12: CCMN-002009: SERVICIOS DE ANALISIS Y ELABORACION DE INFORMES EN TEMAS LEGALES | T12: 0000000006. CCMN-002009: SERVICIOS DE ANALISIS Y ELABORACION DE INFORMES EN TEMAS LEGALES | U12: 0015 | V12: UFAJ | W12: 0015. UFAJ | X12: 5-23. BIENES Y SERVICIOS | Y12: 23 2 9 1 1 | Z12: LOCACIÓN DE SERVICIOS REALIZADOS POR PERSONA NATURAL | AA12: 23 2 9 1 1. LOCACIÓN DE SERVICIOS REALIZADOS POR PERSONA NATURAL | AB12: 8000 | AC12: 8000 | AD12: 0 | AE12: 8000 | AF12: 8000 | AG12: 0 | AH12: 8000 | AI12: 2026 | AJ12: 8000 | AK12: 0 | AL12: 0 | AM12: 0 | AN12: 0 | AO12: 0 | AP12: 0 | AQ12: 0 | AR12: 0 | AS12: 0 | AT12: 0 | AU12: 0 | AV12: CCP SIN SALDO | AW12: CCP DEVENGADO | AX12: LOCADOR
A13: 46035 | B13: 01. ENE | C13: APROBADO | D13: UFAF | E13: 01. PIA 2026 | F13: 3000001.ACCIONES COMUNES | G13: 5000276.GESTION DEL PROGRAMA | H13: LOCADORES | I13: NO RESTRINGIDA | J13: OFICINA NACIONAL | K13: UFAF | L13: 0000000048 | M13: 0000040 | N13: 16/01/2026 | O13: 10719216124 | P13: 0000000007 | 0000040 | SANTANA DAZA PIERO ANGEL | Q13: 00 | R13: 0000000007 | S13: CCMN-002011: SERVICIO ANALISIS Y SEGUIMIENTO ADMINISTRATIVO Y PRESUPUESTAL - UFAF | T13: 0000000007. CCMN-002011: SERVICIO ANALISIS Y SEGUIMIENTO ADMINISTRATIVO Y PRESUPUESTAL - UFAF | U13: 0014 | V13: UFAF | W13: 0014. UFAF | X13: 5-23. BIENES Y SERVICIOS | Y13: 23 2 9 1 1 | Z13: LOCACIÓN DE SERVICIOS REALIZADOS POR PERSONA NATURAL | AA13: 23 2 9 1 1. LOCACIÓN DE SERVICIOS REALIZADOS POR PERSONA NATURAL | AB13: 7500 | AC13: 7500 | AD13: 0 | AE13: 7500 | AF13: 7500 | AG13: 0 | AH13: 7500 | AI13: 2026 | AJ13: 7500 | AK13: 0 | AL13: 0 | AM13: 0 | AN13: 0 | AO13: 0 | AP13: 0 | AQ13: 0 | AR13: 0 | AS13: 0 | AT13: 0 | AU13: 0 | AV13: CCP SIN SALDO | AW13: CCP DEVENGADO | AX13: LOCADOR
A14: 46035 | B14: 01. ENE | C14: APROBADO | D14: UFAF | E14: 01. PIA 2026 | F14: 3000001.ACCIONES COMUNES | G14: 5000276.GESTION DEL PROGRAMA | H14: LOCADORES | I14: NO RESTRINGIDA | J14: OFICINA NACIONAL | K14: UFAF | L14: 0000000043 | M14: 0000035 | N14: 16/01/2026 | O14: 10729341113 | P14: 0000000008 | 0000035 | VILLEGAS MEDINA KEVIN ALEXANDER | Q14: 00 | R14: 0000000008 | S14: CCMN-002010: SERVICIO ESPECIALIZADO EN MATERIA LEGAL - UFAF | T14: 0000000008. CCMN-002010: SERVICIO ESPECIALIZADO EN MATERIA LEGAL - UFAF | U14: 0014 | V14: UFAF | W14: 0014. UFAF | X14: 5-23. BIENES Y SERVICIOS | Y14: 23 2 9 1 1 | Z14: LOCACIÓN DE SERVICIOS REALIZADOS POR PERSONA NATURAL | AA14: 23 2 9 1 1. LOCACIÓN DE SERVICIOS REALIZADOS POR PERSONA NATURAL | AB14: 8500 | AC14: 8500 | AD14: 0 | AE14: 8500 | AF14: 8500 | AG14: 0 | AH14: 8500 | AI14: 2026 | AJ14: 8500 | AK14: 0 | AL14: 0 | AM14: 0 | AN14: 0 | AO14: 0 | AP14: 0 | AQ14: 0 | AR14: 0 | AS14: 0 | AT14: 0 | AU14: 0 | AV14: CCP SIN SALDO | AW14: CCP DEVENGADO | AX14: LOCADOR
A15: 46035 | B15: 01. ENE | C15: APROBADO | D15: UFAF | E15: 01. PIA 2026 | F15: 3000001.ACCIONES COMUNES | G15: 5000276.GESTION DEL PROGRAMA | H15: LOCADORES | I15: NO RESTRINGIDA | J15: OFICINA NACIONAL | K15: UFAF | L15: 0000000025 | M15: 0000021 | N15: 16/01/2026 | O15: 10739875418 | P15: 0000000009 | 0000021 | QUISPE DE LA CRUZ ADRIANA ISABEL | Q15: 00 | R15: 0000000009 | S15: CCMN-002014: SERVICIO ESPECIALIZADO EN EJECUCION CONTRACTUAL PARA LA COORDINACION FUNCIONAL DE ABASTECIMIENTO | T15: 0000000009. CCMN-002014: SERVICIO ESPECIALIZADO EN EJECUCION CONTRACTUAL PARA LA COORDINACION FUNCIONAL DE ABASTECIMIENTO | U15: 0014 | V15: UFAF | W15: 0014. UFAF | X15: 5-23. BIENES Y SERVICIOS | Y15: 23 2 9 1 1 | Z15: LOCACIÓN DE SERVICIOS REALIZADOS POR PERSONA NATURAL | AA15: 23 2 9 1 1. LOCACIÓN DE SERVICIOS REALIZADOS POR PERSONA NATURAL | AB15: 7000 | AC15: 7000 | AD15: 0 | AE15: 7000 | AF15: 7000 | AG15: 0 | AH15: 7000 | AI15: 2026 | AJ15: 7000 | AK15: 0 | AL15: 0 | AM15: 0 | AN15: 0 | AO15: 0 | AP15: 0 | AQ15: 0 | AR15: 0 | AS15: 0 | AT15: 0 | AU15: 0 | AV15: CCP SIN SALDO | AW15: CCP DEVENGADO | AX15: LOCADOR
A16: 46035 | B16: 01. ENE | C16: APROBADO | D16: UFSMI | E16: 01. PIA 2026 | F16: 3000194.EMPLEO TEMPORAL GENERADO | G16: 5006296.SEGUIMIENTO DE LOS PROYECTOS Y ACTIVIDADES EN EJECUCION | H16: LOCADORES | I16: NO RESTRINGIDA | J16: OFICINA NACIONAL | K16: UFSMI | L16: 0000000014 | M16: 0000010 | N16: 16/01/2026 | O16: 10707573428 | P16: 0000000010 | 0000010 | LUNA COLLAZOS JUAN ARTURO | Q16: 00 | R16: 0000000010 | S16: CCMN-002001: SERVICIO DE SUPERVISION, SEGUIMIENTO Y MONITOREO A LA EJECUCION DE PROYECTOS DE INVERSION Y ACTIVIDA | T16: 0000000010. CCMN-002001: SERVICIO DE SUPERVISION, SEGUIMIENTO Y MONITOREO A LA EJECUCION DE PROYECTOS DE INVERSION Y ACTIVIDA | U16: 0056 | V16: UFSMI | W16: 0056. UFSMI | X16: 5-23. BIENES Y SERVICIOS | Y16: 23 2 9 1 1 | Z16: LOCACIÓN DE SERVICIOS REALIZADOS POR PERSONA NATURAL | AA16: 23 2 9 1 1. LOCACIÓN DE SERVICIOS REALIZADOS POR PERSONA NATURAL | AB16: 7000 | AC16: 7000 | AD16: 0 | AE16: 7000 | AF16: 7000 | AG16: 0 | AH16: 7000 | AI16: 2026 | AJ16: 7000 | AK16: 0 | AL16: 0 | AM16: 0 | AN16: 0 | AO16: 0 | AP16: 0 | AQ16: 0 | AR16: 0 | AS16: 0 | AT16: 0 | AU16: 0 | AV16: CCP SIN SALDO | AW16: CCP DEVENGADO | AX16: LOCADOR
A17: 46035 | B17: 01. ENE | C17: APROBADO | D17: UFSMI | E17: 01. PIA 2026 | F17: 3000194.EMPLEO TEMPORAL GENERADO | G17: 5006296.SEGUIMIENTO DE LOS PROYECTOS Y ACTIVIDADES EN EJECUCION | H17: LOCADORES | I17: NO RESTRINGIDA | J17: OFICINA NACIONAL | K17: UFSMI | L17: 0000000015 | M17: 0000011 | N17: 16/01/2026 | O17: 10710114108 | P17: 0000000011 | 0000011 | CRUZ ADRIANZEN LEONEL ANTONIO | Q17: 00 | R17: 0000000011 | S17: CCMN-002002: SERVICIO DE SUPERVISION, SEGUIMIENTO Y MONITOREO A LA EJECUCION DE PROYECTOS DE INVERSION Y ACTIVIDA | T17: 0000000011. CCMN-002002: SERVICIO DE SUPERVISION, SEGUIMIENTO Y MONITOREO A LA EJECUCION DE PROYECTOS DE INVERSION Y ACTIVIDA | U17: 0056 | V17: UFSMI | W17: 0056. UFSMI | X17: 5-23. BIENES Y SERVICIOS | Y17: 23 2 9 1 1 | Z17: LOCACIÓN DE SERVICIOS REALIZADOS POR PERSONA NATURAL | AA17: 23 2 9 1 1. LOCACIÓN DE SERVICIOS REALIZADOS POR PERSONA NATURAL | AB17: 7000 | AC17: 7000 | AD17: 0 | AE17: 7000 | AF17: 7000 | AG17: 0 | AH17: 7000 | AI17: 2026 | AJ17: 7000 | AK17: 0 | AL17: 0 | AM17: 0 | AN17: 0 | AO17: 0 | AP17: 0 | AQ17: 0 | AR17: 0 | AS17: 0 | AT17: 0 | AU17: 0 | AV17: CCP SIN SALDO | AW17: CCP DEVENGADO | AX17: LOCADOR
A18: 46035 | B18: 01. ENE | C18: APROBADO | D18: UFSMI | E18: 01. PIA 2026 | F18: 3000194.EMPLEO TEMPORAL GENERADO | G18: 5006296.SEGUIMIENTO DE LOS PROYECTOS Y ACTIVIDADES EN EJECUCION | H18: LOCADORES | I18: NO RESTRINGIDA | J18: OFICINA NACIONAL | K18: UFSMI | L18: 0000000016 | M18: 0000012 | N18: 16/01/2026 | O18: 10440018853 | P18: 0000000012 | 0000012 | HUIHUA BARREDA CESAR ARTURO | Q18: 00 | R18: 0000000012 | S18: CCMN-002003: SERVICIO DE SUPERVISION, SEGUIMIENTO Y MONITOREO A LA EJECUCION DE PROYECTOS DE INVERSION Y ACTIVIDA | T18: 0000000012. CCMN-002003: SERVICIO DE SUPERVISION, SEGUIMIENTO Y MONITOREO A LA EJECUCION DE PROYECTOS DE INVERSION Y ACTIVIDA | U18: 0056 | V18: UFSMI | W18: 0056. UFSMI | X18: 5-23. BIENES Y SERVICIOS | Y18: 23 2 9 1 1 | Z18: LOCACIÓN DE SERVICIOS REALIZADOS POR PERSONA NATURAL | AA18: 23 2 9 1 1. LOCACIÓN DE SERVICIOS REALIZADOS POR PERSONA NATURAL | AB18: 7000 | AC18: 7000 | AD18: 0 | AE18: 7000 | AF18: 7000 | AG18: 0 | AH18: 7000 | AI18: 2026 | AJ18: 7000 | AK18: 0 | AL18: 0 | AM18: 0 | AN18: 0 | AO18: 0 | AP18: 0 | AQ18: 0 | AR18: 0 | AS18: 0 | AT18: 0 | AU18: 0 | AV18: CCP SIN SALDO | AW18: CCP DEVENGADO | AX18: LOCADOR
... A306: 46038 | B306: 01. ENE | C306: APROBADO | D306: DE | E306: 01. PIA 2026 | F306: 3000001.ACCIONES COMUNES | G306: 5000276.GESTION DEL PROGRAMA | H306: LOCADORES | I306: NO RESTRINGIDA | J306: OFICINA NACIONAL | K306: DE | L306: 0000000035 | M306: 0000031 | N306: 16/01/2026 | O306: 10463982304 | P306: 0000000074 | 0000031 | HUDSON GOMEZ KEVIN ENRIQUE | Q306: 00 | R306: 0000000074 | S306: CCMN-002075: SERVICIO DE COORDINACION Y ELABORACION DE CONTENIDOS COMUNICACIONALES PARA LA DIRECCION EJECUTIVA DE | T306: 0000000074. CCMN-002075: SERVICIO DE COORDINACION Y ELABORACION DE CONTENIDOS COMUNICACIONALES PARA LA DIRECCION EJECUTIVA DE | U306: 0022 | V306: DE | W306: 0022. DE | X306: 5-23. BIENES Y SERVICIOS | Y306: 23 2 9 1 1 | Z306: LOCACIÓN DE SERVICIOS REALIZADOS POR PERSONA NATURAL | AA306: 23 2 9 1 1. LOCACIÓN DE SERVICIOS REALIZADOS POR PERSONA NATURAL | AB306: 5000 | AC306: 5000 | AD306: 0 | AE306: 5000 | AF306: 5000 | AG306: 0 | AH306: 5000 | AI306: 2026 | AJ306: 0 | AK306: 5000 | AL306: 0 | AM306: 0 | AN306: 0 | AO306: 0 | AP306: 0 | AQ306: 0 | AR306: 0 | AS306: 0 | AT306: 0 | AU306: 0 | AV306: CCP SIN SALDO | AW306: CCP DEVENGADO | AX306: LOCADOR
A307: 46038 | B307: 01. ENE | C307: APROBADO | D307: UFAF | E307: 01. PIA 2026 | F307: 3000001.ACCIONES COMUNES | G307: 5000276.GESTION DEL PROGRAMA | H307: LOCADORES | I307: NO RESTRINGIDA | J307: OFICINA NACIONAL | K307: UFAF | L307: - | M307: - | N307: - | O307: - | P307: 0000000075 | - | - | Q307: 00 | R307: 0000000075 | S307: CCMN-002071: SERVICIO DE ASISTENCIA AL SEGUIMIENTO Y NECESIDADES DE COMUNICACION | T307: 0000000075. CCMN-002071: SERVICIO DE ASISTENCIA AL SEGUIMIENTO Y NECESIDADES DE COMUNICACION | U307: 0014 | V307: UFAF | W307: 0014. UFAF | X307: 5-23. BIENES Y SERVICIOS | Y307: 23 2 9 1 1 | Z307: LOCACIÓN DE SERVICIOS REALIZADOS POR PERSONA NATURAL | AA307: 23 2 9 1 1. LOCACIÓN DE SERVICIOS REALIZADOS POR PERSONA NATURAL | AB307: 0 | AC307: 0 | AD307: 0 | AE307: 0 | AF307: 0 | AG307: 0 | AH307: 0 | AI307: 2026 | AJ307: 0 | AK307: 0 | AL307: 0 | AM307: 0 | AN307: 0 | AO307: 0 | AP307: 0 | AQ307: 0 | AR307: 0 | AS307: 0 | AT307: 0 | AU307: 0 | AV307: CCP ANULADO | AW307: CCP ANULADO | AX307: LOCADOR
A308: 46038 | B308: 01. ENE | C308: APROBADO | D308: UFAF | E308: 01. PIA 2026 | F308: 3000001.ACCIONES COMUNES | G308: 5000276.GESTION DEL PROGRAMA | H308: SERVICIOS DIVERSOS | I308: RESTRINGIDA | J308: UNIDADES TERRITORIALES | K308: UT HUANCAVELICA | L308: 0000000067 | M308: 0000062 | N308: 19/01/2026 | O308: 10712334610 | P308: 0000000076 | 0000062 | CCANTO HUIZA MARIA ISABEL | Q308: 00 | R308: 0000000076 | S308: CCMN-002076: SERVICIO DE MANTENIMIENTO Y LIMPIEZA DE LOCAL PARA LA UT HUANCAVELICA DEL PROGRAMA LLAMKASUN PERU | T308: 0000000076. CCMN-002076: SERVICIO DE MANTENIMIENTO Y LIMPIEZA DE LOCAL PARA LA UT HUANCAVELICA DEL PROGRAMA LLAMKASUN PERU | U308: 0008 | V308: UT HUANCAVELICA | W308: 0008. UT HUANCAVELICA | X308: 5-23. BIENES Y SERVICIOS | Y308: 23 2 71199 | Z308: SERVICIOS DIVERSOS | AA308: 23 2 71199. SERVICIOS DIVERSOS | AB308: 2600 | AC308: 2600 | AD308: 0 | AE308: 2600 | AF308: 2600 | AG308: 0 | AH308: 2600 | AI308: 2026 | AJ308: 0 | AK308: 1300 | AL308: 1300 | AM308: 0 | AN308: 0 | AO308: 0 | AP308: 0 | AQ308: 0 | AR308: 0 | AS308: 0 | AT308: 0 | AU308: 0 | AV308: CCP SIN SALDO | AW308: CCP DEVENGADO | AX308: LIMPIEZA DE LOCAL
A309: 46038 | B309: 01. ENE | C309: APROBADO | D309: UFAF | E309: 01. PIA 2026 | F309: 3000001.ACCIONES COMUNES | G309: 5000276.GESTION DEL PROGRAMA | H309: SERVICIOS DE LUZ, AGUA, INTERNET, TELF. FJA | I309: RESTRINGIDA | J309: UNIDADES TERRITORIALES | K309: UT HUANCAVELICA | L309: 0000000083 | M309: 0000080 | N309: 19/01/2026 | O309: 20129646099 | P309: 0000000077 | 0000080 | ELECTROCENTRO S.A. | Q309: 00 | R309: 0000000077 | S309: CCMN-002073: SERVICIO DE ENERGIA ELECTRICA PARA LA UNIDAD TERRITORIAL HUANCAVELICA | T309: 0000000077. CCMN-002073: SERVICIO DE ENERGIA ELECTRICA PARA LA UNIDAD TERRITORIAL HUANCAVELICA | U309: 0008 | V309: UT HUANCAVELICA | W309: 0008. UT HUANCAVELICA | X309: 5-23. BIENES Y SERVICIOS | Y309: 23 2 2 1 1 | Z309: SERVICIO DE SUMINISTRO DE ENERGIA ELECTRICA | AA309: 23 2 2 1 1. SERVICIO DE SUMINISTRO DE ENERGIA ELECTRICA | AB309: 6000 | AC309: 6000 | AD309: 0 | AE309: 6000 | AF309: 2614.5 | AG309: 3385.5 | AH309: 2614.5 | AI309: 2026 | AJ309: 302.8 | AK309: 0 | AL309: 662.9 | AM309: 0 | AN309: 436.3 | AO309: 1636.3 | AP309: -423.8 | AQ309: 0 | AR309: 0 | AS309: 0 | AT309: 0 | AU309: 0 | AV309: CCP SIN SALDO | AW309: CCP POR DEVENGAR | AX309: -
A310: 46038 | B310: 01. ENE | C310: APROBADO | D310: UFRH | E310: 01. PIA 2026 | F310: 3000001.ACCIONES COMUNES | G310: 5000276.GESTION DEL PROGRAMA | H310: LOCADORES | I310: NO RESTRINGIDA | J310: OFICINA NACIONAL | K310: UFRH | L310: 0000000052 | M310: 0000044 | N310: 16/01/2026 | O310: 10406948311 | P310: 0000000078 | 0000044 | MANRIQUE HENRIQUEZ WILLIAM ERIC | Q310: 00 | R310: 0000000078 | S310: CCMN-002078: SERVICIO DE ELABORACION Y REVISION DE DOCUMENTOS ADMINISTRATIVOS PARA LA UNIDAD FUNCIONAL DE RECURSO | T310: 0000000078. CCMN-002078: SERVICIO DE ELABORACION Y REVISION DE DOCUMENTOS ADMINISTRATIVOS PARA LA UNIDAD FUNCIONAL DE RECURSO | U310: 0018 | V310: UFRH | W310: 0018. UFRH | X310: 5-23. BIENES Y SERVICIOS | Y310: 23 2 9 1 1 | Z310: LOCACIÓN DE SERVICIOS REALIZADOS POR PERSONA NATURAL | AA310: 23 2 9 1 1. LOCACIÓN DE SERVICIOS REALIZADOS POR PERSONA NATURAL | AB310: 9000 | AC310: 9000 | AD310: 0 | AE310: 9000 | AF310: 9000 | AG310: 0 | AH310: 9000 | AI310: 2026 | AJ310: 0 | AK310: 4500 | AL310: 4500 | AM310: 0 | AN310: 0 | AO310: 0 | AP310: 0 | AQ310: 0 | AR310: 0 | AS310: 0 | AT310: 0 | AU310: 0 | AV310: CCP SIN SALDO | AW310: CCP DEVENGADO | AX310: LOCADOR
A311: 46038 | B311: 01. ENE | C311: APROBADO | D311: UFTI | E311: 01. PIA 2026 | F311: 3000001.ACCIONES COMUNES | G311: 5000276.GESTION DEL PROGRAMA | H311: LOCADORES | I311: NO RESTRINGIDA | J311: OFICINA NACIONAL | K311: UFTI | L311: 0000000057 | M311: 0000051 | N311: 16/01/2026 | O311: 10453258411 | P311: 0000000079 | 0000051 | ABANTO MALDONADO CESAR DANIEL | Q311: 00 | R311: 0000000079 | S311: CCMN-002079: SERVICIO DE COORDINACION DE INFRAESTRUCTURA Y SOPORTE DE TECNOLOGIAS | T311: 0000000079. CCMN-002079: SERVICIO DE COORDINACION DE INFRAESTRUCTURA Y SOPORTE DE TECNOLOGIAS | U311: 0019 | V311: UFTI | W311: 0019. UFTI | X311: 5-23. BIENES Y SERVICIOS | Y311: 23 2 9 1 1 | Z311: LOCACIÓN DE SERVICIOS REALIZADOS POR PERSONA NATURAL | AA311: 23 2 9 1 1. LOCACIÓN DE SERVICIOS REALIZADOS POR PERSONA NATURAL | AB311: 18000 | AC311: 18000 | AD311: 0 | AE311: 18000 | AF311: 18000 | AG311: 0 | AH311: 18000 | AI311: 2026 | AJ311: 0 | AK311: 6000 | AL311: 12000 | AM311: 0 | AN311: 0 | AO311: 0 | AP311: 0 | AQ311: 0 | AR311: 0 | AS311: 0 | AT311: 0 | AU311: 0 | AV311: CCP SIN SALDO | AW311: CCP DEVENGADO | AX311: LOCADOR
A312: 46038 | B312: 01. ENE | C312: APROBADO | D312: UFAF | E312: 01. PIA 2026 | F312: 3000001.ACCIONES COMUNES | G312: 5000276.GESTION DEL PROGRAMA | H312: LOCADORES | I312: NO RESTRINGIDA | J312: UNIDADES TERRITORIALES | K312: UT LIMA CENTRO - CALLAO | L312: 0000000040 | M312: 0000056 | N312: 16/01/2026 | O312: 10729261225 | P312: 0000000080 | 0000056 | VILLENA MARCELO JIMMY JHOEL | Q312: 00 | R312: 0000000080 | S312: CCMN-002080: SERVICIO DE ORGANIZACION, FOLIACION E INVENTARIO DEL ACERVO DOCUMENTARIO UT LIMA CENTRO -CALLAO | T312: 0000000080. CCMN-002080: SERVICIO DE ORGANIZACION, FOLIACION E INVENTARIO DEL ACERVO DOCUMENTARIO UT LIMA CENTRO -CALLAO | U312: 0021 | V312: UT LIMA CENTRO - CALLAO | W312: 0021. UT LIMA CENTRO - CALLAO | X312: 5-23. BIENES Y SERVICIOS | Y312: 23 2 9 1 1 | Z312: LOCACIÓN DE SERVICIOS REALIZADOS POR PERSONA NATURAL | AA312: 23 2 9 1 1. LOCACIÓN DE SERVICIOS REALIZADOS POR PERSONA NATURAL | AB312: 7500 | AC312: 7500 | AD312: 0 | AE312: 7500 | AF312: 7500 | AG312: 0 | AH312: 7500 | AI312: 2026 | AJ312: 0 | AK312: 2500 | AL312: 2500 | AM312: 2500 | AN312: 0 | AO312: 0 | AP312: 0 | AQ312: 0 | AR312: 0 | AS312: 0 | AT312: 0 | AU312: 0 | AV312: CCP SIN SALDO | AW312: CCP DEVENGADO | AX312: ADMINISTRATIVO / ARCHIVO
A313: 46038 | B313: 01. ENE | C313: APROBADO | D313: UFRH | E313: 01. PIA 2026 | F313: 3000001.ACCIONES COMUNES | G313: 5000276.GESTION DEL PROGRAMA | H313: LOCADORES | I313: NO RESTRINGIDA | J313: OFICINA NACIONAL | K313: UFRH | L313: 0000000053 | M313: 0000045 | N313: 16/01/2026 | O313: 10720943536 | P313: 0000000081 | 0000045 | GALVEZ SALDAÑA DAVID GUILLERMO | Q313: 00 | R313: 0000000081 | S313: CCMN-002081: SERVICIO DE ASISTENCIA TECNICA EN LA GESTION DE RECURSOS HUMANOS, PARA LA UNIDAD FUNCIONAL DE RECURS | T313: 0000000081. CCMN-002081: SERVICIO DE ASISTENCIA TECNICA EN LA GESTION DE RECURSOS HUMANOS, PARA LA UNIDAD FUNCIONAL DE RECURS | U313: 0018 | V313: UFRH | W313: 0018. UFRH | X313: 5-23. BIENES Y SERVICIOS | Y313: 23 2 9 1 1 | Z313: LOCACIÓN DE SERVICIOS REALIZADOS POR PERSONA NATURAL | AA313: 23 2 9 1 1. LOCACIÓN DE SERVICIOS REALIZADOS POR PERSONA NATURAL | AB313: 9000 | AC313: 9000 | AD313: 0 | AE313: 9000 | AF313: 9000 | AG313: 0 | AH313: 9000 | AI313: 2026 | AJ313: 0 | AK313: 4500 | AL313: 4500 | AM313: 0 | AN313: 0 | AO313: 0 | AP313: 0 | AQ313: 0 | AR313: 0 | AS313: 0 | AT313: 0 | AU313: 0 | AV313: CCP SIN SALDO | AW313: CCP DEVENGADO | AX313: LOCADOR
A314: 46038 | B314: 01. ENE | C314: APROBADO | D314: UFRH | E314: 01. PIA 2026 | F314: 3000001.ACCIONES COMUNES | G314: 5000276.GESTION DEL PROGRAMA | H314: LOCADORES | I314: NO RESTRINGIDA | J314: OFICINA NACIONAL | K314: UFRH | L314: 0000000054 | M314: 0000046 | N314: 16/01/2026 | O314: 10446025118 | P314: 0000000082 | 0000046 | LECCA CHAVEZ AUREA FIORELLA | Q314: 00 | R314: 0000000082 | S314: CCMN-002082: SERVICIO DE SEGUIMIENTO Y PROCESAMIENTO DE LA IMPLEMENTACION DEL MODELO DE INTEGRIDAD PARA LA UNIDAD | T314: 0000000082. CCMN-002082: SERVICIO DE SEGUIMIENTO Y PROCESAMIENTO DE LA IMPLEMENTACION DEL MODELO DE INTEGRIDAD PARA LA UNIDAD | U314: 0018 | V314: UFRH | W314: 0018. UFRH | X314: 5-23. BIENES Y SERVICIOS | Y314: 23 2 9 1 1 | Z314: LOCACIÓN DE SERVICIOS REALIZADOS POR PERSONA NATURAL | AA314: 23 2 9 1 1. LOCACIÓN DE SERVICIOS REALIZADOS POR PERSONA NATURAL | AB314: 16000 | AC314: 16000 | AD314: 0 | AE314: 16000 | AF314: 16000 | AG314: 0 | AH314: 16000 | AI314: 2026 | AJ314: 0 | AK314: 8000 | AL314: 8000 | AM314: 0 | AN314: 0 | AO314: 0 | AP314: 0 | AQ314: 0 | AR314: 0 | AS314: 0 | AT314: 0 | AU314: 0 | AV314: CCP SIN SALDO | AW314: CCP DEVENGADO | AX314: LOCADOR
A315: 46038 | B315: 01. ENE | C315: APROBADO | D315: UFAF | E315: 01. PIA 2026 | F315: 3000001.ACCIONES COMUNES | G315: 5000276.GESTION DEL PROGRAMA | H315: SERVICIOS DIVERSOS | I315: RESTRINGIDA | J315: UNIDADES TERRITORIALES | K315: UT LORETO | L315: 0000000066 | M315: 0000060 | N315: 19/01/2026 | O315: 10053206170 | P315: 0000000083 | 0000060 | ARIMUYA MORALES ROSARIO | Q315: 00 | R315: 0000000083 | S315: CCMN-002083: SERVICIO DE MANTENIMIENTO Y LIMPIEZA DE LOCAL PARA LA UNIDAD TERRITORIAL LORETO DEL PROGRAMA DE EMPL | T315: 0000000083. CCMN-002083: SERVICIO DE MANTENIMIENTO Y LIMPIEZA DE LOCAL PARA LA UNIDAD TERRITORIAL LORETO DEL PROGRAMA DE EMPL | U315: 0023 | V315: UT LORETO | W315: 0023. UT LORETO | X315: 5-23. BIENES Y SERVICIOS | Y315: 23 2 71199 | Z315: SERVICIOS DIVERSOS | AA315: 23 2 71199. SERVICIOS DIVERSOS | AB315: 2600 | AC315: 2600 | AD315: 0 | AE315: 2600 | AF315: 2600 | AG315: 0 | AH315: 2600 | AI315: 2026 | AJ315: 0 | AK315: 1300 | AL315: 1300 | AM315: 0 | AN315: 0 | AO315: 0 | AP315: 0 | AQ315: 0 | AR315: 0 | AS315: 0 | AT315: 0 | AU315: 0 | AV315: CCP SIN SALDO | AW315: CCP DEVENGADO | AX315: LIMPIEZA DE LOCAL
A316: 46038 | B316: 01. ENE | C316: APROBADO | D316: UFTI | E316: 01. PIA 2026 | F316: 3000001.ACCIONES COMUNES | G316: 5000276.GESTION DEL PROGRAMA | H316: LOCADORES | I316: NO RESTRINGIDA | J316: OFICINA NACIONAL | K316: UFTI | L316: 0000000061 | M316: 0000055 | N316: 16/01/2026 | O316: 10702328239 | P316: 0000000084 | 0000055 | BARZOLA GONZALES HECTOR RONALDO | Q316: 00 | R316: 0000000084 | S316: CCMN-002077: SERVICIO PROGRAMACION DE APLICACIONES INFORMATICAS PARA LA UNIDAD FUNCIONAL DE TECNOLOGIAS | T316: 0000000084. CCMN-002077: SERVICIO PROGRAMACION DE APLICACIONES INFORMATICAS PARA LA UNIDAD FUNCIONAL DE TECNOLOGIAS | U316: 0019 | V316: UFTI | W316: 0019. UFTI | X316: 5-23. BIENES Y SERVICIOS | Y316: 23 2 9 1 1 | Z316: LOCACIÓN DE SERVICIOS REALIZADOS POR PERSONA NATURAL | AA316: 23 2 9 1 1. LOCACIÓN DE SERVICIOS REALIZADOS POR PERSONA NATURAL | AB316: 18000 | AC316: 18000 | AD316: 0 | AE316: 18000 | AF316: 18000 | AG316: 0 | AH316: 18000 | AI316: 2026 | AJ316: 0 | AK316: 6000 | AL316: 6000 | AM316: 6000 | AN316: 0 | AO316: 0 | AP316: 0 | AQ316: 0 | AR316: 0 | AS316: 0 | AT316: 0 | AU316: 0 | AV316: CCP SIN SALDO | AW316: CCP DEVENGADO | AX316: LOCADOR
A317: 46038 | B317: 01. ENE | C317: APROBADO | D317: UFTI | E317: 01. PIA 2026 | F317: 3000001.ACCIONES COMUNES | G317: 5000276.GESTION DEL PROGRAMA | H317: LOCADORES | I317: NO RESTRINGIDA | J317: OFICINA NACIONAL | K317: UFTI | L317: 0000000060 | M317: 0000054 | N317: 16/01/2026 | O317: 10791823434 | P317: 0000000085 | 0000054 | CARLOS VASQUEZ JOAN ROY | Q317: 00 | R317: 0000000085 | S317: CCMN-002085: SERVICIO PROGRAMACION DE APLICACIONES INFORMATICAS UFTI | T317: 0000000085. CCMN-002085: SERVICIO PROGRAMACION DE APLICACIONES INFORMATICAS UFTI | U317: 0019 | V317: UFTI | W317: 0019. UFTI | X317: 5-23. BIENES Y SERVICIOS | Y317: 23 2 9 1 1 | Z317: LOCACIÓN DE SERVICIOS REALIZADOS POR PERSONA NATURAL | AA317: 23 2 9 1 1. LOCACIÓN DE SERVICIOS REALIZADOS POR PERSONA NATURAL | AB317: 18000 | AC317: 18000 | AD317: 0 | AE317: 18000 | AF317: 18000 | AG317: 0 | AH317: 18000 | AI317: 2026 | AJ317: 0 | AK317: 6000 | AL317: 6000 | AM317: 6000 | AN317: 0 | AO317: 0 | AP317: 0 | AQ317: 0 | AR317: 0 | AS317: 0 | AT317: 0 | AU317: 0 | AV317: CCP SIN SALDO | AW317: CCP DEVENGADO | AX317: LOCADOR
A318: 46038 | B318: 01. ENE | C318: APROBADO | D318: UFAF | E318: 01. PIA 2026 | F318: 3000001.ACCIONES COMUNES | G318: 5000276.GESTION DEL PROGRAMA | H318: SERVICIOS DE LUZ, AGUA, INTERNET, TELF. FJA | I318: RESTRINGIDA | J318: UNIDADES TERRITORIALES | K318: UT LORETO | L318: 0000000101 | M318: 0000095 | N318: 20/01/2026 | O318: 20103795631 | P318: 0000000086 | 0000095 | EMP REG DE SERV PUBLICO DE ELECTRICIDAD | Q318: 00 | R318: 0000000086 | S318: CCMN-002084: SERVICIO DE ENERGIA ELECTRICA UT LORETO - ENE - DIC 2026 | T318: 0000000086. CCMN-002084: SERVICIO DE ENERGIA ELECTRICA UT LORETO - ENE - DIC 2026 | U318: 0023 | V318: UT LORETO | W318: 0023. UT LORETO | X318: 5-23. BIENES Y SERVICIOS | Y318: 23 2 2 1 1 | Z318: SERVICIO DE SUMINISTRO DE ENERGIA ELECTRICA | AA318: 23 2 2 1 1. SERVICIO DE SUMINISTRO DE ENERGIA ELECTRICA | AB318: 10800 | AC318: 10800 | AD318: 0 | AE318: 10800 | AF318: 3588.5 | AG318: 7211.5 | AH318: 3588.5 | AI318: 2026 | AJ318: 726.5 | AK318: 401 | AL318: 342 | AM318: 593 | AN318: 547 | AO318: 455.5 | AP318: 523.5 | AQ318: 0 | AR318: 0 | AS318: 0 | AT318: 0 | AU318: 0 | AV318: CCP SIN SALDO | AW318: CCP POR DEVENGAR | AX318: -
A319: 46038 | B319: 01. ENE | C319: APROBADO | D319: UFTI | E319: 01. PIA 2026 | F319: 3000001.ACCIONES COMUNES | G319: 5000276.GESTION DEL PROGRAMA | H319: LOCADORES | I319: NO RESTRINGIDA | J319: OFICINA NACIONAL | K319: UFTI | L319: 0000000068 | M319: 0000063 | N319: 19/01/2026 | O319: 10157376212 | P319: 0000000087 | 0000063 | LUYO ORTIZ JESSICA ROSEMERY | Q319: 00 | R319: 0000000087 | S319: CCMN-002086: ASISTENCIA TECNICA ADMINISTRATIVA PARA UFTI DEL PROGRAMA LLAMKASUN PERU | T319: 0000000087. CCMN-002086: ASISTENCIA TECNICA ADMINISTRATIVA PARA UFTI DEL PROGRAMA LLAMKASUN PERU | U319: 0019 | V319: UFTI | W319: 0019. UFTI | X319: 5-23. BIENES Y SERVICIOS | Y319: 23 2 9 1 1 | Z319: LOCACIÓN DE SERVICIOS REALIZADOS POR PERSONA NATURAL | AA319: 23 2 9 1 1. LOCACIÓN DE SERVICIOS REALIZADOS POR PERSONA NATURAL | AB319: 9000 | AC319: 9000 | AD319: 0 | AE319: 9000 | AF319: 9000 | AG319: 0 | AH319: 9000 | AI319: 2026 | AJ319: 0 | AK319: 3000 | AL319: 3000 | AM319: 3000 | AN319: 0 | AO319: 0 | AP319: 0 | AQ319: 0 | AR319: 0 | AS319: 0 | AT319: 0 | AU319: 0 | AV319: CCP SIN SALDO | AW319: CCP DEVENGADO | AX319: LOCADOR
... A491: 46045 | B491: 01. ENE | C491: APROBADO | D491: UFGP | E491: 01. PIA 2026 | F491: 3000194.EMPLEO TEMPORAL GENERADO | G491: 5006296.SEGUIMIENTO DE LOS PROYECTOS Y ACTIVIDADES EN EJECUCION | H491: PASAJES Y VIATICOS | I491: NO RESTRINGIDA | J491: OFICINA NACIONAL | K491: UFGP | L491: 0000001211 | M491: 0000537 | N491: 01/04/2026 | O491: 20603446543 | P491: 0000000207 | 0000537 | SKY AIRLINE PERU S.A.C. | Q491: 00 | R491: 0000000207 | S491: CCMN-002157: CONTRATACION DEL SERVICIO DE TRANSPORTE AEREO PARA LA COMISION DEL PERSONAL DE LLAMKASUN PERU A TRAV | T491: 0000000207. CCMN-002157: CONTRATACION DEL SERVICIO DE TRANSPORTE AEREO PARA LA COMISION DEL PERSONAL DE LLAMKASUN PERU A TRAV | U491: 0058 | V491: UFGP | W491: 0058. UFGP | X491: 5-23. BIENES Y SERVICIOS | Y491: 23 2 1 2 1 | Z491: PASAJES Y GASTOS DE TRANSPORTE | AA491: 23 2 1 2 1. PASAJES Y GASTOS DE TRANSPORTE | AB491: 15680 | AC491: 15680 | AD491: 0 | AE491: 4735.47 | AF491: 4735.47 | AG491: 10944.53 | AH491: 4735.47 | AI491: 2026 | AJ491: 0 | AK491: 0 | AL491: 0 | AM491: 920.51 | AN491: 0 | AO491: 1862.49 | AP491: 1952.47 | AQ491: 0 | AR491: 0 | AS491: 0 | AT491: 0 | AU491: 0 | AV491: CCP SIN SALDO | AW491: CCP POR DEVENGAR | AX491: -
A492: 46045 | B492: 01. ENE | C492: APROBADO | D492: UFGP | E492: 01. PIA 2026 | F492: 3000194.EMPLEO TEMPORAL GENERADO | G492: 5006296.SEGUIMIENTO DE LOS PROYECTOS Y ACTIVIDADES EN EJECUCION | H492: PASAJES Y VIATICOS | I492: NO RESTRINGIDA | J492: OFICINA NACIONAL | K492: UFGP | L492: - | M492: - | N492: - | O492: - | P492: 0000000208 | - | - | Q492: 00 | R492: 0000000208 | S492: CCMN-002158: CONTRATACION DEL SERVICIO DE TRANSPORTE AEREO PARA LA COMISION DEL PERSONAL DE LLAMKASUN PERU A TRAV | T492: 0000000208. CCMN-002158: CONTRATACION DEL SERVICIO DE TRANSPORTE AEREO PARA LA COMISION DEL PERSONAL DE LLAMKASUN PERU A TRAV | U492: 0058 | V492: UFGP | W492: 0058. UFGP | X492: 5-23. BIENES Y SERVICIOS | Y492: 23 2 1 2 1 | Z492: PASAJES Y GASTOS DE TRANSPORTE | AA492: 23 2 1 2 1. PASAJES Y GASTOS DE TRANSPORTE | AB492: 6720 | AC492: 6720 | AD492: 0 | AE492: 0 | AF492: 0 | AG492: 6720 | AH492: 0 | AI492: 2026 | AJ492: 0 | AK492: 0 | AL492: 0 | AM492: 0 | AN492: 0 | AO492: 0 | AP492: 0 | AQ492: 0 | AR492: 0 | AS492: 0 | AT492: 0 | AU492: 0 | AV492: CCP SIN SALDO | AW492: CCP POR DEVENGAR | AX492: -
A493: 46045 | B493: 01. ENE | C493: APROBADO | D493: UFGP | E493: 01. PIA 2026 | F493: 3000194.EMPLEO TEMPORAL GENERADO | G493: 5006296.SEGUIMIENTO DE LOS PROYECTOS Y ACTIVIDADES EN EJECUCION | H493: PASAJES Y VIATICOS | I493: NO RESTRINGIDA | J493: OFICINA NACIONAL | K493: UFGP | L493: 0000002072 | M493: 0000905 | N493: 09/07/2026 | O493: 20100010721 | P493: 0000000209 | 0000905 | AERO TRANSPORTE S A | Q493: 00 | R493: 0000000209 | S493: CCMN-002159: CONTRATACION DEL SERVICIO DE TRANSPORTE AEREO PARA LA COMISION DEL PERSONAL DE LLAMKASUN PERU A TRAV | T493: 0000000209. CCMN-002159: CONTRATACION DEL SERVICIO DE TRANSPORTE AEREO PARA LA COMISION DEL PERSONAL DE LLAMKASUN PERU A TRAV | U493: 0058 | V493: UFGP | W493: 0058. UFGP | X493: 5-23. BIENES Y SERVICIOS | Y493: 23 2 1 2 1 | Z493: PASAJES Y GASTOS DE TRANSPORTE | AA493: 23 2 1 2 1. PASAJES Y GASTOS DE TRANSPORTE | AB493: 4480 | AC493: 4480 | AD493: 0 | AE493: 1160.62 | AF493: 1160.62 | AG493: 3319.38 | AH493: 1160.62 | AI493: 2026 | AJ493: 0 | AK493: 0 | AL493: 0 | AM493: 0 | AN493: 0 | AO493: 0 | AP493: 1160.62 | AQ493: 0 | AR493: 0 | AS493: 0 | AT493: 0 | AU493: 0 | AV493: CCP SIN SALDO | AW493: CCP POR DEVENGAR | AX493: -
A494: 46045 | B494: 01. ENE | C494: APROBADO | D494: UFAF | E494: 01. PIA 2026 | F494: 3000001.ACCIONES COMUNES | G494: 5000276.GESTION DEL PROGRAMA | H494: SEGUROS | I494: NO RESTRINGIDA | J494: OFICINA NACIONAL | K494: UFAF | L494: 0000000187 | M494: 0000175 | N494: 26/01/2026 | O494: 20517207331 | P494: 0000000210 | 0000175 | PROTECTA S.A. COMPAÑIA DE SEGUROS Y REASEGUROS | Q494: 00 | R494: 0000000210 | S494: CCMN-000078: SERVICIO DE SEGURO OBLIGATORIO DE ACCIDENTES DE TRANSITO (SOAT) PARA (24) VEINTICUATRO UNIDADES VEHI | T494: 0000000210. CCMN-000078: SERVICIO DE SEGURO OBLIGATORIO DE ACCIDENTES DE TRANSITO (SOAT) PARA (24) VEINTICUATRO UNIDADES VEHI | U494: 0014 | V494: UFAF | W494: 0014. UFAF | X494: 5-23. BIENES Y SERVICIOS | Y494: 23 2 6 3 3 | Z494: SEGURO OBLIGATORIO ACCIDENTES DE TRANSITO (SOAT) | AA494: 23 2 6 3 3. SEGURO OBLIGATORIO ACCIDENTES DE TRANSITO (SOAT) | AB494: 3200 | AC494: 3200 | AD494: 0 | AE494: 3200 | AF494: 3200 | AG494: 0 | AH494: 3200 | AI494: 2026 | AJ494: 0 | AK494: 0 | AL494: 0 | AM494: 0 | AN494: 0 | AO494: 3200 | AP494: 0 | AQ494: 0 | AR494: 0 | AS494: 0 | AT494: 0 | AU494: 0 | AV494: CCP SIN SALDO | AW494: CCP DEVENGADO | AX494: -
A495: 46045 | B495: 01. ENE | C495: APROBADO | D495: UFGI | E495: 01. PIA 2026 | F495: 3000194.EMPLEO TEMPORAL GENERADO | G495: 5006295.PROMOCION DE MODALIDADES DE INTERVENCION DEL PROGRAMA PARA DESARROLLO DE PROYECTOS Y ACTIVIDADES INTENSIVOS EN MANO DE OBRA NO CALIFICADA | H495: PASAJES Y VIATICOS | I495: NO RESTRINGIDA | J495: OFICINA NACIONAL | K495: UFGI | L495: 0000001179 | M495: 0000520 | N495: 26/03/2026 | O495: 20341841357 | P495: 0000000211 | 0000520 | LATAM AIRLINES PERU S.A. | Q495: 00 | R495: 0000000211 | S495: CCMN-002160: CONTRATACION DEL SERVICIO DE TRANSPORTE AEREO PARA LA COMISION DEL PERSONAL DE LLAMKASUN PERU A TRAV | T495: 0000000211. CCMN-002160: CONTRATACION DEL SERVICIO DE TRANSPORTE AEREO PARA LA COMISION DEL PERSONAL DE LLAMKASUN PERU A TRAV | U495: 0039 | V495: UFGI | W495: 0039. UFGI | X495: 5-23. BIENES Y SERVICIOS | Y495: 23 2 1 2 1 | Z495: PASAJES Y GASTOS DE TRANSPORTE | AA495: 23 2 1 2 1. PASAJES Y GASTOS DE TRANSPORTE | AB495: 22320 | AC495: 22320 | AD495: 0 | AE495: 4104.64 | AF495: 4104.64 | AG495: 18215.36 | AH495: 4104.64 | AI495: 2026 | AJ495: 0 | AK495: 0 | AL495: 0 | AM495: 1939.74 | AN495: 0 | AO495: 991.17 | AP495: 1173.73 | AQ495: 0 | AR495: 0 | AS495: 0 | AT495: 0 | AU495: 0 | AV495: CCP SIN SALDO | AW495: CCP POR DEVENGAR | AX495: -
A496: 46045 | B496: 01. ENE | C496: APROBADO | D496: UFGI | E496: 01. PIA 2026 | F496: 3000194.EMPLEO TEMPORAL GENERADO | G496: 5006295.PROMOCION DE MODALIDADES DE INTERVENCION DEL PROGRAMA PARA DESARROLLO DE PROYECTOS Y ACTIVIDADES INTENSIVOS EN MANO DE OBRA NO CALIFICADA | H496: PASAJES Y VIATICOS | I496: NO RESTRINGIDA | J496: OFICINA NACIONAL | K496: UFGI | L496: - | M496: - | N496: - | O496: - | P496: 0000000212 | - | - | Q496: 00 | R496: 0000000212 | S496: CCMN-002161: CONTRATACION DEL SERVICIO DE TRANSPORTE AEREO PARA LA COMISION DEL PERSONAL DE LLAMKASUN PERU A TRAV | T496: 0000000212. CCMN-002161: CONTRATACION DEL SERVICIO DE TRANSPORTE AEREO PARA LA COMISION DEL PERSONAL DE LLAMKASUN PERU A TRAV | U496: 0039 | V496: UFGI | W496: 0039. UFGI | X496: 5-23. BIENES Y SERVICIOS | Y496: 23 2 1 2 1 | Z496: PASAJES Y GASTOS DE TRANSPORTE | AA496: 23 2 1 2 1. PASAJES Y GASTOS DE TRANSPORTE | AB496: 19530 | AC496: 19530 | AD496: 0 | AE496: 0 | AF496: 0 | AG496: 19530 | AH496: 0 | AI496: 2026 | AJ496: 0 | AK496: 0 | AL496: 0 | AM496: 0 | AN496: 0 | AO496: 0 | AP496: 0 | AQ496: 0 | AR496: 0 | AS496: 0 | AT496: 0 | AU496: 0 | AV496: CCP SIN SALDO | AW496: CCP POR DEVENGAR | AX496: -
A497: 46045 | B497: 01. ENE | C497: APROBADO | D497: UFGI | E497: 01. PIA 2026 | F497: 3000194.EMPLEO TEMPORAL GENERADO | G497: 5006295.PROMOCION DE MODALIDADES DE INTERVENCION DEL PROGRAMA PARA DESARROLLO DE PROYECTOS Y ACTIVIDADES INTENSIVOS EN MANO DE OBRA NO CALIFICADA | H497: PASAJES Y VIATICOS | I497: NO RESTRINGIDA | J497: OFICINA NACIONAL | K497: UFGI | L497: 0000002070 | M497: 0000903 | N497: 09/07/2026 | O497: 20342868844 | P497: 0000000213 | 0000903 | STAR UP S.A.C. | Q497: 00 | R497: 0000000213 | S497: CCMN-002162: CONTRATACION DEL SERVICIO DE TRANSPORTE AEREO PARA LA COMISION DEL PERSONAL DE LLAMKASUN PERU A TRAV | T497: 0000000213. CCMN-002162: CONTRATACION DEL SERVICIO DE TRANSPORTE AEREO PARA LA COMISION DEL PERSONAL DE LLAMKASUN PERU A TRAV | U497: 0039 | V497: UFGI | W497: 0039. UFGI | X497: 5-23. BIENES Y SERVICIOS | Y497: 23 2 1 2 1 | Z497: PASAJES Y GASTOS DE TRANSPORTE | AA497: 23 2 1 2 1. PASAJES Y GASTOS DE TRANSPORTE | AB497: 8370 | AC497: 8370 | AD497: 0 | AE497: 767.36 | AF497: 767.36 | AG497: 7602.64 | AH497: 767.36 | AI497: 2026 | AJ497: 0 | AK497: 0 | AL497: 0 | AM497: 0 | AN497: 0 | AO497: 0 | AP497: 767.36 | AQ497: 0 | AR497: 0 | AS497: 0 | AT497: 0 | AU497: 0 | AV497: CCP SIN SALDO | AW497: CCP POR DEVENGAR | AX497: -
A498: 46045 | B498: 01. ENE | C498: APROBADO | D498: UFGI | E498: 01. PIA 2026 | F498: 3000194.EMPLEO TEMPORAL GENERADO | G498: 5006295.PROMOCION DE MODALIDADES DE INTERVENCION DEL PROGRAMA PARA DESARROLLO DE PROYECTOS Y ACTIVIDADES INTENSIVOS EN MANO DE OBRA NO CALIFICADA | H498: PASAJES Y VIATICOS | I498: NO RESTRINGIDA | J498: OFICINA NACIONAL | K498: UFGI | L498: 0000002074 | M498: 0000907 | N498: 09/07/2026 | O498: 20100010721 | P498: 0000000214 | 0000907 | AERO TRANSPORTE S A | Q498: 00 | R498: 0000000214 | S498: CCMN-002163: CONTRATACION DEL SERVICIO DE TRANSPORTE AEREO PARA LA COMISION DEL PERSONAL DE LLAMKASUN PERU A TRAV | T498: 0000000214. CCMN-002163: CONTRATACION DEL SERVICIO DE TRANSPORTE AEREO PARA LA COMISION DEL PERSONAL DE LLAMKASUN PERU A TRAV | U498: 0039 | V498: UFGI | W498: 0039. UFGI | X498: 5-23. BIENES Y SERVICIOS | Y498: 23 2 1 2 1 | Z498: PASAJES Y GASTOS DE TRANSPORTE | AA498: 23 2 1 2 1. PASAJES Y GASTOS DE TRANSPORTE | AB498: 5580 | AC498: 5580 | AD498: 0 | AE498: 580.31 | AF498: 580.31 | AG498: 4999.69 | AH498: 580.31 | AI498: 2026 | AJ498: 0 | AK498: 0 | AL498: 0 | AM498: 0 | AN498: 0 | AO498: 0 | AP498: 580.31 | AQ498: 0 | AR498: 0 | AS498: 0 | AT498: 0 | AU498: 0 | AV498: CCP SIN SALDO | AW498: CCP POR DEVENGAR | AX498: -
A499: 46048 | B499: 01. ENE | C499: APROBADO | D499: UFAF | E499: 01. PIA 2026 | F499: 3000001.ACCIONES COMUNES | G499: 5000276.GESTION DEL PROGRAMA | H499: ALQUILER DE LOCAL | I499: NO RESTRINGIDA | J499: UNIDADES TERRITORIALES | K499: UT ANCASH | L499: 0000000237 | M499: 0000220 | N499: 30/01/2026 | O499: 10316510758 | P499: 0000000215 | 0000220 | CABELLO ANTUNEZ CESAR MARINO | Q499: 00 | R499: 0000000215 | S499: CCMN-002165: CONTRATACION DEL SERVICIO DE ALQUILER DE COCHERA PARA EL VEHICULO INSTITUCIONAL ASIGNADO A LA UNID | T499: 0000000215. CCMN-002165: CONTRATACION DEL SERVICIO DE ALQUILER DE COCHERA PARA EL VEHICULO INSTITUCIONAL ASIGNADO A LA UNID | U499: 0002 | V499: UT ANCASH | W499: 0002. UT ANCASH | X499: 5-23. BIENES Y SERVICIOS | Y499: 23 2 5 1 1 | Z499: DE EDIFICIOS Y ESTRUCTURAS | AA499: 23 2 5 1 1. DE EDIFICIOS Y ESTRUCTURAS | AB499: 3600 | AC499: 3600 | AD499: 0 | AE499: 3600 | AF499: 1800 | AG499: 1800 | AH499: 1800 | AI499: 2026 | AJ499: 0 | AK499: 300 | AL499: 600 | AM499: 0 | AN499: 600 | AO499: 300 | AP499: 0 | AQ499: 0 | AR499: 0 | AS499: 0 | AT499: 0 | AU499: 0 | AV499: CCP SIN SALDO | AW499: CCP POR DEVENGAR | AX499: -
A500: 46048 | B500: 01. ENE | C500: APROBADO | D500: UFAF | E500: 01. PIA 2026 | F500: 3000001.ACCIONES COMUNES | G500: 5000276.GESTION DEL PROGRAMA | H500: SERVICIOS DE LUZ, AGUA, INTERNET, TELF. FJA | I500: RESTRINGIDA | J500: UNIDADES TERRITORIALES | K500: UT SAN MARTIN | L500: 0000000201 | M500: 0000184 | N500: 27/01/2026 | O500: 20467534026 | P500: 0000000216 | 0000184 | AMERICA MOVIL PERU S.A.C. | Q500: 00 | R500: 0000000216 | S500: CCMN-002164: SERVICIO DE INTERNET DE LA UNIDAD TERRITORIAL SAN MARTIN DEL PROGRAMA LLAMKASUN PERU | T500: 0000000216. CCMN-002164: SERVICIO DE INTERNET DE LA UNIDAD TERRITORIAL SAN MARTIN DEL PROGRAMA LLAMKASUN PERU | U500: 0027 | V500: UT SAN MARTIN | W500: 0027. UT SAN MARTIN | X500: 5-23. BIENES Y SERVICIOS | Y500: 23 2 2 2 3 | Z500: SERVICIO DE INTERNET | AA500: 23 2 2 2 3. SERVICIO DE INTERNET | AB500: 292.95 | AC500: 292.95 | AD500: 0 | AE500: 292.95 | AF500: 292.95 | AG500: 0 | AH500: 292.95 | AI500: 2026 | AJ500: 0 | AK500: 199.98 | AL500: 92.97 | AM500: 0 | AN500: 0 | AO500: 0 | AP500: 0 | AQ500: 0 | AR500: 0 | AS500: 0 | AT500: 0 | AU500: 0 | AV500: CCP SIN SALDO | AW500: CCP DEVENGADO | AX500: -
A501: 46045 | B501: 01. ENE | C501: APROBADO | D501: UFAF | E501: 01. PIA 2026 | F501: 3000001.ACCIONES COMUNES | G501: 5000276.GESTION DEL PROGRAMA | H501: SERVICIO DE LIMPIEZA | I501: NO RESTRINGIDA | J501: OFICINA NACIONAL | K501: UFAF | L501: 0000000192 | M501: 0000179 | N501: 27/01/2026 | O501: 20614212510 | P501: 0000000217 | 0000179 | K & CH SERVICIOS S.R.L. | Q501: 00 | R501: 0000000217 | S501: Contrato-026-2025-LLP: SERVICIO DE LIMPIEZA INTEGRAL PARA LAS INSTALACIONES DE LA OFICINA NACIONAL Y ARCHIVO CENTRAL | T501: 0000000217. Contrato-026-2025-LLP: SERVICIO DE LIMPIEZA INTEGRAL PARA LAS INSTALACIONES DE LA OFICINA NACIONAL Y ARCHIVO CENTRAL | U501: 0014 | V501: UFAF | W501: 0014. UFAF | X501: 5-23. BIENES Y SERVICIOS | Y501: 23 2 3 1 1 | Z501: SERVICIOS DE LIMPIEZA E HIGIENE | AA501: 23 2 3 1 1. SERVICIOS DE LIMPIEZA E HIGIENE | AB501: 290833.34 | AC501: 290833.34 | AD501: 0 | AE501: 290833.34 | AF501: 174499.98 | AG501: 116333.36 | AH501: 174499.98 | AI501: 2026 | AJ501: 0 | AK501: 58166.66 | AL501: 29083.33 | AM501: 29083.33 | AN501: 29083.33 | AO501: 29083.33 | AP501: 0 | AQ501: 0 | AR501: 0 | AS501: 0 | AT501: 0 | AU501: 0 | AV501: CCP SIN SALDO | AW501: CCP POR DEVENGAR | AX501: -
A502: 46045 | B502: 01. ENE | C502: APROBADO | D502: UFAF | E502: 01. PIA 2026 | F502: 3000001.ACCIONES COMUNES | G502: 5000276.GESTION DEL PROGRAMA | H502: ALQUILER DE LOCAL | I502: NO RESTRINGIDA | J502: UNIDADES TERRITORIALES | K502: UT LA LIBERTAD - ANCASH NOROESTE | L502: 0000000191 | M502: 0000178 | N502: 27/01/2026 | O502: 10703016460 | P502: 0000000218 | 0000178 | CALMET WIESE KARLA CECILIA | Q502: 00 | R502: 0000000218 | S502: Contrato-022-2025-LLP: CONTRATACION DEL SERVICIO DE ALQUILER DE LA UNIDAD TERRITORIAL LA LIBERTAD - ANCASH NOROESTE | T502: 0000000218. Contrato-022-2025-LLP: CONTRATACION DEL SERVICIO DE ALQUILER DE LA UNIDAD TERRITORIAL LA LIBERTAD - ANCASH NOROESTE | U502: 0012 | V502: UT LA LIBERTAD - ANCASH NOROESTE | W502: 0012. UT LA LIBERTAD - ANCASH NOROESTE | X502: 5-23. BIENES Y SERVICIOS | Y502: 23 2 5 1 1 | Z502: DE EDIFICIOS Y ESTRUCTURAS | AA502: 23 2 5 1 1. DE EDIFICIOS Y ESTRUCTURAS | AB502: 48000 | AC502: 48000 | AD502: 0 | AE502: 48000 | AF502: 42000 | AG502: 6000 | AH502: 42000 | AI502: 2026 | AJ502: 6000 | AK502: 6000 | AL502: 6000 | AM502: 6000 | AN502: 6000 | AO502: 6000 | AP502: 6000 | AQ502: 0 | AR502: 0 | AS502: 0 | AT502: 0 | AU502: 0 | AV502: CCP SIN SALDO | AW502: CCP POR DEVENGAR | AX502: -
A503: 46045 | B503: 01. ENE | C503: APROBADO | D503: UFAF | E503: 01. PIA 2026 | F503: 3000001.ACCIONES COMUNES | G503: 5000276.GESTION DEL PROGRAMA | H503: ALQUILER DE LOCAL | I503: NO RESTRINGIDA | J503: UNIDADES TERRITORIALES | K503: UT ICA - AYACUCHO SUR | L503: 0000000305 | M503: 0000194 | N503: 29/01/2026 | O503: 10215595591 | P503: 0000000219 | 0000194 | MATOS HILARIO GIOVANNA AMELIA | Q503: 00 | R503: 0000000219 | S503: Contrato-021-2025: CONTRATACION DEL SERVICIO DE ALQUILER DE INMUEBLE PARA LA UNIDAD TERRITORIAL ICA-AYACUCHO SUR | T503: 0000000219. Contrato-021-2025: CONTRATACION DEL SERVICIO DE ALQUILER DE INMUEBLE PARA LA UNIDAD TERRITORIAL ICA-AYACUCHO SUR | U503: 0010 | V503: UT ICA - AYACUCHO SUR | W503: 0010. UT ICA - AYACUCHO SUR | X503: 5-23. BIENES Y SERVICIOS | Y503: 23 2 5 1 1 | Z503: DE EDIFICIOS Y ESTRUCTURAS | AA503: 23 2 5 1 1. DE EDIFICIOS Y ESTRUCTURAS | AB503: 40000 | AC503: 40000 | AD503: 0 | AE503: 40000 | AF503: 35000 | AG503: 5000 | AH503: 30000 | AI503: 2026 | AJ503: 0 | AK503: 10000 | AL503: 5000 | AM503: 5000 | AN503: 5000 | AO503: 5000 | AP503: 5000 | AQ503: 0 | AR503: 0 | AS503: 0 | AT503: 0 | AU503: 0 | AV503: CCP SIN SALDO | AW503: CCP POR DEVENGAR | AX503: -
A504: 46048 | B504: 01. ENE | C504: APROBADO | D504: UFSMI / UFGP | E504: 01. PIA 2026 | F504: 3000194.EMPLEO TEMPORAL GENERADO | G504: 5006296.SEGUIMIENTO DE LOS PROYECTOS Y ACTIVIDADES EN EJECUCION | H504: LOCADORES | I504: NO RESTRINGIDA | J504: UNIDADES TERRITORIALES | K504: UT LORETO | L504: 0000000193 | M504: 0000180 | N504: 27/01/2026 | O504: 10474738979 | P504: 0000000220 | 0000180 | VARGAS AREQUI PAUL MARCUS | Q504: 00 | R504: 0000000220 | S504: CCMN-002166: SERVICIO DE ASISTENCIA TECNICA A ORGANISMOS EJECUTORES Y SEGUIMIENTO VINCULADO A GESTION UT LORETO | T504: 0000000220. CCMN-002166: SERVICIO DE ASISTENCIA TECNICA A ORGANISMOS EJECUTORES Y SEGUIMIENTO VINCULADO A GESTION UT LORETO | U504: 0061 | V504: UT LORETO | W504: 0061. UT LORETO | X504: 5-23. BIENES Y SERVICIOS | Y504: 23 2 9 1 1 | Z504: LOCACIÓN DE SERVICIOS REALIZADOS POR PERSONA NATURAL | AA504: 23 2 9 1 1. LOCACIÓN DE SERVICIOS REALIZADOS POR PERSONA NATURAL | AB504: 7000 | AC504: 7000 | AD504: 0 | AE504: 7000 | AF504: 7000 | AG504: 0 | AH504: 7000 | AI504: 2026 | AJ504: 0 | AK504: 0 | AL504: 3500 | AM504: 3500 | AN504: 0 | AO504: 0 | AP504: 0 | AQ504: 0 | AR504: 0 | AS504: 0 | AT504: 0 | AU504: 0 | AV504: CCP SIN SALDO | AW504: CCP DEVENGADO | AX504: SEGUIMIENTO PARTICIPANTES
A505: 46048 | B505: 01. ENE | C505: APROBADO | D505: UFAF | E505: 01. PIA 2026 | F505: 3000001.ACCIONES COMUNES | G505: 5000276.GESTION DEL PROGRAMA | H505: COMBUSTIBLE | I505: NO RESTRINGIDA | J505: UNIDADES TERRITORIALES | K505: UT CAJAMARCA | L505: 0000001917 | M505: 0000119 | N505: 22/06/2026 | O505: 20601042135 | P505: 0000000221 | 0000119 | GRIFO OTUZCO S.R.L. | Q505: 00 | R505: 0000000221 | S505: Contrato-020-2025-LLP: ADQUISICION DE COMBUSTIBLE DIESEL B5 S50 PARA EL SUMINISTRO A LA CAMIONETA DE LA UT CAJAMARCA | T505: 0000000221. Contrato-020-2025-LLP: ADQUISICION DE COMBUSTIBLE DIESEL B5 S50 PARA EL SUMINISTRO A LA CAMIONETA DE LA UT CAJAMARCA | U505: 0006 | V505: UT CAJAMARCA | W505: 0006. UT CAJAMARCA | X505: 5-23. BIENES Y SERVICIOS | Y505: 23 1 3 1 1 | Z505: COMBUSTIBLES Y CARBURANTES | AA505: 23 1 3 1 1. COMBUSTIBLES Y CARBURANTES | AB505: 1039.69 | AC505: 1039.69 | AD505: 0 | AE505: 654.14 | AF505: 654.14 | AG505: 385.55 | AH505: 654.14 | AI505: 2026 | AJ505: 0 | AK505: 0 | AL505: 0 | AM505: 0 | AN505: 0 | AO505: 654.14 | AP505: 0 | AQ505: 0 | AR505: 0 | AS505: 0 | AT505: 0 | AU505: 0 | AV505: CCP SIN SALDO | AW505: CCP POR DEVENGAR | AX505: -
A506: 46048 | B506: 01. ENE | C506: APROBADO | D506: UFAF | E506: 01. PIA 2026 | F506: 3000001.ACCIONES COMUNES | G506: 5000276.GESTION DEL PROGRAMA | H506: SERVICIOS DIVERSOS | I506: RESTRINGIDA | J506: UNIDADES TERRITORIALES | K506: UT UCAYALI | L506: 0000000196 | M506: 0000181 | N506: 27/01/2026 | O506: 10404682216 | P506: 0000000222 | 0000181 | RUIZ PEÑA RONALD | Q506: 00 | R506: 0000000222 | S506: CCMN-002167: SERVICIO DE CONDUCCION DE VEHICULO PARA EL TRASLADO DEL PERSONAL QUE LABORA EN LA UNIDAD TERRITORIAL | T506: 0000000222. CCMN-002167: SERVICIO DE CONDUCCION DE VEHICULO PARA EL TRASLADO DEL PERSONAL QUE LABORA EN LA UNIDAD TERRITORIAL | U506: 0029 | V506: UT UCAYALI | W506: 0029. UT UCAYALI | X506: 5-23. BIENES Y SERVICIOS | Y506: 23 2 71199 | Z506: SERVICIOS DIVERSOS | AA506: 23 2 71199. SERVICIOS DIVERSOS | AB506: 6600 | AC506: 6600 | AD506: 0 | AE506: 6600 | AF506: 6600 | AG506: 0 | AH506: 6600 | AI506: 2026 | AJ506: 0 | AK506: 2200 | AL506: 2200 | AM506: 2200 | AN506: 0 | AO506: 0 | AP506: 0 | AQ506: 0 | AR506: 0 | AS506: 0 | AT506: 0 | AU506: 0 | AV506: CCP SIN SALDO | AW506: CCP DEVENGADO | AX506: CHOFER / CONDUCTOR
A507: 46041.208 | B507: 01. ENE | C507: APROBADO | D507: UFSMI | E507: 01. PIA 2026 | F507: 3000194.EMPLEO TEMPORAL GENERADO | G507: 5006296.SEGUIMIENTO DE LOS PROYECTOS Y ACTIVIDADES EN EJECUCION | H507: PASAJES Y VIATICOS | I507: NO RESTRINGIDA | J507: OFICINA NACIONAL | K507: UFSMI | L507: 0000000486 | M507: PLLA VIATICO 4-2026 | N507: 17/02/2026 | O507: 0 | P507: 0000000223 | PLLA VIATICO 4-2026 | SIN NOMBRE | Q507: 00 | R507: 0000000223 | S507: PROGRAMACION DE VIATICOS POR COMISION DE SERVICIO DE LA UNIDAD FUNCIONAL DE SEGUIMIENTO Y MONITOREO DE INTERVENCIONES | T507: 0000000223. PROGRAMACION DE VIATICOS POR COMISION DE SERVICIO DE LA UNIDAD FUNCIONAL DE SEGUIMIENTO Y MONITOREO DE INTERVENCIONES | U507: 0056 | V507: UFSMI | W507: 0056. UFSMI | X507: 5-23. BIENES Y SERVICIOS | Y507: 23 2 1 2 1 | Z507: PASAJES Y GASTOS DE TRANSPORTE | AA507: 23 2 1 2 1. PASAJES Y GASTOS DE TRANSPORTE | AB507: 33600 | AC507: 200 | AD507: 33400 | AE507: 625 | AF507: 625 | AG507: 32975 | AH507: 625 | AI507: 2026 | AJ507: 0 | AK507: 0 | AL507: 200 | AM507: -90 | AN507: 0 | AO507: 800 | AP507: -285 | AQ507: 0 | AR507: 0 | AS507: 0 | AT507: 0 | AU507: 0 | AV507: CCP CON SALDO POR COMP | AW507: CCP POR DEVENGAR | AX507: -
A508: 46041.208 | B508: 01. ENE | C508: APROBADO | D508: UFSMI | E508: 01. PIA 2026 | F508: 3000194.EMPLEO TEMPORAL GENERADO | G508: 5006296.SEGUIMIENTO DE LOS PROYECTOS Y ACTIVIDADES EN EJECUCION | H508: PASAJES Y VIATICOS | I508: NO RESTRINGIDA | J508: OFICINA NACIONAL | K508: UFSMI | L508: 0000000486 | M508: PLLA VIATICO 4-2026 | N508: 17/02/2026 | O508: 0 | P508: 0000000223 | PLLA VIATICO 4-2026 | SIN NOMBRE | Q508: 00 | R508: 0000000223 | S508: PROGRAMACION DE VIATICOS POR COMISION DE SERVICIO DE LA UNIDAD FUNCIONAL DE SEGUIMIENTO Y MONITOREO DE INTERVENCIONES | T508: 0000000223. PROGRAMACION DE VIATICOS POR COMISION DE SERVICIO DE LA UNIDAD FUNCIONAL DE SEGUIMIENTO Y MONITOREO DE INTERVENCIONES | U508: 0056 | V508: UFSMI | W508: 0056. UFSMI | X508: 5-23. BIENES Y SERVICIOS | Y508: 23 2 1 2 2 | Z508: VIATICOS Y ASIGNACIONES POR COMISION DE SERVICIO | AA508: 23 2 1 2 2. VIATICOS Y ASIGNACIONES POR COMISION DE SERVICIO | AB508: 21000 | AC508: 4640 | AD508: 16360 | AE508: 4673.9 | AF508: 4673.9 | AG508: 16326.1 | AH508: 4673.9 | AI508: 2026 | AJ508: 0 | AK508: 640 | AL508: 2240 | AM508: -485.5 | AN508: 0 | AO508: 1920 | AP508: 359.4 | AQ508: 0 | AR508: 0 | AS508: 0 | AT508: 0 | AU508: 0 | AV508: CCP CON SALDO POR COMP | AW508: CCP POR DEVENGAR | AX508: -
... A661: 46049.208 | B661: 01. ENE | C661: APROBADO | D661: UFAF | E661: 01. PIA 2026 | F661: 3000001.ACCIONES COMUNES | G661: 5000276.GESTION DEL PROGRAMA | H661: PASAJES Y VIATICOS | I661: NO RESTRINGIDA | J661: OFICINA NACIONAL | K661: UFAF | L661: 0000001197 | M661: PLLA VIATICO 21-26 | N661: 30/03/2026 | O661: 0 | P661: 0000000234 | PLLA VIATICO 21-26 | SIN NOMBRE | Q661: 00 | R661: 0000000234 | S661: PROGRAMACION DE VIATICO POR COMISION DE SERVICIO DE LA COORDINACION FUNCIONAL DE ABASTECIMIENTO Y SERVICIOS GENERALES | T661: 0000000234. PROGRAMACION DE VIATICO POR COMISION DE SERVICIO DE LA COORDINACION FUNCIONAL DE ABASTECIMIENTO Y SERVICIOS GENERALES | U661: 0014 | V661: UFAF | W661: 0014. UFAF | X661: 5-23. BIENES Y SERVICIOS | Y661: 23 2 1 2 2 | Z661: VIATICOS Y ASIGNACIONES POR COMISION DE SERVICIO | AA661: 23 2 1 2 2. VIATICOS Y ASIGNACIONES POR COMISION DE SERVICIO | AB661: 4480 | AC661: 123.5 | AD661: 4356.5 | AE661: 443.5 | AF661: 443.5 | AG661: 4036.5 | AH661: 443.5 | AI661: 2026 | AJ661: 0 | AK661: 0 | AL661: 320 | AM661: -126.5 | AN661: 0 | AO661: 250 | AP661: 0 | AQ661: 0 | AR661: 0 | AS661: 0 | AT661: 0 | AU661: 0 | AV661: CCP CON SALDO POR COMP | AW661: CCP POR DEVENGAR | AX661: -
A662: 46049.208 | B662: 01. ENE | C662: APROBADO | D662: UFAF | E662: 01. PIA 2026 | F662: 3000001.ACCIONES COMUNES | G662: 5000276.GESTION DEL PROGRAMA | H662: PASAJES Y VIATICOS | I662: NO RESTRINGIDA | J662: OFICINA NACIONAL | K662: UFAF | L662: - | M662: - | N662: - | O662: - | P662: 0000000235 | - | - | Q662: 00 | R662: 0000000235 | S662: PROGRAMACION DE VIATICOS POR COMISION DE SERVICIO DE LA COORDINACION FUNCIONAL DE CONTABILIDAD | T662: 0000000235. PROGRAMACION DE VIATICOS POR COMISION DE SERVICIO DE LA COORDINACION FUNCIONAL DE CONTABILIDAD | U662: 0014 | V662: UFAF | W662: 0014. UFAF | X662: 5-23. BIENES Y SERVICIOS | Y662: 23 2 1 2 1 | Z662: PASAJES Y GASTOS DE TRANSPORTE | AA662: 23 2 1 2 1. PASAJES Y GASTOS DE TRANSPORTE | AB662: 6400 | AC662: 0 | AD662: 6400 | AE662: 0 | AF662: 0 | AG662: 6400 | AH662: 0 | AI662: 2026 | AJ662: 0 | AK662: 0 | AL662: 0 | AM662: 0 | AN662: 0 | AO662: 0 | AP662: 0 | AQ662: 0 | AR662: 0 | AS662: 0 | AT662: 0 | AU662: 0 | AV662: CCP SIN COMP | AW662: CCP POR DEVENGAR | AX662: -
A663: 46049.208 | B663: 01. ENE | C663: APROBADO | D663: UFAF | E663: 01. PIA 2026 | F663: 3000001.ACCIONES COMUNES | G663: 5000276.GESTION DEL PROGRAMA | H663: PASAJES Y VIATICOS | I663: NO RESTRINGIDA | J663: OFICINA NACIONAL | K663: UFAF | L663: - | M663: - | N663: - | O663: - | P663: 0000000235 | - | - | Q663: 00 | R663: 0000000235 | S663: PROGRAMACION DE VIATICOS POR COMISION DE SERVICIO DE LA COORDINACION FUNCIONAL DE CONTABILIDAD | T663: 0000000235. PROGRAMACION DE VIATICOS POR COMISION DE SERVICIO DE LA COORDINACION FUNCIONAL DE CONTABILIDAD | U663: 0014 | V663: UFAF | W663: 0014. UFAF | X663: 5-23. BIENES Y SERVICIOS | Y663: 23 2 1 2 2 | Z663: VIATICOS Y ASIGNACIONES POR COMISION DE SERVICIO | AA663: 23 2 1 2 2. VIATICOS Y ASIGNACIONES POR COMISION DE SERVICIO | AB663: 600 | AC663: 0 | AD663: 600 | AE663: 0 | AF663: 0 | AG663: 600 | AH663: 0 | AI663: 2026 | AJ663: 0 | AK663: 0 | AL663: 0 | AM663: 0 | AN663: 0 | AO663: 0 | AP663: 0 | AQ663: 0 | AR663: 0 | AS663: 0 | AT663: 0 | AU663: 0 | AV663: CCP SIN COMP | AW663: CCP POR DEVENGAR | AX663: -
A664: 46049.208 | B664: 01. ENE | C664: APROBADO | D664: UFAF | E664: 01. PIA 2026 | F664: 3000001.ACCIONES COMUNES | G664: 5000276.GESTION DEL PROGRAMA | H664: PASAJES Y VIATICOS | I664: NO RESTRINGIDA | J664: OFICINA NACIONAL | K664: UFAF | L664: 0000002261 | M664: PLLA VIATICO 86-26 | N664: 16/07/2026 | O664: 0 | P664: 0000000236 | PLLA VIATICO 86-26 | SIN NOMBRE | Q664: 00 | R664: 0000000236 | S664: PROGRAMACION DE VIATICOS POR COMISION DE SERVICIO DE LA COORDINACION FUNCIONAL DE TESORERIA | T664: 0000000236. PROGRAMACION DE VIATICOS POR COMISION DE SERVICIO DE LA COORDINACION FUNCIONAL DE TESORERIA | U664: 0014 | V664: UFAF | W664: 0014. UFAF | X664: 5-23. BIENES Y SERVICIOS | Y664: 23 2 1 2 1 | Z664: PASAJES Y GASTOS DE TRANSPORTE | AA664: 23 2 1 2 1. PASAJES Y GASTOS DE TRANSPORTE | AB664: 400 | AC664: 0 | AD664: 400 | AE664: 0 | AF664: 0 | AG664: 400 | AH664: 0 | AI664: 2026 | AJ664: 0 | AK664: 0 | AL664: 0 | AM664: 0 | AN664: 0 | AO664: 0 | AP664: 0 | AQ664: 0 | AR664: 0 | AS664: 0 | AT664: 0 | AU664: 0 | AV664: CCP SIN COMP | AW664: CCP POR DEVENGAR | AX664: -
A665: 46049.208 | B665: 01. ENE | C665: APROBADO | D665: UFAF | E665: 01. PIA 2026 | F665: 3000001.ACCIONES COMUNES | G665: 5000276.GESTION DEL PROGRAMA | H665: PASAJES Y VIATICOS | I665: NO RESTRINGIDA | J665: OFICINA NACIONAL | K665: UFAF | L665: 0000002261 | M665: PLLA VIATICO 86-26 | N665: 16/07/2026 | O665: 0 | P665: 0000000236 | PLLA VIATICO 86-26 | SIN NOMBRE | Q665: 00 | R665: 0000000236 | S665: PROGRAMACION DE VIATICOS POR COMISION DE SERVICIO DE LA COORDINACION FUNCIONAL DE TESORERIA | T665: 0000000236. PROGRAMACION DE VIATICOS POR COMISION DE SERVICIO DE LA COORDINACION FUNCIONAL DE TESORERIA | U665: 0014 | V665: UFAF | W665: 0014. UFAF | X665: 5-23. BIENES Y SERVICIOS | Y665: 23 2 1 2 2 | Z665: VIATICOS Y ASIGNACIONES POR COMISION DE SERVICIO | AA665: 23 2 1 2 2. VIATICOS Y ASIGNACIONES POR COMISION DE SERVICIO | AB665: 7040 | AC665: 0 | AD665: 7040 | AE665: 640 | AF665: 640 | AG665: 6400 | AH665: 640 | AI665: 2026 | AJ665: 0 | AK665: 0 | AL665: 0 | AM665: 0 | AN665: 0 | AO665: 0 | AP665: 640 | AQ665: 0 | AR665: 0 | AS665: 0 | AT665: 0 | AU665: 0 | AV665: CCP SIN COMP | AW665: CCP POR DEVENGAR | AX665: -
A666: 46049 | B666: 01. ENE | C666: APROBADO | D666: UFAF | E666: 01. PIA 2026 | F666: 3000001.ACCIONES COMUNES | G666: 5000276.GESTION DEL PROGRAMA | H666: ALQUILER DE LOCAL | I666: NO RESTRINGIDA | J666: UNIDADES TERRITORIALES | K666: UT MOQUEGUA | L666: 0000000203 | M666: 0000189 | N666: 28/01/2026 | O666: 10044043357 | P666: 0000000237 | 0000189 | RUEDA QUISPE DE MENDOZA MARTHA ROSALVINA | Q666: 00 | R666: 0000000237 | S666: CCMN-002172: SERVICIO DE ALQUILER DE INMUEBLE PARA LA UNIDAD TERRITORIAL MOQUEGUA DEL PROGRAMA DE EMPLEO TEMPORAL | T666: 0000000237. CCMN-002172: SERVICIO DE ALQUILER DE INMUEBLE PARA LA UNIDAD TERRITORIAL MOQUEGUA DEL PROGRAMA DE EMPLEO TEMPORAL | U666: 0024 | V666: UT MOQUEGUA | W666: 0024. UT MOQUEGUA | X666: 5-23. BIENES Y SERVICIOS | Y666: 23 2 5 1 1 | Z666: DE EDIFICIOS Y ESTRUCTURAS | AA666: 23 2 5 1 1. DE EDIFICIOS Y ESTRUCTURAS | AB666: 3000 | AC666: 3000 | AD666: 0 | AE666: 3000 | AF666: 3000 | AG666: 0 | AH666: 3000 | AI666: 2026 | AJ666: 0 | AK666: 3000 | AL666: 0 | AM666: 0 | AN666: 0 | AO666: 0 | AP666: 0 | AQ666: 0 | AR666: 0 | AS666: 0 | AT666: 0 | AU666: 0 | AV666: CCP SIN SALDO | AW666: CCP DEVENGADO | AX666: -
A667: 46049 | B667: 01. ENE | C667: APROBADO | D667: UFAF | E667: 01. PIA 2026 | F667: 3000001.ACCIONES COMUNES | G667: 5000276.GESTION DEL PROGRAMA | H667: ALQUILER DE LOCAL | I667: NO RESTRINGIDA | J667: UNIDADES TERRITORIALES | K667: UT HUANCAVELICA | L667: 0000000230 | M667: 0000188 | N667: 28/01/2026 | O667: 10200839311 | P667: 0000000238 | 0000188 | CENCIA CRISPIN ARMANDO | Q667: 00 | R667: 0000000238 | S667: CCMN-002173: SERVICIO DE ALQUILER DE INMUEBLE PARA LA UNIDAD TERRITORIAL HUANCAVELICA DEL PROGRAMA LLAMKASUN PERU | T667: 0000000238. CCMN-002173: SERVICIO DE ALQUILER DE INMUEBLE PARA LA UNIDAD TERRITORIAL HUANCAVELICA DEL PROGRAMA LLAMKASUN PERU | U667: 0008 | V667: UT HUANCAVELICA | W667: 0008. UT HUANCAVELICA | X667: 5-23. BIENES Y SERVICIOS | Y667: 23 2 5 1 1 | Z667: DE EDIFICIOS Y ESTRUCTURAS | AA667: 23 2 5 1 1. DE EDIFICIOS Y ESTRUCTURAS | AB667: 17000 | AC667: 17000 | AD667: 0 | AE667: 17000 | AF667: 17000 | AG667: 0 | AH667: 17000 | AI667: 2026 | AJ667: 0 | AK667: 6800 | AL667: 3400 | AM667: 3400 | AN667: 0 | AO667: 3400 | AP667: 0 | AQ667: 0 | AR667: 0 | AS667: 0 | AT667: 0 | AU667: 0 | AV667: CCP SIN SALDO | AW667: CCP DEVENGADO | AX667: -
A668: 46050 | B668: 01. ENE | C668: APROBADO | D668: UFAF | E668: 01. PIA 2026 | F668: 3000001.ACCIONES COMUNES | G668: 5000276.GESTION DEL PROGRAMA | H668: SERVICIOS DIVERSOS | I668: RESTRINGIDA | J668: UNIDADES TERRITORIALES | K668: UT LAMBAYEQUE | L668: 0000000235 | M668: 0000218 | N668: 30/01/2026 | O668: 10475925471 | P668: 0000000239 | 0000218 | LUCERO YAIPEN RAUL EVARISTO | Q668: 00 | R668: 0000000239 | S668: CCMN-002176: CONTRATACION DEL SERVICIO DE CONDUCCION DE VEHICULO PARA EL TRASLADO DEL PERSONAL QUE LABORA EN LA U | T668: 0000000239. CCMN-002176: CONTRATACION DEL SERVICIO DE CONDUCCION DE VEHICULO PARA EL TRASLADO DEL PERSONAL QUE LABORA EN LA U | U668: 0013 | V668: UT LAMBAYEQUE | W668: 0013. UT LAMBAYEQUE | X668: 5-23. BIENES Y SERVICIOS | Y668: 23 2 71199 | Z668: SERVICIOS DIVERSOS | AA668: 23 2 71199. SERVICIOS DIVERSOS | AB668: 6600 | AC668: 6600 | AD668: 0 | AE668: 6600 | AF668: 6600 | AG668: 0 | AH668: 6600 | AI668: 2026 | AJ668: 0 | AK668: 0 | AL668: 2200 | AM668: 2200 | AN668: 2200 | AO668: 0 | AP668: 0 | AQ668: 0 | AR668: 0 | AS668: 0 | AT668: 0 | AU668: 0 | AV668: CCP SIN SALDO | AW668: CCP DEVENGADO | AX668: CHOFER / CONDUCTOR
A669: 46050 | B669: 01. ENE | C669: APROBADO | D669: UFAF | E669: 01. PIA 2026 | F669: 3000001.ACCIONES COMUNES | G669: 5000276.GESTION DEL PROGRAMA | H669: SERVICIOS DE LUZ, AGUA, INTERNET, TELF. FJA | I669: RESTRINGIDA | J669: UNIDADES TERRITORIALES | K669: UT LORETO | L669: 0000000459 | M669: 0000323 | N669: 13/02/2026 | O669: 20518777646 | P669: 0000000240 | 0000323 | GLOBAL FIBER PERU S.A.C. | Q669: 00 | R669: 0000000240 | S669: CCMN-002177: CONTRATACION DEL SERVICIO DE INTERNET PARA LA OFICINA DE UNIDAD TERRITORIAL LORETO DEL PROGRAMA DE E | T669: 0000000240. CCMN-002177: CONTRATACION DEL SERVICIO DE INTERNET PARA LA OFICINA DE UNIDAD TERRITORIAL LORETO DEL PROGRAMA DE E | U669: 0023 | V669: UT LORETO | W669: 0023. UT LORETO | X669: 5-23. BIENES Y SERVICIOS | Y669: 23 2 2 2 3 | Z669: SERVICIO DE INTERNET | AA669: 23 2 2 2 3. SERVICIO DE INTERNET | AB669: 15000 | AC669: 15000 | AD669: 0 | AE669: 15000 | AF669: 7500 | AG669: 7500 | AH669: 7500 | AI669: 2026 | AJ669: 0 | AK669: 0 | AL669: 1500 | AM669: 1500 | AN669: 1500 | AO669: 1500 | AP669: 1500 | AQ669: 0 | AR669: 0 | AS669: 0 | AT669: 0 | AU669: 0 | AV669: CCP SIN SALDO | AW669: CCP POR DEVENGAR | AX669: -
A670: 46050 | B670: 01. ENE | C670: APROBADO | D670: UFAF | E670: 01. PIA 2026 | F670: 3000001.ACCIONES COMUNES | G670: 5000276.GESTION DEL PROGRAMA | H670: SERVICIOS DE LUZ, AGUA, INTERNET, TELF. FJA | I670: RESTRINGIDA | J670: UNIDADES TERRITORIALES | K670: UT LAMBAYEQUE | L670: 0000000311 | M670: 0000252 | N670: 04/02/2026 | O670: 20103117560 | P670: 0000000242 | 0000252 | EMP REG DE SERV PUB DE ELECT DL NORTE SA | Q670: 00 | R670: 0000000242 | S670: CCMN-002180: SERVICIO DE ENERGIA ELECTRICA PARA LA UT LAMBAYEQUE | T670: 0000000242. CCMN-002180: SERVICIO DE ENERGIA ELECTRICA PARA LA UT LAMBAYEQUE | U670: 0013 | V670: UT LAMBAYEQUE | W670: 0013. UT LAMBAYEQUE | X670: 5-23. BIENES Y SERVICIOS | Y670: 23 2 2 1 1 | Z670: SERVICIO DE SUMINISTRO DE ENERGIA ELECTRICA | AA670: 23 2 2 1 1. SERVICIO DE SUMINISTRO DE ENERGIA ELECTRICA | AB670: 840 | AC670: 840 | AD670: 0 | AE670: 840 | AF670: 358.9 | AG670: 481.1 | AH670: 358.9 | AI670: 2026 | AJ670: 0 | AK670: 100.3 | AL670: 73.8 | AM670: 63.7 | AN670: 60.1 | AO670: 61 | AP670: 0 | AQ670: 0 | AR670: 0 | AS670: 0 | AT670: 0 | AU670: 0 | AV670: CCP SIN SALDO | AW670: CCP POR DEVENGAR | AX670: -
A671: 46050 | B671: 01. ENE | C671: APROBADO | D671: UFSMI / UFGP | E671: 01. PIA 2026 | F671: 3000194.EMPLEO TEMPORAL GENERADO | G671: 5006296.SEGUIMIENTO DE LOS PROYECTOS Y ACTIVIDADES EN EJECUCION | H671: LOCADORES | I671: NO RESTRINGIDA | J671: UNIDADES TERRITORIALES | K671: UT ICA - AYACUCHO SUR | L671: 0000000210 | M671: 0000197 | N671: 29/01/2026 | O671: 10722461113 | P671: 0000000243 | 0000197 | RIVERA ANTEZANA LUIS ANTONIO | Q671: 00 | R671: 0000000243 | S671: CCMN-002183: SERVICIO DE SUPERVISION, SEGUIMIENTO Y MONITOREO A LAS INTERVENCIONES FINANCIADAS POR EL PROGRAMA DE | T671: 0000000243. CCMN-002183: SERVICIO DE SUPERVISION, SEGUIMIENTO Y MONITOREO A LAS INTERVENCIONES FINANCIADAS POR EL PROGRAMA DE | U671: 0053 | V671: UT ICA - AYACUCHO SUR | W671: 0053. UT ICA - AYACUCHO SUR | X671: 5-23. BIENES Y SERVICIOS | Y671: 23 2 9 1 1 | Z671: LOCACIÓN DE SERVICIOS REALIZADOS POR PERSONA NATURAL | AA671: 23 2 9 1 1. LOCACIÓN DE SERVICIOS REALIZADOS POR PERSONA NATURAL | AB671: 10000 | AC671: 10000 | AD671: 0 | AE671: 10000 | AF671: 10000 | AG671: 0 | AH671: 10000 | AI671: 2026 | AJ671: 0 | AK671: 5000 | AL671: 5000 | AM671: 0 | AN671: 0 | AO671: 0 | AP671: 0 | AQ671: 0 | AR671: 0 | AS671: 0 | AT671: 0 | AU671: 0 | AV671: CCP SIN SALDO | AW671: CCP DEVENGADO | AX671: SEGUIMIENTO
A672: 46050 | B672: 01. ENE | C672: APROBADO | D672: UFSMI / UFGP | E672: 01. PIA 2026 | F672: 3000194.EMPLEO TEMPORAL GENERADO | G672: 5006296.SEGUIMIENTO DE LOS PROYECTOS Y ACTIVIDADES EN EJECUCION | H672: LOCADORES | I672: NO RESTRINGIDA | J672: UNIDADES TERRITORIALES | K672: UT AMAZONAS | L672: 0000000208 | M672: 0000195 | N672: 29/01/2026 | O672: 10436483533 | P672: 0000000244 | 0000195 | NANFUÑAY LABRIN PATRICIA ALEXANDRA | Q672: 00 | R672: 0000000244 | S672: CCMN-002182: SERVICIO DE SUPERVISION, SEGUIMIENTO Y MONITOREO A LAS INTERVENCIONES - UT AMAZONAS | T672: 0000000244. CCMN-002182: SERVICIO DE SUPERVISION, SEGUIMIENTO Y MONITOREO A LAS INTERVENCIONES - UT AMAZONAS | U672: 0044 | V672: UT AMAZONAS | W672: 0044. UT AMAZONAS | X672: 5-23. BIENES Y SERVICIOS | Y672: 23 2 9 1 1 | Z672: LOCACIÓN DE SERVICIOS REALIZADOS POR PERSONA NATURAL | AA672: 23 2 9 1 1. LOCACIÓN DE SERVICIOS REALIZADOS POR PERSONA NATURAL | AB672: 10000 | AC672: 10000 | AD672: 0 | AE672: 10000 | AF672: 10000 | AG672: 0 | AH672: 10000 | AI672: 2026 | AJ672: 0 | AK672: 0 | AL672: 10000 | AM672: 0 | AN672: 0 | AO672: 0 | AP672: 0 | AQ672: 0 | AR672: 0 | AS672: 0 | AT672: 0 | AU672: 0 | AV672: CCP SIN SALDO | AW672: CCP DEVENGADO | AX672: SEGUIMIENTO
A673: 46050 | B673: 01. ENE | C673: APROBADO | D673: UFSMI / UFGP | E673: 01. PIA 2026 | F673: 3000194.EMPLEO TEMPORAL GENERADO | G673: 5006296.SEGUIMIENTO DE LOS PROYECTOS Y ACTIVIDADES EN EJECUCION | H673: LOCADORES | I673: NO RESTRINGIDA | J673: UNIDADES TERRITORIALES | K673: UT CAJAMARCA | L673: 0000000209 | M673: 0000196 | N673: 29/01/2026 | O673: 10414644240 | P673: 0000000245 | 0000196 | RONCAL MUJICA MONICA CAROLINA | Q673: 00 | R673: 0000000245 | S673: CCMN-002185: SERVICIO DE SUPERVISION, SEGUIMIENTO Y MONITOREO A LAS INTERVENCIONES - UT CAJAMARCA | T673: 0000000245. CCMN-002185: SERVICIO DE SUPERVISION, SEGUIMIENTO Y MONITOREO A LAS INTERVENCIONES - UT CAJAMARCA | U673: 0049 | V673: UT CAJAMARCA | W673: 0049. UT CAJAMARCA | X673: 5-23. BIENES Y SERVICIOS | Y673: 23 2 9 1 1 | Z673: LOCACIÓN DE SERVICIOS REALIZADOS POR PERSONA NATURAL | AA673: 23 2 9 1 1. LOCACIÓN DE SERVICIOS REALIZADOS POR PERSONA NATURAL | AB673: 10000 | AC673: 10000 | AD673: 0 | AE673: 10000 | AF673: 10000 | AG673: 0 | AH673: 10000 | AI673: 2026 | AJ673: 0 | AK673: 0 | AL673: 5000 | AM673: 5000 | AN673: 0 | AO673: 0 | AP673: 0 | AQ673: 0 | AR673: 0 | AS673: 0 | AT673: 0 | AU673: 0 | AV673: CCP SIN SALDO | AW673: CCP DEVENGADO | AX673: SEGUIMIENTO
A674: 46050 | B674: 01. ENE | C674: APROBADO | D674: UFSMI / UFGP | E674: 01. PIA 2026 | F674: - | G674: - | H674: LOCADORES | I674: NO RESTRINGIDA | J674: UNIDADES TERRITORIALES | K674: UT LIMA CENTRO - CALLAO | L674: 0000000221 | M674: 221.25.65.2510770 | N674: 12/01/2026 | O674: 20602025234 | P674: 0000000246 | 221.25.65.2510770 | SEGURIDAD Y VIGILANCIA TACNA SOCIEDAD COMERCIAL DE RESPONSABILIDAD LIMITADA - SEVITAC S.R.L. | Q674: 00 | R674: 0000000246 | S674: CCMN-002184: SERVICIO DE SUPERVISION, SEGUIMIENTO Y MONITOREO A LAS INTERVENCIONES FINANCIADAS POR EL PROGRAMA DE | T674: 0000000246. CCMN-002184: SERVICIO DE SUPERVISION, SEGUIMIENTO Y MONITOREO A LAS INTERVENCIONES FINANCIADAS POR EL PROGRAMA DE | U674: 0060 | V674: UT LIMA CENTRO - CALLAO | W674: 0060. UT LIMA CENTRO - CALLAO | X674: 5-23. BIENES Y SERVICIOS | Y674: 23 2 9 1 1 | Z674: LOCACIÓN DE SERVICIOS REALIZADOS POR PERSONA NATURAL | AA674: 23 2 9 1 1. LOCACIÓN DE SERVICIOS REALIZADOS POR PERSONA NATURAL | AB674: 10000 | AC674: 10000 | AD674: 0 | AE674: 10000 | AF674: 10000 | AG674: 0 | AH674: 10000 | AI674: 2026 | AJ674: 0 | AK674: 0 | AL674: 10000 | AM674: 0 | AN674: 0 | AO674: 0 | AP674: 0 | AQ674: 0 | AR674: 0 | AS674: 0 | AT674: 0 | AU674: 0 | AV674: CCP SIN SALDO | AW674: CCP DEVENGADO | AX674: SEGUIMIENTO
A675: 46050 | B675: 01. ENE | C675: APROBADO | D675: UFAF | E675: 01. PIA 2026 | F675: 3000001.ACCIONES COMUNES | G675: 5000276.GESTION DEL PROGRAMA | H675: MANTENIMIENOT DE VEHICULOS | I675: RESTRINGIDA | J675: UNIDADES TERRITORIALES | K675: UT SAN MARTIN | L675: 0000000213 | M675: 0000200 | N675: 29/01/2026 | O675: 20450475042 | P675: 0000000248 | 0000200 | AUTOCENTRO TARAPOTO S.R.L. | Q675: 00 | R675: 0000000248 | S675: CCMN-002181: SERVICIO DE MANTENIMIENTO PREVENTIVO PARA EL VEHICULO DE PLACA A1D-872 UT SAN MARTIN | T675: 0000000248. CCMN-002181: SERVICIO DE MANTENIMIENTO PREVENTIVO PARA EL VEHICULO DE PLACA A1D-872 UT SAN MARTIN | U675: 0027 | V675: UT SAN MARTIN | W675: 0027. UT SAN MARTIN | X675: 5-23. BIENES Y SERVICIOS | Y675: 23 2 4 5 1 | Z675: DE VEHICULOS | AA675: 23 2 4 5 1. DE VEHICULOS | AB675: 1485.5 | AC675: 1485.5 | AD675: 0 | AE675: 1485.5 | AF675: 1485.5 | AG675: 0 | AH675: 1485.5 | AI675: 2026 | AJ675: 0 | AK675: 1485.5 | AL675: 0 | AM675: 0 | AN675: 0 | AO675: 0 | AP675: 0 | AQ675: 0 | AR675: 0 | AS675: 0 | AT675: 0 | AU675: 0 | AV675: CCP SIN SALDO | AW675: CCP DEVENGADO | AX675: -
... A693: 46051 | B693: 01. ENE | C693: APROBADO | D693: UFSMI / UFGP | E693: 01. PIA 2026 | F693: 3000194.EMPLEO TEMPORAL GENERADO | G693: 5006296.SEGUIMIENTO DE LOS PROYECTOS Y ACTIVIDADES EN EJECUCION | H693: LOCADORES | I693: NO RESTRINGIDA | J693: UNIDADES TERRITORIALES | K693: UT PUNO | L693: 0000000227 | M693: 0000213 | N693: 30/01/2026 | O693: 10716378433 | P693: 0000000263 | 0000213 | QUISPE HUACASI LEYTER ADILSON | Q693: 00 | R693: 0000000263 | S693: CCMN-002201: SERVICIO DE SUPERVISION, SEGUIMIENTO Y MONITOREO A LAS INTERVENCIONES FINANCIADAS UT PUNO | T693: 0000000263. CCMN-002201: SERVICIO DE SUPERVISION, SEGUIMIENTO Y MONITOREO A LAS INTERVENCIONES FINANCIADAS UT PUNO | U693: 0064 | V693: UT PUNO | W693: 0064. UT PUNO | X693: 5-23. BIENES Y SERVICIOS | Y693: 23 2 9 1 1 | Z693: LOCACIÓN DE SERVICIOS REALIZADOS POR PERSONA NATURAL | AA693: 23 2 9 1 1. LOCACIÓN DE SERVICIOS REALIZADOS POR PERSONA NATURAL | AB693: 10000 | AC693: 10000 | AD693: 0 | AE693: 10000 | AF693: 10000 | AG693: 0 | AH693: 10000 | AI693: 2026 | AJ693: 0 | AK693: 0 | AL693: 5000 | AM693: 5000 | AN693: 0 | AO693: 0 | AP693: 0 | AQ693: 0 | AR693: 0 | AS693: 0 | AT693: 0 | AU693: 0 | AV693: CCP SIN SALDO | AW693: CCP DEVENGADO | AX693: SEGUIMIENTO
A694: 46051 | B694: 01. ENE | C694: APROBADO | D694: UFTI | E694: 01. PIA 2026 | F694: 3000001.ACCIONES COMUNES | G694: 5000276.GESTION DEL PROGRAMA | H694: ALQUILER DE OTROS BIENES | I694: NO RESTRINGIDA | J694: OFICINA NACIONAL | K694: UFTI | L694: - | M694: - | N694: - | O694: - | P694: 0000000264 | - | - | Q694: 00 | R694: 0000000264 | S694: CCMN-000084: ERVICIO DE SUSCRIPCION DE LICENCIAS DE SOFTWARE DE VIRTUALIZACION VMWARE O EQUIVALENTE | T694: 0000000264. CCMN-000084: ERVICIO DE SUSCRIPCION DE LICENCIAS DE SOFTWARE DE VIRTUALIZACION VMWARE O EQUIVALENTE | U694: 0019 | V694: UFTI | W694: 0019. UFTI | X694: 5-23. BIENES Y SERVICIOS | Y694: 23 2 5 199 | Z694: DE OTROS BIENES Y ACTIVOS | AA694: 23 2 5 199. DE OTROS BIENES Y ACTIVOS | AB694: 214020 | AC694: 0 | AD694: 214020 | AE694: 0 | AF694: 0 | AG694: 214020 | AH694: 0 | AI694: 2026 | AJ694: 0 | AK694: 0 | AL694: 0 | AM694: 0 | AN694: 0 | AO694: 0 | AP694: 0 | AQ694: 0 | AR694: 0 | AS694: 0 | AT694: 0 | AU694: 0 | AV694: CCP SIN COMP | AW694: CCP POR DEVENGAR | AX694: -
A695: 46051 | B695: 01. ENE | C695: APROBADO | D695: UFAF | E695: 01. PIA 2026 | F695: 3000001.ACCIONES COMUNES | G695: 5000276.GESTION DEL PROGRAMA | H695: LOCADORES | I695: NO RESTRINGIDA | J695: OFICINA NACIONAL | K695: UFAF | L695: 0000000229 | M695: 0000216 | N695: 30/01/2026 | O695: 10770297376 | P695: 0000000265 | 0000216 | LUJAN NICACIO DIANA STEFANIE | Q695: 00 | R695: 0000000265 | S695: CCMN-002202: SERVICIO DE CLASIFICACION, ORDENAMIENTO E INVENTARIO DOCUMENTARIO PARA ARCHIVO CENTRAL - UFAF | T695: 0000000265. CCMN-002202: SERVICIO DE CLASIFICACION, ORDENAMIENTO E INVENTARIO DOCUMENTARIO PARA ARCHIVO CENTRAL - UFAF | U695: 0014 | V695: UFAF | W695: 0014. UFAF | X695: 5-23. BIENES Y SERVICIOS | Y695: 23 2 9 1 1 | Z695: LOCACIÓN DE SERVICIOS REALIZADOS POR PERSONA NATURAL | AA695: 23 2 9 1 1. LOCACIÓN DE SERVICIOS REALIZADOS POR PERSONA NATURAL | AB695: 2500 | AC695: 2500 | AD695: 0 | AE695: 2500 | AF695: 2500 | AG695: 0 | AH695: 2500 | AI695: 2026 | AJ695: 0 | AK695: 2500 | AL695: 0 | AM695: 0 | AN695: 0 | AO695: 0 | AP695: 0 | AQ695: 0 | AR695: 0 | AS695: 0 | AT695: 0 | AU695: 0 | AV695: CCP SIN SALDO | AW695: CCP DEVENGADO | AX695: LOCADOR
A696: 46051 | B696: 01. ENE | C696: APROBADO | D696: UFSMI / UFGP | E696: 01. PIA 2026 | F696: 3000194.EMPLEO TEMPORAL GENERADO | G696: 5006296.SEGUIMIENTO DE LOS PROYECTOS Y ACTIVIDADES EN EJECUCION | H696: LOCADORES | I696: NO RESTRINGIDA | J696: UNIDADES TERRITORIALES | K696: UT SAN MARTIN | L696: 0000000232 | M696: 0000217 | N696: 30/01/2026 | O696: 10613990246 | P696: 0000000266 | 0000217 | TELLO SINARAHUA KATERYN | Q696: 00 | R696: 0000000266 | S696: CCMN-002203: SERVICIO DE SUPERVISION, SEGUIMIENTO Y MONITOREO A LAS INTERVENCIONES FINANCIADAS POR EL PROGRAMA DE | T696: 0000000266. CCMN-002203: SERVICIO DE SUPERVISION, SEGUIMIENTO Y MONITOREO A LAS INTERVENCIONES FINANCIADAS POR EL PROGRAMA DE | U696: 0065 | V696: UT SAN MARTIN | W696: 0065. UT SAN MARTIN | X696: 5-23. BIENES Y SERVICIOS | Y696: 23 2 9 1 1 | Z696: LOCACIÓN DE SERVICIOS REALIZADOS POR PERSONA NATURAL | AA696: 23 2 9 1 1. LOCACIÓN DE SERVICIOS REALIZADOS POR PERSONA NATURAL | AB696: 10000 | AC696: 10000 | AD696: 0 | AE696: 10000 | AF696: 10000 | AG696: 0 | AH696: 10000 | AI696: 2026 | AJ696: 0 | AK696: 0 | AL696: 10000 | AM696: 0 | AN696: 0 | AO696: 0 | AP696: 0 | AQ696: 0 | AR696: 0 | AS696: 0 | AT696: 0 | AU696: 0 | AV696: CCP SIN SALDO | AW696: CCP DEVENGADO | AX696: SEGUIMIENTO
A697: 46051 | B697: 01. ENE | C697: APROBADO | D697: UFAF | E697: 01. PIA 2026 | F697: 3000001.ACCIONES COMUNES | G697: 5000276.GESTION DEL PROGRAMA | H697: SERVICIO DE SEGURIDAD Y VIGILANCIA | I697: NO RESTRINGIDA | J697: UNIDADES TERRITORIALES | K697: UT AYACUCHO | L697: 0000000321 | M697: 0000263 | N697: 04/02/2026 | O697: 20609884470 | P697: 0000000267 | 0000263 | SUMAQ R & Y SERVICIOS S.R.L. | Q697: 00 | R697: 0000000267 | S697: Contrato-41-2025: SERVICIO DE SEGURIDAD Y VIGILANCIA PARA LA UT AYACUCHO | T697: 0000000267. Contrato-41-2025: SERVICIO DE SEGURIDAD Y VIGILANCIA PARA LA UT AYACUCHO | U697: 0005 | V697: UT AYACUCHO | W697: 0005. UT AYACUCHO | X697: 5-23. BIENES Y SERVICIOS | Y697: 23 2 3 1 2 | Z697: SERVICIOS DE SEGURIDAD Y VIGILANCIA | AA697: 23 2 3 1 2. SERVICIOS DE SEGURIDAD Y VIGILANCIA | AB697: 124230.24 | AC697: 124230.24 | AD697: 0 | AE697: 124230.24 | AF697: 72467.64 | AG697: 51762.6 | AH697: 72467.64 | AI697: 2026 | AJ697: 0 | AK697: 20705.04 | AL697: 10352.52 | AM697: 10352.52 | AN697: 10352.52 | AO697: 10352.52 | AP697: 10352.52 | AQ697: 0 | AR697: 0 | AS697: 0 | AT697: 0 | AU697: 0 | AV697: CCP SIN SALDO | AW697: CCP POR DEVENGAR | AX697: -
A698: 46051 | B698: 01. ENE | C698: APROBADO | D698: UFAF | E698: 01. PIA 2026 | F698: 3000001.ACCIONES COMUNES | G698: 5000276.GESTION DEL PROGRAMA | H698: SERVICIO DE SEGURIDAD Y VIGILANCIA | I698: NO RESTRINGIDA | J698: UNIDADES TERRITORIALES | K698: UT CAJAMARCA | L698: 0000000322 | M698: 0000265 | N698: 04/02/2026 | O698: 20601221331 | P698: 0000000268 | 0000265 | BOXER SECURITY CORPORATIVA S.R.L. | Q698: 00 | R698: 0000000268 | S698: CCMN-000033: SEGURIDAD Y VIGILANCIA UT CAJAMARCA | T698: 0000000268. CCMN-000033: SEGURIDAD Y VIGILANCIA UT CAJAMARCA | U698: 0006 | V698: UT CAJAMARCA | W698: 0006. UT CAJAMARCA | X698: 5-23. BIENES Y SERVICIOS | Y698: 23 2 3 1 2 | Z698: SERVICIOS DE SEGURIDAD Y VIGILANCIA | AA698: 23 2 3 1 2. SERVICIOS DE SEGURIDAD Y VIGILANCIA | AB698: 115337.04 | AC698: 115337.04 | AD698: 0 | AE698: 115337.04 | AF698: 48057.1 | AG698: 67279.94 | AH698: 48057.1 | AI698: 2026 | AJ698: 0 | AK698: 0 | AL698: 19222.84 | AM698: 19222.84 | AN698: 0 | AO698: 0 | AP698: 9611.42 | AQ698: 0 | AR698: 0 | AS698: 0 | AT698: 0 | AU698: 0 | AV698: CCP SIN SALDO | AW698: CCP POR DEVENGAR | AX698: -
A699: 46052 | B699: 01. ENE | C699: APROBADO | D699: UFSMI / UFGP | E699: 01. PIA 2026 | F699: 3000194.EMPLEO TEMPORAL GENERADO | G699: 5006296.SEGUIMIENTO DE LOS PROYECTOS Y ACTIVIDADES EN EJECUCION | H699: LOCADORES | I699: NO RESTRINGIDA | J699: UNIDADES TERRITORIALES | K699: UT HUANCAVELICA | L699: 0000000245 | M699: 0000226 | N699: 02/02/2026 | O699: 10436453049 | P699: 0000000269 | 0000226 | HUIZA BORDA WILLIAM EDILBERTO | Q699: 00 | R699: 0000000269 | S699: CCMN-002204: SERVICIO DE SUPERVISION, SEGUIMIENTO Y MONITOREO A LAS INTERVENCIONES FINANCIADAS POR EL PROGRAMA DE | T699: 0000000269. CCMN-002204: SERVICIO DE SUPERVISION, SEGUIMIENTO Y MONITOREO A LAS INTERVENCIONES FINANCIADAS POR EL PROGRAMA DE | U699: 0051 | V699: UT HUANCAVELICA | W699: 0051. UT HUANCAVELICA | X699: 5-23. BIENES Y SERVICIOS | Y699: 23 2 9 1 1 | Z699: LOCACIÓN DE SERVICIOS REALIZADOS POR PERSONA NATURAL | AA699: 23 2 9 1 1. LOCACIÓN DE SERVICIOS REALIZADOS POR PERSONA NATURAL | AB699: 10000 | AC699: 10000 | AD699: 0 | AE699: 10000 | AF699: 10000 | AG699: 0 | AH699: 10000 | AI699: 2026 | AJ699: 0 | AK699: 0 | AL699: 5000 | AM699: 5000 | AN699: 0 | AO699: 0 | AP699: 0 | AQ699: 0 | AR699: 0 | AS699: 0 | AT699: 0 | AU699: 0 | AV699: CCP SIN SALDO | AW699: CCP DEVENGADO | AX699: SEGUIMIENTO
A700: 46052 | B700: 01. ENE | C700: APROBADO | D700: UFSMI / UFGP | E700: 01. PIA 2026 | F700: 3000194.EMPLEO TEMPORAL GENERADO | G700: 5006296.SEGUIMIENTO DE LOS PROYECTOS Y ACTIVIDADES EN EJECUCION | H700: LOCADORES | I700: NO RESTRINGIDA | J700: UNIDADES TERRITORIALES | K700: UT APURIMAC | L700: 0000000246 | M700: 0000227 | N700: 02/02/2026 | O700: 10464017980 | P700: 0000000270 | 0000227 | CARBAJAL CESPEDES CARMEN | Q700: 00 | R700: 0000000270 | S700: CCMN-002205: SERVICIO DE SUPERVISION, SEGUIMIENTO Y MONITOREO A LAS INTERVENCIONES FINANCIADAS POR EL PROGRAMA DE | T700: 0000000270. CCMN-002205: SERVICIO DE SUPERVISION, SEGUIMIENTO Y MONITOREO A LAS INTERVENCIONES FINANCIADAS POR EL PROGRAMA DE | U700: 0046 | V700: UT APURIMAC | W700: 0046. UT APURIMAC | X700: 5-23. BIENES Y SERVICIOS | Y700: 23 2 9 1 1 | Z700: LOCACIÓN DE SERVICIOS REALIZADOS POR PERSONA NATURAL | AA700: 23 2 9 1 1. LOCACIÓN DE SERVICIOS REALIZADOS POR PERSONA NATURAL | AB700: 10000 | AC700: 10000 | AD700: 0 | AE700: 10000 | AF700: 10000 | AG700: 0 | AH700: 10000 | AI700: 2026 | AJ700: 0 | AK700: 0 | AL700: 5000 | AM700: 5000 | AN700: 0 | AO700: 0 | AP700: 0 | AQ700: 0 | AR700: 0 | AS700: 0 | AT700: 0 | AU700: 0 | AV700: CCP SIN SALDO | AW700: CCP DEVENGADO | AX700: SEGUIMIENTO
A701: 46052 | B701: 01. ENE | C701: APROBADO | D701: UFSMI / UFGP | E701: 01. PIA 2026 | F701: 3000194.EMPLEO TEMPORAL GENERADO | G701: 5006296.SEGUIMIENTO DE LOS PROYECTOS Y ACTIVIDADES EN EJECUCION | H701: LOCADORES | I701: NO RESTRINGIDA | J701: UNIDADES TERRITORIALES | K701: UT JUNIN | L701: 0000000247 | M701: 0000228 | N701: 02/02/2026 | O701: 10444250416 | P701: 0000000271 | 0000228 | HUARCAYA RODRIGUEZ GHIAN FRANCIZ | Q701: 00 | R701: 0000000271 | S701: CCMN-002206: SERVICIO DE SUPERVISION, SEGUIMIENTO Y MONITOREO A LAS INTERVENCIONES FINANCIADAS POR EL PROGRAMA DE | T701: 0000000271. CCMN-002206: SERVICIO DE SUPERVISION, SEGUIMIENTO Y MONITOREO A LAS INTERVENCIONES FINANCIADAS POR EL PROGRAMA DE | U701: 0054 | V701: UT JUNIN | W701: 0054. UT JUNIN | X701: 5-23. BIENES Y SERVICIOS | Y701: 23 2 9 1 1 | Z701: LOCACIÓN DE SERVICIOS REALIZADOS POR PERSONA NATURAL | AA701: 23 2 9 1 1. LOCACIÓN DE SERVICIOS REALIZADOS POR PERSONA NATURAL | AB701: 0 | AC701: 0 | AD701: 0 | AE701: 0 | AF701: 0 | AG701: 0 | AH701: 0 | AI701: 2026 | AJ701: 0 | AK701: 0 | AL701: 0 | AM701: 0 | AN701: 0 | AO701: 0 | AP701: 0 | AQ701: 0 | AR701: 0 | AS701: 0 | AT701: 0 | AU701: 0 | AV701: CCP ANULADO | AW701: CCP ANULADO | AX701: SEGUIMIENTO
A702: 46052 | B702: 01. ENE | C702: APROBADO | D702: UFAF | E702: 01. PIA 2026 | F702: 3000001.ACCIONES COMUNES | G702: 5000276.GESTION DEL PROGRAMA | H702: SERVICIOS DE LUZ, AGUA, INTERNET, TELF. FJA | I702: RESTRINGIDA | J702: UNIDADES TERRITORIALES | K702: UT ANCASH | L702: 0000000242 | M702: 0000224 | N702: 30/01/2026 | O702: 20467534026 | P702: 0000000272 | 0000224 | AMERICA MOVIL PERU S.A.C. | Q702: 00 | R702: 0000000272 | S702: CCMN-002207: SERVICIO DE TELEFONICA FIJA E INTERNET PARA LA UNIDAD TERRITORIAL ANCASH DEL PROGRAMA DE EMPLEO TEMP | T702: 0000000272. CCMN-002207: SERVICIO DE TELEFONICA FIJA E INTERNET PARA LA UNIDAD TERRITORIAL ANCASH DEL PROGRAMA DE EMPLEO TEMP | U702: 0002 | V702: UT ANCASH | W702: 0002. UT ANCASH | X702: 5-23. BIENES Y SERVICIOS | Y702: 23 2 2 2 3 | Z702: SERVICIO DE INTERNET | AA702: 23 2 2 2 3. SERVICIO DE INTERNET | AB702: 72.91 | AC702: 72.91 | AD702: 0 | AE702: 182.26 | AF702: 182.26 | AG702: -109.35 | AH702: 182.26 | AI702: 2026 | AJ702: 0 | AK702: 100 | AL702: 50 | AM702: 32.26 | AN702: 0 | AO702: 0 | AP702: 0 | AQ702: 0 | AR702: 0 | AS702: 0 | AT702: 0 | AU702: 0 | AV702: CCP SIN SALDO | AW702: CCP DEVENGADO | AX702: -
A703: 46052 | B703: 01. ENE | C703: APROBADO | D703: UFAF | E703: 01. PIA 2026 | F703: 3000001.ACCIONES COMUNES | G703: 5000276.GESTION DEL PROGRAMA | H703: SERVICIOS DE LUZ, AGUA, INTERNET, TELF. FJA | I703: RESTRINGIDA | J703: UNIDADES TERRITORIALES | K703: UT ANCASH | L703: 0000000242 | M703: 0000224 | N703: 30/01/2026 | O703: 20467534026 | P703: 0000000272 | 0000224 | AMERICA MOVIL PERU S.A.C. | Q703: 00 | R703: 0000000272 | S703: CCMN-002207: SERVICIO DE TELEFONICA FIJA E INTERNET PARA LA UNIDAD TERRITORIAL ANCASH DEL PROGRAMA DE EMPLEO TEMP | T703: 0000000272. CCMN-002207: SERVICIO DE TELEFONICA FIJA E INTERNET PARA LA UNIDAD TERRITORIAL ANCASH DEL PROGRAMA DE EMPLEO TEMP | U703: 0002 | V703: UT ANCASH | W703: 0002. UT ANCASH | X703: 5-23. BIENES Y SERVICIOS | Y703: 23 2 2 2 2 | Z703: SERVICIO DE TELEFONIA FIJA | AA703: 23 2 2 2 2. SERVICIO DE TELEFONIA FIJA | AB703: 182.26 | AC703: 182.26 | AD703: 0 | AE703: 72.91 | AF703: 72.91 | AG703: 109.35 | AH703: 72.91 | AI703: 2026 | AJ703: 0 | AK703: 40 | AL703: 20 | AM703: 12.91 | AN703: 0 | AO703: 0 | AP703: 0 | AQ703: 0 | AR703: 0 | AS703: 0 | AT703: 0 | AU703: 0 | AV703: CCP SIN SALDO | AW703: CCP POR DEVENGAR | AX703: -
A704: 46052 | B704: 01. ENE | C704: APROBADO | D704: UFSMI / UFGP | E704: 01. PIA 2026 | F704: 3000194.EMPLEO TEMPORAL GENERADO | G704: 5006296.SEGUIMIENTO DE LOS PROYECTOS Y ACTIVIDADES EN EJECUCION | H704: LOCADORES | I704: NO RESTRINGIDA | J704: UNIDADES TERRITORIALES | K704: UT PIURA - TUMBES | L704: 0000000239 | M704: 0000222 | N704: 30/01/2026 | O704: 10730047083 | P704: 0000000273 | 0000222 | CORDOVA PURIZACA EDY JAIR ALDAIR | Q704: 00 | R704: 0000000273 | S704: CCMN-002208: SERVICIO DE SUPERVISION, SEGUIMIENTO Y MONITOREO A LAS INTERVENCIONES UT PIURA - TUMBES | T704: 0000000273. CCMN-002208: SERVICIO DE SUPERVISION, SEGUIMIENTO Y MONITOREO A LAS INTERVENCIONES UT PIURA - TUMBES | U704: 0063 | V704: UT PIURA - TUMBES | W704: 0063. UT PIURA - TUMBES | X704: 5-23. BIENES Y SERVICIOS | Y704: 23 2 9 1 1 | Z704: LOCACIÓN DE SERVICIOS REALIZADOS POR PERSONA NATURAL | AA704: 23 2 9 1 1. LOCACIÓN DE SERVICIOS REALIZADOS POR PERSONA NATURAL | AB704: 7000 | AC704: 7000 | AD704: 0 | AE704: 7000 | AF704: 7000 | AG704: 0 | AH704: 7000 | AI704: 2026 | AJ704: 0 | AK704: 0 | AL704: 7000 | AM704: 0 | AN704: 0 | AO704: 0 | AP704: 0 | AQ704: 0 | AR704: 0 | AS704: 0 | AT704: 0 | AU704: 0 | AV704: CCP SIN SALDO | AW704: CCP DEVENGADO | AX704: SEGUIMIENTO
A705: 46052 | B705: 01. ENE | C705: APROBADO | D705: UFAF | E705: 01. PIA 2026 | F705: 3000001.ACCIONES COMUNES | G705: 5000276.GESTION DEL PROGRAMA | H705: LOCADORES | I705: NO RESTRINGIDA | J705: OFICINA NACIONAL | K705: UFAF | L705: 0000000241 | M705: 0000223 | N705: 30/01/2026 | O705: 10743665070 | P705: 0000000274 | 0000223 | UCHUYA CAÑAHUA LETICIA VANEZA | Q705: 00 | R705: 0000000274 | S705: CCMN-002193: SERVICIO ESPECIALIZADO EN ANALISIS Y GESTION DE DOCUMENTACION PARA LA COORDINACION FUNCIONAL DE ABAS | T705: 0000000274. CCMN-002193: SERVICIO ESPECIALIZADO EN ANALISIS Y GESTION DE DOCUMENTACION PARA LA COORDINACION FUNCIONAL DE ABAS | U705: 0014 | V705: UFAF | W705: 0014. UFAF | X705: 5-23. BIENES Y SERVICIOS | Y705: 23 2 9 1 1 | Z705: LOCACIÓN DE SERVICIOS REALIZADOS POR PERSONA NATURAL | AA705: 23 2 9 1 1. LOCACIÓN DE SERVICIOS REALIZADOS POR PERSONA NATURAL | AB705: 12000 | AC705: 12000 | AD705: 0 | AE705: 12000 | AF705: 12000 | AG705: 0 | AH705: 12000 | AI705: 2026 | AJ705: 0 | AK705: 4000 | AL705: 4000 | AM705: 4000 | AN705: 0 | AO705: 0 | AP705: 0 | AQ705: 0 | AR705: 0 | AS705: 0 | AT705: 0 | AU705: 0 | AV705: CCP SIN SALDO | AW705: CCP DEVENGADO | AX705: LOCADOR
A706: 46052 | B706: 01. ENE | C706: APROBADO | D706: UFGP | E706: 01. PIA 2026 | F706: 3000194.EMPLEO TEMPORAL GENERADO | G706: 5006296.SEGUIMIENTO DE LOS PROYECTOS Y ACTIVIDADES EN EJECUCION | H706: LOCADORES | I706: NO RESTRINGIDA | J706: OFICINA NACIONAL | K706: UFGP | L706: 0000000258 | M706: 0000232 | N706: 02/02/2026 | O706: 10761425345 | P706: 0000000275 | 0000232 | JUAREZ VILCHEZ JHONNY ANTONY | Q706: 00 | R706: 0000000275 | S706: CCMN-002209: SERVICIO DE SUPERVISION Y ASISTENCIA TECNICA PARA LAS UNIDADES TERRITORIALES AREQUIPA, HUANUCO-PASCO | T706: 0000000275. CCMN-002209: SERVICIO DE SUPERVISION Y ASISTENCIA TECNICA PARA LAS UNIDADES TERRITORIALES AREQUIPA, HUANUCO-PASCO | U706: 0058 | V706: UFGP | W706: 0058. UFGP | X706: 5-23. BIENES Y SERVICIOS | Y706: 23 2 9 1 1 | Z706: LOCACIÓN DE SERVICIOS REALIZADOS POR PERSONA NATURAL | AA706: 23 2 9 1 1. LOCACIÓN DE SERVICIOS REALIZADOS POR PERSONA NATURAL | AB706: 21000 | AC706: 21000 | AD706: 0 | AE706: 21000 | AF706: 21000 | AG706: 0 | AH706: 21000 | AI706: 2026 | AJ706: 0 | AK706: 7000 | AL706: 7000 | AM706: 7000 | AN706: 0 | AO706: 0 | AP706: 0 | AQ706: 0 | AR706: 0 | AS706: 0 | AT706: 0 | AU706: 0 | AV706: CCP SIN SALDO | AW706: CCP DEVENGADO | AX706: LOCADOR
... A711: 46055 | B711: 02. FEB | C711: APROBADO | D711: UFAF | E711: 01. PIA 2026 | F711: 3000001.ACCIONES COMUNES | G711: 5000276.GESTION DEL PROGRAMA | H711: SERVICIOS DIVERSOS | I711: RESTRINGIDA | J711: UNIDADES TERRITORIALES | K711: UT ANCASH | L711: 0000000253 | M711: 0000235 | N711: 02/02/2026 | O711: 10713974655 | P711: 0000000280 | 0000235 | MACEDO MENDEZ RUDY ERICK | Q711: 00 | R711: 0000000280 | S711: CCMN-002217: SERVICIO DE GUARDIANIA TURNO NOCTURNO PARA LAS INSTALACIONES DE LA UT ANCASH | T711: 0000000280. CCMN-002217: SERVICIO DE GUARDIANIA TURNO NOCTURNO PARA LAS INSTALACIONES DE LA UT ANCASH | U711: 0002 | V711: UT ANCASH | W711: 0002. UT ANCASH | X711: 5-23. BIENES Y SERVICIOS | Y711: 23 2 71199 | Z711: SERVICIOS DIVERSOS | AA711: 23 2 71199. SERVICIOS DIVERSOS | AB711: 1700 | AC711: 1700 | AD711: 0 | AE711: 1700 | AF711: 1700 | AG711: 0 | AH711: 1700 | AI711: 2026 | AJ711: 0 | AK711: 0 | AL711: 1700 | AM711: 0 | AN711: 0 | AO711: 0 | AP711: 0 | AQ711: 0 | AR711: 0 | AS711: 0 | AT711: 0 | AU711: 0 | AV711: CCP SIN SALDO | AW711: CCP DEVENGADO | AX711: GUARDIANÍA
A712: 46055 | B712: 02. FEB | C712: APROBADO | D712: UFAF | E712: 01. PIA 2026 | F712: 3000001.ACCIONES COMUNES | G712: 5000276.GESTION DEL PROGRAMA | H712: PASAJES Y VIATICOS | I712: NO RESTRINGIDA | J712: OFICINA NACIONAL | K712: UFAF | L712: - | M712: - | N712: - | O712: - | P712: 0000000281 | - | - | Q712: 00 | R712: 0000000281 | S712: CCMN-002213: CONTRATACION DEL SERVICIO DE TRANSPORTE AEREO PARA LA COMISION DEL PERSONAL DE LLAMKASUN PERU | T712: 0000000281. CCMN-002213: CONTRATACION DEL SERVICIO DE TRANSPORTE AEREO PARA LA COMISION DEL PERSONAL DE LLAMKASUN PERU | U712: 0014 | V712: UFAF | W712: 0014. UFAF | X712: 5-23. BIENES Y SERVICIOS | Y712: 23 2 1 2 1 | Z712: PASAJES Y GASTOS DE TRANSPORTE | AA712: 23 2 1 2 1. PASAJES Y GASTOS DE TRANSPORTE | AB712: 12000 | AC712: 12000 | AD712: 0 | AE712: 0 | AF712: 0 | AG712: 12000 | AH712: 0 | AI712: 2026 | AJ712: 0 | AK712: 0 | AL712: 0 | AM712: 0 | AN712: 0 | AO712: 0 | AP712: 0 | AQ712: 0 | AR712: 0 | AS712: 0 | AT712: 0 | AU712: 0 | AV712: CCP SIN SALDO | AW712: CCP POR DEVENGAR | AX712: -
A713: 46055 | B713: 02. FEB | C713: APROBADO | D713: UFAF | E713: 01. PIA 2026 | F713: 3000001.ACCIONES COMUNES | G713: 5000276.GESTION DEL PROGRAMA | H713: PASAJES Y VIATICOS | I713: NO RESTRINGIDA | J713: OFICINA NACIONAL | K713: UFAF | L713: 0000002297 | M713: 0001056 | N713: 31/07/2026 | O713: 20341841357 | P713: 0000000282 | 0001056 | LATAM AIRLINES PERU S.A. | Q713: 00 | R713: 0000000282 | S713: CCMN-002214: CONTRATACION DEL SERVICIO DE TRANSPORTE AEREO PARA LA COMISION DEL PERSONAL DE LLAMKASUN PERU | T713: 0000000282. CCMN-002214: CONTRATACION DEL SERVICIO DE TRANSPORTE AEREO PARA LA COMISION DEL PERSONAL DE LLAMKASUN PERU | U713: 0014 | V713: UFAF | W713: 0014. UFAF | X713: 5-23. BIENES Y SERVICIOS | Y713: 23 2 1 2 1 | Z713: PASAJES Y GASTOS DE TRANSPORTE | AA713: 23 2 1 2 1. PASAJES Y GASTOS DE TRANSPORTE | AB713: 10500 | AC713: 10500 | AD713: 0 | AE713: 1126.65 | AF713: 0 | AG713: 10500 | AH713: 0 | AI713: 2026 | AJ713: 0 | AK713: 0 | AL713: 0 | AM713: 0 | AN713: 0 | AO713: 0 | AP713: 0 | AQ713: 0 | AR713: 0 | AS713: 0 | AT713: 0 | AU713: 0 | AV713: CCP SIN SALDO | AW713: CCP POR DEVENGAR | AX713: -
A714: 46055 | B714: 02. FEB | C714: APROBADO | D714: UFAF | E714: 01. PIA 2026 | F714: 3000001.ACCIONES COMUNES | G714: 5000276.GESTION DEL PROGRAMA | H714: PASAJES Y VIATICOS | I714: NO RESTRINGIDA | J714: OFICINA NACIONAL | K714: UFAF | L714: - | M714: - | N714: - | O714: - | P714: 0000000283 | - | - | Q714: 00 | R714: 0000000283 | S714: CCMN-002215: CONTRATACION DEL SERVICIO DE TRANSPORTE AEREO PARA LA COMISION DEL PERSONAL DE LLAMKASUN PERU | T714: 0000000283. CCMN-002215: CONTRATACION DEL SERVICIO DE TRANSPORTE AEREO PARA LA COMISION DEL PERSONAL DE LLAMKASUN PERU | U714: 0014 | V714: UFAF | W714: 0014. UFAF | X714: 5-23. BIENES Y SERVICIOS | Y714: 23 2 1 2 1 | Z714: PASAJES Y GASTOS DE TRANSPORTE | AA714: 23 2 1 2 1. PASAJES Y GASTOS DE TRANSPORTE | AB714: 3000 | AC714: 3000 | AD714: 0 | AE714: 0 | AF714: 0 | AG714: 3000 | AH714: 0 | AI714: 2026 | AJ714: 0 | AK714: 0 | AL714: 0 | AM714: 0 | AN714: 0 | AO714: 0 | AP714: 0 | AQ714: 0 | AR714: 0 | AS714: 0 | AT714: 0 | AU714: 0 | AV714: CCP SIN SALDO | AW714: CCP POR DEVENGAR | AX714: -
A715: 46055 | B715: 02. FEB | C715: APROBADO | D715: UFAF | E715: 01. PIA 2026 | F715: 3000001.ACCIONES COMUNES | G715: 5000276.GESTION DEL PROGRAMA | H715: PASAJES Y VIATICOS | I715: NO RESTRINGIDA | J715: OFICINA NACIONAL | K715: UFAF | L715: - | M715: - | N715: - | O715: - | P715: 0000000284 | - | - | Q715: 00 | R715: 0000000284 | S715: CCMN-002216: CONTRATACION DEL SERVICIO DE TRANSPORTE AEREO PARA LA COMISION DEL PERSONAL DE LLAMKASUN PERU | T715: 0000000284. CCMN-002216: CONTRATACION DEL SERVICIO DE TRANSPORTE AEREO PARA LA COMISION DEL PERSONAL DE LLAMKASUN PERU | U715: 0014 | V715: UFAF | W715: 0014. UFAF | X715: 5-23. BIENES Y SERVICIOS | Y715: 23 2 1 2 1 | Z715: PASAJES Y GASTOS DE TRANSPORTE | AA715: 23 2 1 2 1. PASAJES Y GASTOS DE TRANSPORTE | AB715: 4600 | AC715: 4600 | AD715: 0 | AE715: 0 | AF715: 0 | AG715: 4600 | AH715: 0 | AI715: 2026 | AJ715: 0 | AK715: 0 | AL715: 0 | AM715: 0 | AN715: 0 | AO715: 0 | AP715: 0 | AQ715: 0 | AR715: 0 | AS715: 0 | AT715: 0 | AU715: 0 | AV715: CCP SIN SALDO | AW715: CCP POR DEVENGAR | AX715: -
A716: 46055 | B716: 02. FEB | C716: APROBADO | D716: UFAF | E716: 01. PIA 2026 | F716: 3000001.ACCIONES COMUNES | G716: 5000276.GESTION DEL PROGRAMA | H716: LOCADORES | I716: NO RESTRINGIDA | J716: OFICINA NACIONAL | K716: UFAF | L716: 0000000251 | M716: 0000236 | N716: 02/02/2026 | O716: 10762008055 | P716: 0000000286 | 0000236 | ESPINOZA SANTANA EDWIN MARTIN | Q716: 00 | R716: 0000000286 | S716: CCMN-002219: SERVICIO DE INDAGACION DE MERCADO Y ELABORACION DE EXPEDIENTES DE BIENES Y SERVICIOS PARA ADJUDICACI | T716: 0000000286. CCMN-002219: SERVICIO DE INDAGACION DE MERCADO Y ELABORACION DE EXPEDIENTES DE BIENES Y SERVICIOS PARA ADJUDICACI | U716: 0014 | V716: UFAF | W716: 0014. UFAF | X716: 5-23. BIENES Y SERVICIOS | Y716: 23 2 9 1 1 | Z716: LOCACIÓN DE SERVICIOS REALIZADOS POR PERSONA NATURAL | AA716: 23 2 9 1 1. LOCACIÓN DE SERVICIOS REALIZADOS POR PERSONA NATURAL | AB716: 19500 | AC716: 19500 | AD716: 0 | AE716: 19500 | AF716: 19500 | AG716: 0 | AH716: 19500 | AI716: 2026 | AJ716: 0 | AK716: 6500 | AL716: 6500 | AM716: 6500 | AN716: 0 | AO716: 0 | AP716: 0 | AQ716: 0 | AR716: 0 | AS716: 0 | AT716: 0 | AU716: 0 | AV716: CCP SIN SALDO | AW716: CCP DEVENGADO | AX716: LOCADOR
A717: 46055 | B717: 02. FEB | C717: APROBADO | D717: UFAF | E717: 01. PIA 2026 | F717: 3000001.ACCIONES COMUNES | G717: 5000276.GESTION DEL PROGRAMA | H717: LOCADORES | I717: NO RESTRINGIDA | J717: OFICINA NACIONAL | K717: UFAF | L717: 0000000249 | M717: 0000229 | N717: 02/02/2026 | O717: 10724605198 | P717: 0000000287 | 0000229 | PALOMINO TAVARA AIRTON ESTUARDO | Q717: 00 | R717: 0000000287 | S717: CCMN-002220: SERVICIO ANALISIS DE INFORMACION CONTABLE FINANCIERA PARA LA COORDINACION FUNCIONAL DE CONTABILIDAD | T717: 0000000287. CCMN-002220: SERVICIO ANALISIS DE INFORMACION CONTABLE FINANCIERA PARA LA COORDINACION FUNCIONAL DE CONTABILIDAD | U717: 0014 | V717: UFAF | W717: 0014. UFAF | X717: 5-23. BIENES Y SERVICIOS | Y717: 23 2 9 1 1 | Z717: LOCACIÓN DE SERVICIOS REALIZADOS POR PERSONA NATURAL | AA717: 23 2 9 1 1. LOCACIÓN DE SERVICIOS REALIZADOS POR PERSONA NATURAL | AB717: 19500 | AC717: 19500 | AD717: 0 | AE717: 19500 | AF717: 19500 | AG717: 0 | AH717: 19500 | AI717: 2026 | AJ717: 0 | AK717: 6500 | AL717: 6500 | AM717: 6500 | AN717: 0 | AO717: 0 | AP717: 0 | AQ717: 0 | AR717: 0 | AS717: 0 | AT717: 0 | AU717: 0 | AV717: CCP SIN SALDO | AW717: CCP DEVENGADO | AX717: LOCADOR
A718: 46055 | B718: 02. FEB | C718: APROBADO | D718: UFAF | E718: 01. PIA 2026 | F718: 3000001.ACCIONES COMUNES | G718: 5000276.GESTION DEL PROGRAMA | H718: LOCADORES | I718: NO RESTRINGIDA | J718: OFICINA NACIONAL | K718: UFAF | L718: 0000000255 | M718: 0000238 | N718: 02/02/2026 | O718: 10420952410 | P718: 0000000288 | 0000238 | ZAVALA MODESTO JOSE LUIS | Q718: 00 | R718: 0000000288 | S718: CCMN-002221: SERVICIO DE GESTION DE REQUERIMIENTOS DE CONTRATOS MENORES O IGUALES A 8 UIT | T718: 0000000288. CCMN-002221: SERVICIO DE GESTION DE REQUERIMIENTOS DE CONTRATOS MENORES O IGUALES A 8 UIT | U718: 0014 | V718: UFAF | W718: 0014. UFAF | X718: 5-23. BIENES Y SERVICIOS | Y718: 23 2 9 1 1 | Z718: LOCACIÓN DE SERVICIOS REALIZADOS POR PERSONA NATURAL | AA718: 23 2 9 1 1. LOCACIÓN DE SERVICIOS REALIZADOS POR PERSONA NATURAL | AB718: 30000 | AC718: 30000 | AD718: 0 | AE718: 30000 | AF718: 30000 | AG718: 0 | AH718: 30000 | AI718: 2026 | AJ718: 0 | AK718: 10000 | AL718: 10000 | AM718: 10000 | AN718: 0 | AO718: 0 | AP718: 0 | AQ718: 0 | AR718: 0 | AS718: 0 | AT718: 0 | AU718: 0 | AV718: CCP SIN SALDO | AW718: CCP DEVENGADO | AX718: LOCADOR
A719: 46055 | B719: 02. FEB | C719: APROBADO | D719: UFAF | E719: 01. PIA 2026 | F719: 3000001.ACCIONES COMUNES | G719: 5000276.GESTION DEL PROGRAMA | H719: SERVICIO DE NUBE | I719: NO RESTRINGIDA | J719: OFICINA NACIONAL | K719: UFAF | L719: 0000000307 | M719: 0000247 | N719: 03/02/2026 | O719: 20492511146 | P719: 0000000289 | 0000247 | AMERICA TELECOMUNICACIONES, SOLUCIONES E INFORMATICA S.A.C. - AMERICA TSI S.A.C. | Q719: 00 | R719: 0000000289 | S719: CCMN-002178: CONTRATACION DEL SERVICIO DE TELEVISION POR CABLE DIGITAL PARA LA OFICINA NACIONAL DEL PROGRAMA DE E | T719: 0000000289. CCMN-002178: CONTRATACION DEL SERVICIO DE TELEVISION POR CABLE DIGITAL PARA LA OFICINA NACIONAL DEL PROGRAMA DE E | U719: 0014 | V719: UFAF | W719: 0014. UFAF | X719: 5-23. BIENES Y SERVICIOS | Y719: 23 2 2 399 | Z719: OTROS SERVICIOS DE COMUNICACION | AA719: 23 2 2 399. OTROS SERVICIOS DE COMUNICACION | AB719: 810 | AC719: 810 | AD719: 0 | AE719: 810 | AF719: 810 | AG719: 0 | AH719: 810 | AI719: 2026 | AJ719: 0 | AK719: 540 | AL719: 270 | AM719: 0 | AN719: 0 | AO719: 0 | AP719: 0 | AQ719: 0 | AR719: 0 | AS719: 0 | AT719: 0 | AU719: 0 | AV719: CCP SIN SALDO | AW719: CCP DEVENGADO | AX719: -
A720: 46055 | B720: 02. FEB | C720: APROBADO | D720: UFAF | E720: 01. PIA 2026 | F720: 3000001.ACCIONES COMUNES | G720: 5000276.GESTION DEL PROGRAMA | H720: LOCADORES | I720: NO RESTRINGIDA | J720: OFICINA NACIONAL | K720: UFAF | L720: 0000000259 | M720: 0000233 | N720: 02/02/2026 | O720: 10701656780 | P720: 0000000290 | 0000233 | CANCHAPOMA HILARIO TANIA ZULEYKA | Q720: 00 | R720: 0000000290 | S720: CCMN-002222: SERVICIO DE FISCALIZACION DE DOCUMENTOS DE CONTRATOS MENORES Y REGISTRO DE INFORMACION EN EL SIRICC | T720: 0000000290. CCMN-002222: SERVICIO DE FISCALIZACION DE DOCUMENTOS DE CONTRATOS MENORES Y REGISTRO DE INFORMACION EN EL SIRICC | U720: 0014 | V720: UFAF | W720: 0014. UFAF | X720: 5-23. BIENES Y SERVICIOS | Y720: 23 2 9 1 1 | Z720: LOCACIÓN DE SERVICIOS REALIZADOS POR PERSONA NATURAL | AA720: 23 2 9 1 1. LOCACIÓN DE SERVICIOS REALIZADOS POR PERSONA NATURAL | AB720: 19500 | AC720: 19500 | AD720: 0 | AE720: 19500 | AF720: 19500 | AG720: 0 | AH720: 19500 | AI720: 2026 | AJ720: 0 | AK720: 6500 | AL720: 6500 | AM720: 6500 | AN720: 0 | AO720: 0 | AP720: 0 | AQ720: 0 | AR720: 0 | AS720: 0 | AT720: 0 | AU720: 0 | AV720: CCP SIN SALDO | AW720: CCP DEVENGADO | AX720: LOCADOR
A721: 46055 | B721: 02. FEB | C721: APROBADO | D721: UFAF | E721: 01. PIA 2026 | F721: 3000001.ACCIONES COMUNES | G721: 5000276.GESTION DEL PROGRAMA | H721: LOCADORES | I721: NO RESTRINGIDA | J721: OFICINA NACIONAL | K721: UFAF | L721: 0000000250 | M721: 0000230 | N721: 02/02/2026 | O721: 10748074959 | P721: 0000000291 | 0000230 | PERALTA SUPANTA GIANFRANCO ANTONIO | Q721: 00 | R721: 0000000291 | S721: CCMN-002223: SERVICIO ANALISIS ADMINISTRATIVO FINANCIERO Y CONTABLE PARA COORDINACION FUNCIONAL DE CONTABILIDAD | T721: 0000000291. CCMN-002223: SERVICIO ANALISIS ADMINISTRATIVO FINANCIERO Y CONTABLE PARA COORDINACION FUNCIONAL DE CONTABILIDAD | U721: 0014 | V721: UFAF | W721: 0014. UFAF | X721: 5-23. BIENES Y SERVICIOS | Y721: 23 2 9 1 1 | Z721: LOCACIÓN DE SERVICIOS REALIZADOS POR PERSONA NATURAL | AA721: 23 2 9 1 1. LOCACIÓN DE SERVICIOS REALIZADOS POR PERSONA NATURAL | AB721: 19500 | AC721: 19500 | AD721: 0 | AE721: 19500 | AF721: 19500 | AG721: 0 | AH721: 19500 | AI721: 2026 | AJ721: 0 | AK721: 6500 | AL721: 6500 | AM721: 6500 | AN721: 0 | AO721: 0 | AP721: 0 | AQ721: 0 | AR721: 0 | AS721: 0 | AT721: 0 | AU721: 0 | AV721: CCP SIN SALDO | AW721: CCP DEVENGADO | AX721: LOCADOR
A722: 46055 | B722: 02. FEB | C722: APROBADO | D722: UFAF | E722: 01. PIA 2026 | F722: 3000001.ACCIONES COMUNES | G722: 5000276.GESTION DEL PROGRAMA | H722: LOCADORES | I722: NO RESTRINGIDA | J722: OFICINA NACIONAL | K722: UFAF | L722: 0000000254 | M722: 0000237 | N722: 02/02/2026 | O722: 10709908249 | P722: 0000000292 | 0000237 | RIVERA CUBA LINCOL JEAMPIER | Q722: 00 | R722: 0000000292 | S722: CCMN-002224: SERVICIO DE ADQUISICIONES POR ACUERDO MARCO Y ELABORACION DE EXPEDIENTE DE CONTRATOS MENORES | T722: 0000000292. CCMN-002224: SERVICIO DE ADQUISICIONES POR ACUERDO MARCO Y ELABORACION DE EXPEDIENTE DE CONTRATOS MENORES | U722: 0014 | V722: UFAF | W722: 0014. UFAF | X722: 5-23. BIENES Y SERVICIOS | Y722: 23 2 9 1 1 | Z722: LOCACIÓN DE SERVICIOS REALIZADOS POR PERSONA NATURAL | AA722: 23 2 9 1 1. LOCACIÓN DE SERVICIOS REALIZADOS POR PERSONA NATURAL | AB722: 19500 | AC722: 19500 | AD722: 0 | AE722: 19500 | AF722: 19500 | AG722: 0 | AH722: 19500 | AI722: 2026 | AJ722: 0 | AK722: 6500 | AL722: 6500 | AM722: 6500 | AN722: 0 | AO722: 0 | AP722: 0 | AQ722: 0 | AR722: 0 | AS722: 0 | AT722: 0 | AU722: 0 | AV722: CCP SIN SALDO | AW722: CCP DEVENGADO | AX722: LOCADOR
A723: 46055 | B723: 02. FEB | C723: APROBADO | D723: UFAF | E723: 01. PIA 2026 | F723: 3000001.ACCIONES COMUNES | G723: 5000276.GESTION DEL PROGRAMA | H723: LOCADORES | I723: NO RESTRINGIDA | J723: UNIDADES TERRITORIALES | K723: UT ICA - AYACUCHO SUR | L723: 0000000264 | M723: 0000243 | N723: 02/02/2026 | O723: 10800006665 | P723: 0000000293 | 0000243 | SUINEY RODRIGUEZ ELSA SHERLY | Q723: 00 | R723: 0000000293 | S723: CCMN-002225: SERVICIO DE ORGANIZACION, FOLIACION E INVENTARIO DEL ACERVO DOCUMENTAL PARA LA UNIDAD TERRITORIAL IC | T723: 0000000293. CCMN-002225: SERVICIO DE ORGANIZACION, FOLIACION E INVENTARIO DEL ACERVO DOCUMENTAL PARA LA UNIDAD TERRITORIAL IC | U723: 0010 | V723: UT ICA - AYACUCHO SUR | W723: 0010. UT ICA - AYACUCHO SUR | X723: 5-23. BIENES Y SERVICIOS | Y723: 23 2 9 1 1 | Z723: LOCACIÓN DE SERVICIOS REALIZADOS POR PERSONA NATURAL | AA723: 23 2 9 1 1. LOCACIÓN DE SERVICIOS REALIZADOS POR PERSONA NATURAL | AB723: 5000 | AC723: 5000 | AD723: 0 | AE723: 5000 | AF723: 5000 | AG723: 0 | AH723: 5000 | AI723: 2026 | AJ723: 0 | AK723: 2500 | AL723: 2500 | AM723: 0 | AN723: 0 | AO723: 0 | AP723: 0 | AQ723: 0 | AR723: 0 | AS723: 0 | AT723: 0 | AU723: 0 | AV723: CCP SIN SALDO | AW723: CCP DEVENGADO | AX723: ADMINISTRATIVO / ARCHIVO
A724: 46055 | B724: 02. FEB | C724: APROBADO | D724: UFSMI | E724: 01. PIA 2026 | F724: 3000194.EMPLEO TEMPORAL GENERADO | G724: 5006296.SEGUIMIENTO DE LOS PROYECTOS Y ACTIVIDADES EN EJECUCION | H724: LOCADORES | I724: NO RESTRINGIDA | J724: OFICINA NACIONAL | K724: UFSMI | L724: 0000000256 | M724: 0000239 | N724: 02/02/2026 | O724: 10182169922 | P724: 0000000294 | 0000239 | MELGAR OCAMPOS FREDY RONALD | Q724: 00 | R724: 0000000294 | S724: CCMN-002226: SERVICIO DE SUPERVISION, SEGUIMIENTO Y MONITOREO A LA EJECUCION DE PI Y AII EN LAS UT AMZONAS, HUANU | T724: 0000000294. CCMN-002226: SERVICIO DE SUPERVISION, SEGUIMIENTO Y MONITOREO A LA EJECUCION DE PI Y AII EN LAS UT AMZONAS, HUANU | U724: 0056 | V724: UFSMI | W724: 0056. UFSMI | X724: 5-23. BIENES Y SERVICIOS | Y724: 23 2 9 1 1 | Z724: LOCACIÓN DE SERVICIOS REALIZADOS POR PERSONA NATURAL | AA724: 23 2 9 1 1. LOCACIÓN DE SERVICIOS REALIZADOS POR PERSONA NATURAL | AB724: 24000 | AC724: 24000 | AD724: 0 | AE724: 24000 | AF724: 24000 | AG724: 0 | AH724: 24000 | AI724: 2026 | AJ724: 0 | AK724: 0 | AL724: 8000 | AM724: 16000 | AN724: 0 | AO724: 0 | AP724: 0 | AQ724: 0 | AR724: 0 | AS724: 0 | AT724: 0 | AU724: 0 | AV724: CCP SIN SALDO | AW724: CCP DEVENGADO | AX724: LOCADOR
A725: 46055 | B725: 02. FEB | C725: APROBADO | D725: UFAF | E725: 01. PIA 2026 | F725: 3000001.ACCIONES COMUNES | G725: 5000276.GESTION DEL PROGRAMA | H725: SERVICIOS DE LUZ, AGUA, INTERNET, TELF. FJA | I725: RESTRINGIDA | J725: UNIDADES TERRITORIALES | K725: UT LA LIBERTAD - ANCASH NOROESTE | L725: 0000000328 | M725: 0000268 | N725: 04/02/2026 | O725: 20481622582 | P725: 0000000295 | 0000268 | RELUX REPRESENTACIONES S.A.C. | Q725: 00 | R725: 0000000295 | S725: CCMN-002227: SERVICIO DE INTERNET PARA LA OFICINA DE LA LIBERTAD - ANCASH NOROESTE | T725: 0000000295. CCMN-002227: SERVICIO DE INTERNET PARA LA OFICINA DE LA LIBERTAD - ANCASH NOROESTE | U725: 0012 | V725: UT LA LIBERTAD - ANCASH NOROESTE | W725: 0012. UT LA LIBERTAD - ANCASH NOROESTE | X725: 5-23. BIENES Y SERVICIOS | Y725: 23 2 2 2 3 | Z725: SERVICIO DE INTERNET | AA725: 23 2 2 2 3. SERVICIO DE INTERNET | AB725: 5850 | AC725: 5850 | AD725: 0 | AE725: 5850 | AF725: 3900 | AG725: 1950 | AH725: 3900 | AI725: 2026 | AJ725: 0 | AK725: 1300 | AL725: 650 | AM725: 650 | AN725: 650 | AO725: 650 | AP725: 0 | AQ725: 0 | AR725: 0 | AS725: 0 | AT725: 0 | AU725: 0 | AV725: CCP SIN SALDO | AW725: CCP POR DEVENGAR | AX725: -
A726: 46055 | B726: 02. FEB | C726: APROBADO | D726: UFAF | E726: 01. PIA 2026 | F726: 3000001.ACCIONES COMUNES | G726: 5000276.GESTION DEL PROGRAMA | H726: LOCADORES | I726: NO RESTRINGIDA | J726: OFICINA NACIONAL | K726: UFAF | L726: 0000000262 | M726: 0000242 | N726: 02/02/2026 | O726: 10434590502 | P726: 0000000296 | 0000242 | JAYO BALLESTEROS JESSICA BENJAMINA | Q726: 00 | R726: 0000000296 | S726: CCMN-002228: SERVICIO DE CLASIFICACION, ORDENAMIENTO E INVENTARIO DOCUMENTARIO PARA ARCHIVO CENTRAL - UFAF | T726: 0000000296. CCMN-002228: SERVICIO DE CLASIFICACION, ORDENAMIENTO E INVENTARIO DOCUMENTARIO PARA ARCHIVO CENTRAL - UFAF | U726: 0014 | V726: UFAF | W726: 0014. UFAF | X726: 5-23. BIENES Y SERVICIOS | Y726: 23 2 9 1 1 | Z726: LOCACIÓN DE SERVICIOS REALIZADOS POR PERSONA NATURAL | AA726: 23 2 9 1 1. LOCACIÓN DE SERVICIOS REALIZADOS POR PERSONA NATURAL | AB726: 7500 | AC726: 7500 | AD726: 0 | AE726: 7500 | AF726: 7500 | AG726: 0 | AH726: 7500 | AI726: 2026 | AJ726: 0 | AK726: 2500 | AL726: 2500 | AM726: 0 | AN726: 2500 | AO726: 0 | AP726: 0 | AQ726: 0 | AR726: 0 | AS726: 0 | AT726: 0 | AU726: 0 | AV726: CCP SIN SALDO | AW726: CCP DEVENGADO | AX726: LOCADOR
A727: 46055 | B727: 02. FEB | C727: APROBADO | D727: UFAF | E727: 01. PIA 2026 | F727: 3000001.ACCIONES COMUNES | G727: 5000276.GESTION DEL PROGRAMA | H727: LOCADORES | I727: NO RESTRINGIDA | J727: OFICINA NACIONAL | K727: UFAF | L727: 0000000260 | M727: 0000240 | N727: 02/02/2026 | O727: 10739875418 | P727: 0000000297 | 0000240 | QUISPE DE LA CRUZ ADRIANA ISABEL | Q727: 00 | R727: 0000000297 | S727: CCMN-002229: SERVICIO ESPECIALIZADO EN EJECUCION CONTRACTUAL - CFASG | T727: 0000000297. CCMN-002229: SERVICIO ESPECIALIZADO EN EJECUCION CONTRACTUAL - CFASG | U727: 0014 | V727: UFAF | W727: 0014. UFAF | X727: 5-23. BIENES Y SERVICIOS | Y727: 23 2 9 1 1 | Z727: LOCACIÓN DE SERVICIOS REALIZADOS POR PERSONA NATURAL | AA727: 23 2 9 1 1. LOCACIÓN DE SERVICIOS REALIZADOS POR PERSONA NATURAL | AB727: 21000 | AC727: 21000 | AD727: 0 | AE727: 21000 | AF727: 21000 | AG727: 0 | AH727: 21000 | AI727: 2026 | AJ727: 0 | AK727: 7000 | AL727: 7000 | AM727: 7000 | AN727: 0 | AO727: 0 | AP727: 0 | AQ727: 0 | AR727: 0 | AS727: 0 | AT727: 0 | AU727: 0 | AV727: CCP SIN SALDO | AW727: CCP DEVENGADO | AX727: LOCADOR
... A810: 46064 | B810: 02. FEB | C810: APROBADO | D810: UFGI | E810: 01. PIA 2026 | F810: 3000194.EMPLEO TEMPORAL GENERADO | G810: 5006295.PROMOCION DE MODALIDADES DE INTERVENCION DEL PROGRAMA PARA DESARROLLO DE PROYECTOS Y ACTIVIDADES INTENSIVOS EN MANO DE OBRA NO CALIFICADA | H810: LOCADORES | I810: NO RESTRINGIDA | J810: UNIDADES TERRITORIALES | K810: UT HUANUCO - PASCO | L810: 0000000430 | M810: 0000314 | N810: 11/02/2026 | O810: 10439104932 | P810: 0000000381 | 0000314 | RUIZ ANGULO WILMER ALEXANDER | Q810: 00 | R810: 0000000381 | S810: CCMN-002308: CONTRATACION DEL SERVICIO PARA LA REVISION Y REGISTRO DE EXPEDIENTES TECNICOS DE PROYECTOS DE INVERS | T810: 0000000381. CCMN-002308: CONTRATACION DEL SERVICIO PARA LA REVISION Y REGISTRO DE EXPEDIENTES TECNICOS DE PROYECTOS DE INVERS | U810: 0037 | V810: UT HUANUCO - PASCO | W810: 0037. UT HUANUCO - PASCO | X810: 5-23. BIENES Y SERVICIOS | Y810: 23 2 9 1 1 | Z810: LOCACIÓN DE SERVICIOS REALIZADOS POR PERSONA NATURAL | AA810: 23 2 9 1 1. LOCACIÓN DE SERVICIOS REALIZADOS POR PERSONA NATURAL | AB810: 6000 | AC810: 6000 | AD810: 0 | AE810: 6000 | AF810: 4950 | AG810: 1050 | AH810: 4950 | AI810: 2026 | AJ810: 0 | AK810: 0 | AL810: 1950 | AM810: 3000 | AN810: 0 | AO810: 0 | AP810: 0 | AQ810: 0 | AR810: 0 | AS810: 0 | AT810: 0 | AU810: 0 | AV810: CCP SIN SALDO | AW810: CCP POR DEVENGAR | AX810: REVISORES - AII
A811: 46064 | B811: 02. FEB | C811: APROBADO | D811: UFAF | E811: 01. PIA 2026 | F811: 3000001.ACCIONES COMUNES | G811: 5000276.GESTION DEL PROGRAMA | H811: COMBUSTIBLE | I811: NO RESTRINGIDA | J811: UNIDADES TERRITORIALES | K811: UT PUNO | L811: - | M811: - | N811: - | O811: - | P811: 0000000382 | - | - | Q811: 00 | R811: 0000000382 | S811: Contrato-CONTRATO N005-2025: ADQUISICION DE COMBUSTIBLE PARA LA CAMIONETA ASIGNADA A LA UT PUNO | T811: 0000000382. Contrato-CONTRATO N005-2025: ADQUISICION DE COMBUSTIBLE PARA LA CAMIONETA ASIGNADA A LA UT PUNO | U811: 0026 | V811: UT PUNO | W811: 0026. UT PUNO | X811: 5-23. BIENES Y SERVICIOS | Y811: 23 1 3 1 1 | Z811: COMBUSTIBLES Y CARBURANTES | AA811: 23 1 3 1 1. COMBUSTIBLES Y CARBURANTES | AB811: 5328 | AC811: 5328 | AD811: 0 | AE811: 0 | AF811: 0 | AG811: 5328 | AH811: 0 | AI811: 2026 | AJ811: 0 | AK811: 0 | AL811: 0 | AM811: 0 | AN811: 0 | AO811: 0 | AP811: 0 | AQ811: 0 | AR811: 0 | AS811: 0 | AT811: 0 | AU811: 0 | AV811: CCP SIN SALDO | AW811: CCP POR DEVENGAR | AX811: -
A812: 46064 | B812: 02. FEB | C812: APROBADO | D812: UFGI | E812: 01. PIA 2026 | F812: 3000194.EMPLEO TEMPORAL GENERADO | G812: 5006295.PROMOCION DE MODALIDADES DE INTERVENCION DEL PROGRAMA PARA DESARROLLO DE PROYECTOS Y ACTIVIDADES INTENSIVOS EN MANO DE OBRA NO CALIFICADA | H812: LOCADORES | I812: NO RESTRINGIDA | J812: UNIDADES TERRITORIALES | K812: UT ANCASH | L812: 0000000445 | M812: 0000317 | N812: 11/02/2026 | O812: 10438551005 | P812: 0000000383 | 0000317 | COLQUE VALENTIN MARIA ISABEL | Q812: 00 | R812: 0000000383 | S812: CCMN-002309: SERVICIO PARA LA REVISION Y REGISTRO DE EXPEDIENTES TECNICOS DE PROYECTOS DE INVERSION INTENSIVOS EN | T812: 0000000383. CCMN-002309: SERVICIO PARA LA REVISION Y REGISTRO DE EXPEDIENTES TECNICOS DE PROYECTOS DE INVERSION INTENSIVOS EN | U812: 0032 | V812: UT ANCASH | W812: 0032. UT ANCASH | X812: 5-23. BIENES Y SERVICIOS | Y812: 23 2 9 1 1 | Z812: LOCACIÓN DE SERVICIOS REALIZADOS POR PERSONA NATURAL | AA812: 23 2 9 1 1. LOCACIÓN DE SERVICIOS REALIZADOS POR PERSONA NATURAL | AB812: 6000 | AC812: 6000 | AD812: 0 | AE812: 6000 | AF812: 6000 | AG812: 0 | AH812: 6000 | AI812: 2026 | AJ812: 0 | AK812: 0 | AL812: 1950 | AM812: 4050 | AN812: 0 | AO812: 0 | AP812: 0 | AQ812: 0 | AR812: 0 | AS812: 0 | AT812: 0 | AU812: 0 | AV812: CCP SIN SALDO | AW812: CCP DEVENGADO | AX812: REVISORES - AII
A813: 46064 | B813: 02. FEB | C813: APROBADO | D813: UFAF | E813: 01. PIA 2026 | F813: 3000001.ACCIONES COMUNES | G813: 5000276.GESTION DEL PROGRAMA | H813: ALQUILER DE LOCAL | I813: NO RESTRINGIDA | J813: UNIDADES TERRITORIALES | K813: UT APURIMAC | L813: 0000001153 | M813: 0000508 | N813: 23/03/2026 | O813: 10310048912 | P813: 0000000384 | 0000508 | CHIRINOS LANTARON DE GUZMAN ESTHER | Q813: 00 | R813: 0000000384 | S813: CCMN-002276: SERVICIO DE ALQUILER DE INMUEBLE PARA LA UNIDAD TERRITORIAL APURIMAC | T813: 0000000384. CCMN-002276: SERVICIO DE ALQUILER DE INMUEBLE PARA LA UNIDAD TERRITORIAL APURIMAC | U813: 0003 | V813: UT APURIMAC | W813: 0003. UT APURIMAC | X813: 5-23. BIENES Y SERVICIOS | Y813: 23 2 5 1 1 | Z813: DE EDIFICIOS Y ESTRUCTURAS | AA813: 23 2 5 1 1. DE EDIFICIOS Y ESTRUCTURAS | AB813: 40000 | AC813: 40000 | AD813: 0 | AE813: 40000 | AF813: 16000 | AG813: 24000 | AH813: 12000 | AI813: 2026 | AJ813: 0 | AK813: 0 | AL813: 0 | AM813: 4000 | AN813: 4000 | AO813: 4000 | AP813: 4000 | AQ813: 0 | AR813: 0 | AS813: 0 | AT813: 0 | AU813: 0 | AV813: CCP SIN SALDO | AW813: CCP POR DEVENGAR | AX813: -
A814: 46064 | B814: 02. FEB | C814: APROBADO | D814: UFAF | E814: 01. PIA 2026 | F814: 3000001.ACCIONES COMUNES | G814: 5000276.GESTION DEL PROGRAMA | H814: ALQUILER DE LOCAL | I814: NO RESTRINGIDA | J814: UNIDADES TERRITORIALES | K814: UT APURIMAC | L814: 0000001148 | M814: 0000504 | N814: 20/03/2026 | O814: 10310048912 | P814: 0000000385 | 0000504 | CHIRINOS LANTARON DE GUZMAN ESTHER | Q814: 00 | R814: 0000000385 | S814: CCMN-002307: GARANTIA DE ALQUILER DE INMUEBLE DE LA UT APURIMAC | T814: 0000000385. CCMN-002307: GARANTIA DE ALQUILER DE INMUEBLE DE LA UT APURIMAC | U814: 0003 | V814: UT APURIMAC | W814: 0003. UT APURIMAC | X814: 5-23. BIENES Y SERVICIOS | Y814: 23 2 5 1 1 | Z814: DE EDIFICIOS Y ESTRUCTURAS | AA814: 23 2 5 1 1. DE EDIFICIOS Y ESTRUCTURAS | AB814: 4000 | AC814: 4000 | AD814: 0 | AE814: 4000 | AF814: 4000 | AG814: 0 | AH814: 4000 | AI814: 2026 | AJ814: 0 | AK814: 0 | AL814: 0 | AM814: 4000 | AN814: 0 | AO814: 0 | AP814: 0 | AQ814: 0 | AR814: 0 | AS814: 0 | AT814: 0 | AU814: 0 | AV814: CCP SIN SALDO | AW814: CCP DEVENGADO | AX814: -
A815: 46064 | B815: 02. FEB | C815: APROBADO | D815: UFGI | E815: 01. PIA 2026 | F815: 3000194.EMPLEO TEMPORAL GENERADO | G815: 5006295.PROMOCION DE MODALIDADES DE INTERVENCION DEL PROGRAMA PARA DESARROLLO DE PROYECTOS Y ACTIVIDADES INTENSIVOS EN MANO DE OBRA NO CALIFICADA | H815: LOCADORES | I815: NO RESTRINGIDA | J815: UNIDADES TERRITORIALES | K815: UT HUANCAVELICA | L815: 0000000456 | M815: 0000321 | N815: 12/02/2026 | O815: 10731178637 | P815: 0000000386 | 0000321 | DUEÑAS ARAUJO GIMMY NAZARIO | Q815: 00 | R815: 0000000386 | S815: CCMN-002310: SERVICIO PARA LA REVISION Y REGISTRO DE EXPEDIENTES TECNICOS DE PROYECTOS DE INVERSION INTENSIVOS | T815: 0000000386. CCMN-002310: SERVICIO PARA LA REVISION Y REGISTRO DE EXPEDIENTES TECNICOS DE PROYECTOS DE INVERSION INTENSIVOS | U815: 0036 | V815: UT HUANCAVELICA | W815: 0036. UT HUANCAVELICA | X815: 5-23. BIENES Y SERVICIOS | Y815: 23 2 9 1 1 | Z815: LOCACIÓN DE SERVICIOS REALIZADOS POR PERSONA NATURAL | AA815: 23 2 9 1 1. LOCACIÓN DE SERVICIOS REALIZADOS POR PERSONA NATURAL | AB815: 8080 | AC815: 8080 | AD815: 0 | AE815: 8080 | AF815: 7100 | AG815: 980 | AH815: 7100 | AI815: 2026 | AJ815: 0 | AK815: 0 | AL815: 1820 | AM815: 0 | AN815: 5280 | AO815: 0 | AP815: 0 | AQ815: 0 | AR815: 0 | AS815: 0 | AT815: 0 | AU815: 0 | AV815: CCP SIN SALDO | AW815: CCP POR DEVENGAR | AX815: REVISORES - AII
...
